Homework3/universal_shift_register/rtl/universal_shift_register.v
module universal_shift_register(
	input	wire		clk,
	input	wire		rst_n,
	input	wire	[1:0]	S,
	input	wire		sl_in,
	input	wire		sr_in,
	input	wire	[3:0]	p_din,
	output	reg	[3:0]	p_dout,	
	output	reg		sr_out,
	output	reg		sl_out
);

	always @(posedge clk or negedge rst_n) begin
		if(!rst_n) begin
			p_dout <= 4'b0;
		end
		else begin
			case(S)
				2'b00: begin
				 	p_dout <= p_dout;
				end
				2'b01: begin
					sr_out <= p_dout[0];
				 	p_dout <= {sr_in, p_dout[3:1]};
				end
				2'b10:	begin
					sl_out = p_dout[3];
					p_dout <= {p_dout[2:0], sl_in};
				end
				2'b11: 	begin
					p_dout <= p_din;
				end
			endcase
		end
	end	

endmodule

Homework3/universal_shift_register/tb/test_bench.v
module test_bench;

	reg		clk, rst_n;
	reg		sr_in, sl_in;
	reg	[1:0]	S;
	reg	[3:0]	p_din;
	wire	[3:0]	p_dout;
	wire		sl_out, sr_out;

	universal_shift_register DUT(.*);

	initial begin
		clk = 0;
		forever #25 clk = ~clk;
	end

	initial begin
		$dumpfile("wave.vcd");
		$dumpvars(0,test_bench);
		$display("===== Universal Shift Register Testbench =====");
		$monitor("\n===== Input value is %4b, Selection's value is %2b, New right value is %b, New left value is %b =====", p_din, S, sr_in, sl_in);
		$display("===== Initial Case: Reset value is Low =====");
		rst_n = 0;
		#1;
		check_result(4'b0000, p_dout);

		$display("===== Case: Reset value is High =====");
		rst_n = 1;
		p_din = 4'b0000; sr_in = 0; sl_in = 0; S = 2'b00;
		@(posedge clk);
		#1;
		check_result(4'b0000, p_dout);

		p_din = 4'b1111; sr_in = 0; sl_in = 0; S = 2'b00;
		@(posedge clk);
		#1;
		check_result(4'b0000, p_dout);
		
		p_din = 4'b1111; sr_in = 0; sl_in = 0; S = 2'b11;
		@(posedge clk);
		#1;
		check_result(4'b1111, p_dout);

		p_din = 4'b1111; sr_in = 0; sl_in = 0; S = 2'b10;
		@(posedge clk);
		#1;
		check_result(4'b1110, p_dout);
		check_shift(1'b1, sl_out);

		p_din = 4'b1111; sr_in = 0; sl_in = 0; S = 2'b01;
		@(posedge clk);
		#1;
		check_result(4'b0111, p_dout);
		check_shift(1'b1, sr_out);

		p_din = 4'b1001; sr_in = 0; sl_in = 0; S = 2'b11;
		@(posedge clk);
		#1;
		check_result(4'b1001, p_dout);

		sr_in = 0; sl_in = 1; S = 2'b10;
		@(posedge clk);
		#1;
		check_result(4'b0011, p_dout);
		check_shift(1'b1, sl_out);

		sr_in = 0; sl_in = 1; S = 2'b01;
		@(posedge clk);
		#1;
		check_result(4'b0001, p_dout);
		check_shift(1'b1, sr_out);

		#10;
		$finish;
	end

	task check_result;
		input	[3:0]	a;
		input	[3:0] 	b;
		if(a!=b) begin
			$display("===== t=%d FAILED, output does not match =====",$time);
			$display("===== t=%d Expected value is %b, Actual value is %b =====",$time, a, b);
		end
		else begin
			$display("===== t=%d PASSED SUCCESSFULLY =====",$time);
		end
	endtask

	task check_shift;
		input		c;
		input	 	d;
		if(c!=d) begin
			$display("===== t=%d FAILED, shift value does not match =====",$time);
			$display("===== t=%d Expected value is %b, Actual value is %b =====",$time, c, d);
		end
		else begin
			$display("===== t=%d PASSED SUCCESSFULLY =====",$time);
		end
	endtask
endmodule

Homework3/universal_shift_register/sim/wave.vcd
$date
	Thu Oct 09 22:23:03 2025
$end
$version
	Icarus Verilog
$end
$timescale
	1s
$end
$scope module test_bench $end
$var wire 1 ! sr_out $end
$var wire 1 " sl_out $end
$var wire 4 # p_dout [3:0] $end
$var reg 2 $ S [1:0] $end
$var reg 1 % clk $end
$var reg 4 & p_din [3:0] $end
$var reg 1 ' rst_n $end
$var reg 1 ( sl_in $end
$var reg 1 ) sr_in $end
$scope module DUT $end
$var wire 2 * S [1:0] $end
$var wire 1 % clk $end
$var wire 4 + p_din [3:0] $end
$var wire 1 ' rst_n $end
$var wire 1 ( sl_in $end
$var wire 1 ) sr_in $end
$var reg 4 , p_dout [3:0] $end
$var reg 1 " sl_out $end
$var reg 1 ! sr_out $end
$upscope $end
$scope task check_result $end
$var reg 4 - a [3:0] $end
$var reg 4 . b [3:0] $end
$upscope $end
$scope task check_shift $end
$var reg 1 / c $end
$var reg 1 0 d $end
$upscope $end
$upscope $end
$enddefinitions $end
#0
$dumpvars
x0
x/
bx .
bx -
b0 ,
bx +
bx *
x)
x(
0'
bx &
0%
bx $
b0 #
x"
x!
$end
#1
b0 $
b0 *
0(
0)
b0 &
b0 +
1'
b0 .
b0 -
#25
1%
#26
b1111 &
b1111 +
#50
0%
#75
1%
#76
b11 $
b11 *
#100
0%
#125
b1111 #
b1111 ,
1%
#126
b10 $
b10 *
b1111 .
b1111 -
#150
0%
#175
b1110 #
b1110 ,
1"
1%
#176
b1 $
b1 *
10
1/
b1110 .
b1110 -
#200
0%
#225
b111 #
b111 ,
0!
1%
#226
b11 $
b11 *
b1001 &
b1001 +
00
b111 .
b111 -
#250
0%
#275
b1001 #
b1001 ,
1%
#276
b10 $
b10 *
1(
b1001 .
b1001 -
#300
0%
#325
b11 #
b11 ,
1%
#326
b1 $
b1 *
10
b11 .
b11 -
#350
0%
#375
b1 #
b1 ,
1!
1%
#376
b1 .
b1 -
