Homework3/full_adder/rtl/full_adder.v
module full_adder(
	input	wire	a,
	input 	wire	b,
	input 	wire	cin,
	output	wire	gate_sum,
	output	wire	data_sum,
	output	reg	behav_sum,
	output	wire	gate_carry,
	output	wire	data_carry,
	output	reg	behav_carry
);

	wire data_carry_1, data_carry_2, data_sum_1;	
	wire gate_carry_1, gate_carry_2, gate_sum_1;
	reg behav_carry_1, behav_carry_2, behav_sum_1;
	
	//structural
	//half_adder_1
	xor(gate_sum_1, a, b);
	and(gate_carry_1, a, b);

	//half_adder_2
	and(gate_carry_2, gate_sum_1, cin);

	//full_adder
	xor(gate_sum, gate_sum_1, cin);
	or(gate_carry, gate_carry_1, gate_carry_2);
	
	//dataflow
	//half_adder_1
	assign data_sum_1 = a ^ b;
	assign data_carry_1 = a & b;

	//half_adder_2
	assign data_carry_2 = data_sum_1 & cin;

	//full_adder
	assign data_sum = data_sum_1 ^ cin;
	assign data_carry = data_carry_1 | data_carry_2;

	//combinational
	//half_adder_1
	always @(*) begin
		behav_carry_1 = a & b;
		behav_sum_1 = a ^ b;
	end

	//half_adder_2
	always @(*) begin
		behav_carry_2 = behav_sum_1 & cin;
	end

	//full_adder
	always @(*) begin
		behav_carry = behav_carry_2 | behav_carry_1;
		behav_sum = behav_sum_1 ^ cin;
	end

endmodule

Homework3/full_adder/tb/test_bench6.v
module test_bench6;

	reg	a, b, cin;
	wire 	gate_sum, data_sum, behav_sum;
	wire 	gate_carry, data_carry, behav_carry;

	full_adder DUT(.*);

	initial begin
		$dumpfile("wave.vcd");
		$dumpvars(0,test_bench6);
		$display("===== Full Adder Testbench =====");
		$display("===== A = 0, B = 0, Cin = 0 =====");
		a = 0; b = 0; cin = 0;
		if(gate_sum!=0 || data_sum!=0 || behav_sum!=0) begin
			$display("===== t=%d FAILED, value does not match =====", $time);
			$display("===== t=%d Expected value is %b, Actual gate_model value is %b, Actual dataflow value is %b, Actual behavioral_model value is %b =====", $time, 0, gate_sum, data_sum, behav_sum);
		end
		else if(gate_carry!=0 || data_carry!=0 || behav_carry!=0) begin
			$display("===== t=%d FAILED, value does not match =====", $time);
			$display("===== t=%d Expected value is %b, Actual gate_model carry is %b, Actual dataflow carry is %b, Actual behavioral_model carry is %b =====", $time, 0, gate_carry, data_carry, behav_carry);
		end
		else begin
			$display("===== PASSED SUCCESSFULLY =====");
		end

		#1;
		$display("===== A = 0, B = 1, Cin = 0 =====");
		a = 0; b = 1; cin = 0;
		#1;
		if(gate_sum!=1 || data_sum!=1 || behav_sum!=1) begin
			$display("===== t=%d FAILED, value does not match =====", $time);
			$display("===== t=%d Expected value is %b, Actual gate_model value is %b, Actual dataflow value is %b, Actual behavioral_model value is %b =====", $time, 1, gate_sum, data_sum, behav_sum);
		end
		else if(gate_carry!=0 || data_carry!=0 || behav_carry!=0) begin
			$display("===== t=%d FAILED, value does not match =====", $time);
			$display("===== t=%d Expected value is %b, Actual gate_model carry is %b, Actual dataflow carry is %b, Actual behavioral_model carry is %b =====", $time, 0, gate_carry, data_carry, behav_carry);
		end
		else begin
			$display("===== PASSED SUCCESSFULLY =====");
		end

		#1;
		$display("===== A = 1, B = 0, Cin = 0 =====");
		a = 1; b = 0; cin = 0;
		#1;
		if(gate_sum!=1 || data_sum!=1 || behav_sum!=1) begin
			$display("===== t=%d FAILED, value does not match =====", $time);
			$display("===== t=%d Expected value is %b, Actual gate_model value is %b, Actual dataflow value is %b, Actual behavioral_model value is %b =====", $time, 1, gate_sum, data_sum, behav_sum);
		end
		else if(gate_carry!=0 || data_carry!=0 || behav_carry!=0) begin
			$display("===== t=%d FAILED, value does not match =====", $time);
			$display("===== t=%d Expected value is %b, Actual gate_model carry is %b, Actual dataflow carry is %b, Actual behavioral_model carry is %b =====", $time, 0, gate_carry, data_carry, behav_carry);
		end
		else begin
			$display("===== PASSED SUCCESSFULLY =====");
		end

		#1;
		$display("===== A = 0, B = 0, Cin = 1 =====");
		a = 0; b = 0; cin = 1;
		#1;
		if(gate_sum!=1 || data_sum!=1 || behav_sum!=1) begin
			$display("===== t=%d FAILED, value does not match =====", $time);
			$display("===== t=%d Expected value is %b, Actual gate_model value is %b, Actual dataflow value is %b, Actual behavioral_model value is %b =====", $time, 1, gate_sum, data_sum, behav_sum);
		end
		else if(gate_carry!=0 || data_carry!=0 || behav_carry!=0) begin
			$display("===== t=%d FAILED, value does not match =====", $time);
			$display("===== t=%d Expected value is %b, Actual gate_model carry is %b, Actual dataflow carry is %b, Actual behavioral_model carry is %b =====", $time, 0, gate_carry, data_carry, behav_carry);
		end
		else begin
			$display("===== PASSED SUCCESSFULLY =====");
		end

		#1;
		$display("===== A = 1, B = 1, Cin = 0 =====");
		a = 1; b = 1; cin = 0;
		#1;
		if(gate_sum!=0 || data_sum!=0 || behav_sum!=0) begin
			$display("===== t=%d FAILED, value does not match =====", $time);
			$display("===== t=%d Expected value is %b, Actual gate_model value is %b, Actual dataflow value is %b, Actual behavioral_model value is %b =====", $time, 1, gate_sum, data_sum, behav_sum);
		end
		else if(gate_carry!=1 || data_carry!=1 || behav_carry!=1) begin
			$display("===== t=%d FAILED, value does not match =====", $time);
			$display("===== t=%d Expected value is %b, Actual gate_model carry is %b, Actual dataflow carry is %b, Actual behavioral_model carry is %b =====", $time, 1, gate_carry, data_carry, behav_carry);
		end
		else begin
			$display("===== PASSED SUCCESSFULLY =====");
		end

		#1;
		$display("===== A = 0, B = 1, Cin = 1 =====");
		a = 0; b = 1; cin = 1;
		#1;
		if(gate_sum!=0 || data_sum!=0 || behav_sum!=0) begin
			$display("===== t=%d FAILED, value does not match =====", $time);
			$display("===== t=%d Expected value is %b, Actual gate_model value is %b, Actual dataflow value is %b, Actual behavioral_model value is %b =====", $time, 1, gate_sum, data_sum, behav_sum);
		end
		else if(gate_carry!=1 || data_carry!=1 || behav_carry!=1) begin
			$display("===== t=%d FAILED, value does not match =====", $time);
			$display("===== t=%d Expected value is %b, Actual gate_model carry is %b, Actual dataflow carry is %b, Actual behavioral_model carry is %b =====", $time, 1, gate_carry, data_carry, behav_carry);
		end
		else begin
			$display("===== PASSED SUCCESSFULLY =====");
		end

		#1;
		$display("===== A = 1, B = 0, Cin = 1 =====");
		a = 1; b = 0; cin = 1;
		#1;
		if(gate_sum!=0 || data_sum!=0 || behav_sum!=0) begin
			$display("===== t=%d FAILED, value does not match =====", $time);
			$display("===== t=%d Expected value is %b, Actual gate_model value is %b, Actual dataflow value is %b, Actual behavioral_model value is %b =====", $time, 1, gate_sum, data_sum, behav_sum);
		end
		else if(gate_carry!=1 || data_carry!=1 || behav_carry!=1) begin
			$display("===== t=%d FAILED, value does not match =====", $time);
			$display("===== t=%d Expected value is %b, Actual gate_model carry is %b, Actual dataflow carry is %b, Actual behavioral_model carry is %b =====", $time, 1, gate_carry, data_carry, behav_carry);
		end
		else begin
			$display("===== PASSED SUCCESSFULLY =====");
		end

		#1;
		$display("===== A = 1, B = 1, Cin = 1 =====");
		a = 1; b = 1; cin = 1;
		#1;
		if(gate_sum!=1 || data_sum!=1 || behav_sum!=1) begin
			$display("===== t=%d FAILED, value does not match =====", $time);
			$display("===== t=%d Expected value is %b, Actual gate_model value is %b, Actual dataflow value is %b, Actual behavioral_model value is %b =====", $time, 1, gate_sum, data_sum, behav_sum);
		end
		else if(gate_carry!=1 || data_carry!=1 || behav_carry!=1) begin
			$display("===== t=%d FAILED, value does not match =====", $time);
			$display("===== t=%d Expected value is %b, Actual gate_model carry is %b, Actual dataflow carry is %b, Actual behavioral_model carry is %b =====", $time, 1, gate_carry, data_carry, behav_carry);
		end
		else begin
			$display("===== PASSED SUCCESSFULLY =====");
		end

		#1;
		$finish;
	end
	
endmodule

Homework3/full_adder/sim/wave.vcd
$date
	Fri Oct 10 20:11:37 2025
$end
$version
	Icarus Verilog
$end
$timescale
	1s
$end
$scope module test_bench6 $end
$var wire 1 ! gate_sum $end
$var wire 1 " gate_carry $end
$var wire 1 # data_sum $end
$var wire 1 $ data_carry $end
$var wire 1 % behav_sum $end
$var wire 1 & behav_carry $end
$var reg 1 ' a $end
$var reg 1 ( b $end
$var reg 1 ) cin $end
$scope module DUT $end
$var wire 1 ' a $end
$var wire 1 ( b $end
$var wire 1 ) cin $end
$var wire 1 $ data_carry $end
$var wire 1 * data_carry_1 $end
$var wire 1 + data_carry_2 $end
$var wire 1 # data_sum $end
$var wire 1 , data_sum_1 $end
$var wire 1 " gate_carry $end
$var wire 1 - gate_carry_1 $end
$var wire 1 . gate_carry_2 $end
$var wire 1 ! gate_sum $end
$var wire 1 / gate_sum_1 $end
$var reg 1 & behav_carry $end
$var reg 1 0 behav_carry_1 $end
$var reg 1 1 behav_carry_2 $end
$var reg 1 % behav_sum $end
$var reg 1 2 behav_sum_1 $end
$upscope $end
$upscope $end
$enddefinitions $end
#0
$dumpvars
02
01
00
0/
0.
0-
0,
0+
0*
0)
0(
0'
0&
0%
0$
0#
0"
0!
$end
#1
1!
1#
1%
1/
1,
12
1(
#3
0(
1'
#5
0/
0,
02
1)
0'
#7
1"
1$
0!
0#
0%
1&
1-
1*
10
0)
1(
1'
#9
1.
1+
11
1/
0-
1,
0*
12
00
1)
0'
#11
0(
1'
#13
0.
1!
0+
1#
01
1%
0/
1-
0,
1*
02
10
1(
