Homework2/alu_2bit/rtl/alu_2bit.v
module alu_2bit(
	input	wire	[1:0]	a,
	input	wire	[1:0]	b,
	input	wire	[1:0]	SL,
	output	wire	[1:0]	data_out,
	output	reg	[1:0]	behav_out,
	output 	wire         	data_carry,
	output 	reg         	behav_carry
);
	wire	[1:0]	add_result;
	wire 	[2:0] 	sum;
	//structural
	

	//dataflow
	assign sum[0] = a[0] ^ b[0];
	assign carry0  = a[0] & b[0];

	assign sum[1] = a[1] ^ b[1] ^ carry0;
	assign carry1 = (a[1] & b[1]) | (a[1] & carry0) | (b[1] & carry0);

	assign sum[2] = carry1;

	assign add_result = sum[1:0];
	assign add_carry  = sum[2];

	
	assign	data_out =	(SL == 2'b00) ? (a & b) :
				(SL == 2'b01) ? (a | b) :
				(SL == 2'b10) ? (add_result) :
				2'b00;

	assign data_carry = 	(SL == 2'b10) ? add_carry : 1'b0;

	//behavioural
	always @(*) begin
		case(SL)
			2'b00: begin
				behav_out = a & b;
				behav_carry = 1'b0;
			end
			2'b01: begin
				behav_out = a | b;
				behav_carry = 1'b0;
			end
			2'b10: begin
				{behav_carry, behav_out} = a + b;
			end
			default: begin
				behav_out 	= 2'b00;
				behav_carry 	= 1'b0;	
			end
		endcase
	end

endmodule

Homework2/alu_2bit/tb/test_bench20.v
module test_bench20;

	reg	[1:0]	a, b, SL;
	wire	[1:0] 	data_out, behav_out;
	wire		data_carry, behav_carry;

	alu_2bit DUT(.*);

	initial begin
		$dumpfile("wave20.vcd");
		$dumpvars(0,test_bench20);
		$display("===== Test Alu 2bit =====");
		$monitor("===== A = %b , B = %b, Control bits = %b =====", a, b, SL);
		$display("===== Check AND Case =====");
		a=2'b00; b=2'b00; SL=2'b00;
		#1;	
		check_result(2'b00, data_out, behav_out);
		check_carry(0, data_carry, behav_carry);

		a=2'b00; b=2'b01; SL=2'b00;
		#1;	
		check_result(2'b00, data_out, behav_out);
		check_carry(0, data_carry, behav_carry);

		a=2'b00; b=2'b10; SL=2'b00;
		#1;	
		check_result(2'b00, data_out, behav_out);
		check_carry(0, data_carry, behav_carry);

		a=2'b01; b=2'b01; SL=2'b00;
		#1;	
		check_result(2'b01, data_out, behav_out);
		check_carry(0, data_carry, behav_carry);

		a=2'b10; b=2'b10; SL=2'b00;
		#1;	
		check_result(2'b10, data_out, behav_out);
		check_carry(0, data_carry, behav_carry);

		a=2'b01; b=2'b10; SL=2'b00;
		#1;	
		check_result(2'b00, data_out, behav_out);
		check_carry(0, data_carry, behav_carry);

		a=2'b11; b=2'b01; SL=2'b00;
		#1;	
		check_result(2'b01, data_out, behav_out);
		check_carry(0, data_carry, behav_carry);

		a=2'b11; b=2'b11; SL=2'b00;
		#1;	
		check_result(2'b11, data_out, behav_out);
		check_carry(0, data_carry, behav_carry);

		$display("===== Check OR Case =====");
		a=2'b00; b=2'b00; SL=2'b01;
		#1;	
		check_result(2'b00, data_out, behav_out);
		check_carry(0, data_carry, behav_carry);

		a=2'b00; b=2'b01; SL=2'b01;
		#1;	
		check_result(2'b01, data_out, behav_out);
		check_carry(0, data_carry, behav_carry);

		a=2'b00; b=2'b10; SL=2'b01;
		#1;	
		check_result(2'b10, data_out, behav_out);
		check_carry(0, data_carry, behav_carry);

		a=2'b01; b=2'b01; SL=2'b01;
		#1;	
		check_result(2'b01, data_out, behav_out);
		check_carry(0, data_carry, behav_carry);

		a=2'b10; b=2'b10; SL=2'b01;
		#1;	
		check_result(2'b10, data_out, behav_out);
		check_carry(0, data_carry, behav_carry);

		a=2'b01; b=2'b10; SL=2'b01;
		#1;	
		check_result(2'b11, data_out, behav_out);
		check_carry(0, data_carry, behav_carry);

		a=2'b11; b=2'b01; SL=2'b01;
		#1;	
		check_result(2'b11, data_out, behav_out);
		check_carry(0, data_carry, behav_carry);

		a=2'b11; b=2'b11; SL=2'b01;
		#1;	
		check_result(2'b11, data_out, behav_out);
		check_carry(0, data_carry, behav_carry);
			
		$display("===== Check ADD Case =====");
		a=2'b00; b=2'b00; SL=2'b10;
		#1;	
		check_result(2'b00, data_out, behav_out);
		check_carry(0, data_carry, behav_carry);

		a=2'b00; b=2'b01; SL=2'b10;
		#1;	
		check_result(2'b01, data_out, behav_out);
		check_carry(0, data_carry, behav_carry);

		a=2'b00; b=2'b10; SL=2'b10;
		#1;	
		check_result(2'b10, data_out, behav_out);
		check_carry(0, data_carry, behav_carry);

		a=2'b01; b=2'b01; SL=2'b10;
		#1;	
		check_result(2'b10, data_out, behav_out);
		check_carry(0, data_carry, behav_carry);

		a=2'b10; b=2'b10; SL=2'b10;
		#1;	
		check_result(2'b00, data_out, behav_out); // 2+2 = 4 (0b100), carry=1
		check_carry(1, data_carry, behav_carry);

		a=2'b01; b=2'b10; SL=2'b10;
		#1;	
		check_result(2'b11, data_out, behav_out); // 1+2=3
		check_carry(0, data_carry, behav_carry);

		a=2'b11; b=2'b01; SL=2'b10;
		#1;	
		check_result(2'b00, data_out, behav_out); // 3+1=4 (0b100), carry=1
		check_carry(1, data_carry, behav_carry);

		a=2'b11; b=2'b11; SL=2'b10;
		#1;	
		check_result(2'b10, data_out, behav_out); // 3+3=6 (0b110), carry=1
		check_carry(1, data_carry, behav_carry);

		
		#1;
		$finish;		

	end

	task check_result;
		input 	[1:0]	expected_result;
		input	[1:0]	d_out;
		input	[1:0]	b_out;
		if(d_out != expected_result || b_out != expected_result) begin
			$display("===== t=%d FAILED, output does not match =====", $time);
			$display("===== t=%d Expected output is %b, Actual dataflow output is %b, Actual behavioral output is %b =====",$time, expected_result, d_out, b_out);
		end
		else begin
			$display("===== t=%d PASSED SUCCESSFULLY =====",$time);
		end
	endtask

	task check_carry;
		input	expected_carry;
		input	d_carry;
		input	b_carry;
		if(d_carry != expected_carry || b_carry != expected_carry) begin
			$display("===== t=%d FAILED, output does not match =====", $time);
			$display("===== t=%d Expected carry is %b, Actual dataflow carry is %b, Actual behavioral carry is %b =====",$time, expected_carry, d_carry, b_carry);
		end
		else begin
			$display("===== t=%d PASSED SUCCESSFULLY =====",$time);
		end
	endtask

endmodule

Homework2/alu_2bit/sim/wave20.vcd
$date
	Mon Sep 29 15:59:14 2025
$end
$version
	Icarus Verilog
$end
$timescale
	1s
$end
$scope module test_bench20 $end
$var wire 2 ! data_out [1:0] $end
$var wire 1 " data_carry $end
$var wire 2 # behav_out [1:0] $end
$var wire 1 $ behav_carry $end
$var reg 2 % SL [1:0] $end
$var reg 2 & a [1:0] $end
$var reg 2 ' b [1:0] $end
$scope module DUT $end
$var wire 2 ( SL [1:0] $end
$var wire 2 ) a [1:0] $end
$var wire 2 * b [1:0] $end
$var wire 1 + carry0 $end
$var wire 1 , carry1 $end
$var wire 3 - sum [2:0] $end
$var wire 2 . data_out [1:0] $end
$var wire 1 " data_carry $end
$var wire 2 / add_result [1:0] $end
$var wire 1 0 add_carry $end
$var reg 1 $ behav_carry $end
$var reg 2 1 behav_out [1:0] $end
$upscope $end
$scope task check_carry $end
$var reg 1 2 b_carry $end
$var reg 1 3 d_carry $end
$var reg 1 4 expected_carry $end
$upscope $end
$scope task check_result $end
$var reg 2 5 b_out [1:0] $end
$var reg 2 6 d_out [1:0] $end
$var reg 2 7 expected_result [1:0] $end
$upscope $end
$upscope $end
$enddefinitions $end
#0
$dumpvars
bx 7
bx 6
bx 5
x4
x3
x2
b0 1
00
b0 /
b0 .
b0 -
0,
0+
b0 *
b0 )
b0 (
b0 '
b0 &
b0 %
0$
b0 #
0"
b0 !
$end
#1
b1 /
b1 -
b1 '
b1 *
02
03
04
b0 5
b0 6
b0 7
#2
b10 /
b10 -
b10 '
b10 *
#3
b1 !
b1 .
1+
b1 #
b1 1
b1 '
b1 *
b1 &
b1 )
#4
10
b0 /
1,
b100 -
b10 !
b10 .
0+
b10 #
b10 1
b10 '
b10 *
b10 &
b10 )
b1 5
b1 6
b1 7
#5
00
0,
b11 /
b0 !
b0 .
b11 -
b0 #
b0 1
b1 &
b1 )
b10 5
b10 6
b10 7
#6
10
1,
b0 /
b100 -
1+
b1 !
b1 .
b1 #
b1 1
b1 '
b1 *
b11 &
b11 )
b0 5
b0 6
b0 7
#7
b10 /
b110 -
b11 !
b11 .
b11 #
b11 1
b11 '
b11 *
b1 5
b1 6
b1 7
#8
00
b0 /
0,
b0 -
0+
b0 !
b0 .
b0 #
b0 1
b1 %
b1 (
b0 '
b0 *
b0 &
b0 )
b11 5
b11 6
b11 7
#9
b1 !
b1 .
b1 /
b1 -
b1 #
b1 1
b1 '
b1 *
b0 5
b0 6
b0 7
#10
b10 !
b10 .
b10 /
b10 -
b10 #
b10 1
b10 '
b10 *
b1 5
b1 6
b1 7
#11
b1 !
b1 .
1+
b1 #
b1 1
b1 '
b1 *
b1 &
b1 )
b10 5
b10 6
b10 7
#12
10
b0 /
1,
b10 !
b10 .
b100 -
0+
b10 #
b10 1
b10 '
b10 *
b10 &
b10 )
b1 5
b1 6
b1 7
#13
00
0,
b11 !
b11 .
b11 /
b11 -
b11 #
b11 1
b1 &
b1 )
b10 5
b10 6
b10 7
#14
10
1,
b0 /
b100 -
1+
b1 '
b1 *
b11 &
b11 )
b11 5
b11 6
b11 7
#15
b10 /
b110 -
b11 '
b11 *
#16
00
b0 /
0,
b0 -
b0 !
b0 .
0+
0"
b0 #
b0 1
b10 %
b10 (
b0 '
b0 *
b0 &
b0 )
#17
b1 !
b1 .
b1 /
b1 -
b1 #
b1 1
b1 '
b1 *
b0 5
b0 6
b0 7
#18
b10 !
b10 .
b10 /
b10 -
b10 #
b10 1
b10 '
b10 *
b1 5
b1 6
b1 7
#19
1+
b1 '
b1 *
b1 &
b1 )
b10 5
b10 6
b10 7
#20
b0 !
b0 .
1"
10
b0 /
1,
b100 -
0+
1$
b0 #
b0 1
b10 '
b10 *
b10 &
b10 )
#21
b11 !
b11 .
0"
00
0,
b11 /
b11 -
0$
b11 #
b11 1
b1 &
b1 )
12
13
14
b0 5
b0 6
b0 7
#22
1"
b0 !
b0 .
10
1,
b0 /
b100 -
1+
1$
b0 #
b0 1
b1 '
b1 *
b11 &
b11 )
02
03
04
b11 5
b11 6
b11 7
#23
b10 !
b10 .
b10 /
b110 -
b10 #
b10 1
b11 '
b11 *
12
13
14
b0 5
b0 6
b0 7
#24
b10 5
b10 6
b10 7
