Homework3/bin_to_gray/rtl/bin_to_gray.v
module  bin_to_gray(
	input	wire	[3:0]	bin,

	output	wire	[3:0]	gate_sum,
	output	wire	[3:0]	data_sum,
	output	reg	[3:0]	behav_sum
);

	//structural
	buf(gate_sum[3], bin[3]); 
	xor(gate_sum[2], bin[3], bin[2]);   
	xor(gate_sum[2], bin[3], bin[2]);
	xor(gate_sum[1], bin[1], bin[2]);   
	xor(gate_sum[0], bin[1], bin[0]);	

	//dataflow
	assign data_sum[3]	= bin[3];
	assign data_sum[2]	= bin[3] ^ bin[2];
	assign data_sum[1]	= bin[1] ^ bin[2];
	assign data_sum[0]	= bin[1] ^ bin[0];
	
	//behavioral 	
	always @(*) begin
		behav_sum[3]	= bin[3];
		behav_sum[2]	= bin[3] ^ bin[2];
		behav_sum[1]	= bin[1] ^ bin[2];
		behav_sum[0]	= bin[1] ^ bin[0];
	end
endmodule

Homework3/bin_to_gray/tb/test_bench.v
module test_bench;

    reg  [3:0] bin;
    wire [3:0] gate_sum, data_sum, behav_sum;

    bin_to_gray DUT(.*);

    initial begin
        $dumpfile("wave.vcd");
        $dumpvars(0,test_bench);
        $display("===== Binary to Gray Code Converter =====");
	$monitor("\n===== t=%d With Binary Code = %b =====", $time, bin);

        bin = 4'b0000;
        #1;
        check_result(4'b0000, gate_sum, data_sum, behav_sum);
	
	bin = 4'b0001;
        #1;
        check_result(4'b0001, gate_sum, data_sum, behav_sum);

        bin = 4'b0010; 
        #1;
        check_result(4'b0011, gate_sum, data_sum, behav_sum);

        bin = 4'b0011; 
        #1; 
        check_result(4'b0010, gate_sum, data_sum, behav_sum);

        bin = 4'b0100; 
        #1; 
        check_result(4'b0110, gate_sum, data_sum, behav_sum);

	bin = 4'b0101;
        #1;
        check_result(4'b0111, gate_sum, data_sum, behav_sum);
	
	bin = 4'b0110;
        #1;
        check_result(4'b0101, gate_sum, data_sum, behav_sum);

        bin = 4'b0111; 
        #1;
        check_result(4'b0100, gate_sum, data_sum, behav_sum);

        bin = 4'b1000; 
        #1; 
        check_result(4'b1100, gate_sum, data_sum, behav_sum);

        bin = 4'b1001; 
        #1; 
        check_result(4'b1101, gate_sum, data_sum, behav_sum);

	bin = 4'b1010; 
        #1; 
        check_result(4'b1111, gate_sum, data_sum, behav_sum);

	bin = 4'b1011;
        #1;
        check_result(4'b1110, gate_sum, data_sum, behav_sum);
	
	bin = 4'b1100;
        #1;
        check_result(4'b1010, gate_sum, data_sum, behav_sum);

        bin = 4'b1101; 
        #1;
        check_result(4'b1011, gate_sum, data_sum, behav_sum);

        bin = 4'b1110; 
        #1; 
        check_result(4'b1001, gate_sum, data_sum, behav_sum);

        bin = 4'b1111; 
        #1; 
        check_result(4'b1000, gate_sum, data_sum, behav_sum);

        $finish;
    end

    // ===== Task for checking result =====
    task check_result;
        input [3:0] expected_result;
        input [3:0] e;    
        input [3:0] f;
        input [3:0] g;
    begin
        if(e != expected_result || f != expected_result || g != expected_result) begin
            $display("===== t=%d FAILED, output value does not match =====", $time);
            $display("===== t=%d Expected value is %2d, Actual gate_model value is %2d, Actual dataflow value is %2d, Actual behavioral_model value is %2d =====", $time, expected_result, e, f, g);
        end
        else begin
            $display("===== t=%d PASSED SUCCESSFULLY =====", $time);
        end
    end
    endtask

endmodule

Homework3/bin_to_gray/sim/wave.vcd
$date
	Fri Oct 10 20:31:28 2025
$end
$version
	Icarus Verilog
$end
$timescale
	1s
$end
$scope module test_bench $end
$var wire 4 ! gate_sum [3:0] $end
$var wire 4 " data_sum [3:0] $end
$var wire 4 # behav_sum [3:0] $end
$var reg 4 $ bin [3:0] $end
$scope module DUT $end
$var wire 4 % bin [3:0] $end
$var wire 4 & gate_sum [3:0] $end
$var wire 4 ' data_sum [3:0] $end
$var reg 4 ( behav_sum [3:0] $end
$upscope $end
$scope task check_result $end
$var reg 4 ) e [3:0] $end
$var reg 4 * expected_result [3:0] $end
$var reg 4 + f [3:0] $end
$var reg 4 , g [3:0] $end
$upscope $end
$upscope $end
$enddefinitions $end
#0
$dumpvars
bx ,
bx +
bx *
bx )
b0 (
b0 '
b0 &
b0 %
b0 $
b0 #
b0 "
b0 !
$end
#1
b1 !
b1 &
b1 "
b1 '
b1 #
b1 (
b1 $
b1 %
b0 ,
b0 +
b0 )
b0 *
#2
b11 !
b11 &
b11 "
b11 '
b11 #
b11 (
b10 $
b10 %
b1 ,
b1 +
b1 )
b1 *
#3
b10 !
b10 &
b10 "
b10 '
b10 #
b10 (
b11 $
b11 %
b11 ,
b11 +
b11 )
b11 *
#4
b110 !
b110 &
b110 "
b110 '
b110 #
b110 (
b100 $
b100 %
b10 ,
b10 +
b10 )
b10 *
#5
b111 !
b111 &
b111 "
b111 '
b111 #
b111 (
b101 $
b101 %
b110 ,
b110 +
b110 )
b110 *
#6
b101 !
b101 &
b101 "
b101 '
b101 #
b101 (
b110 $
b110 %
b111 ,
b111 +
b111 )
b111 *
#7
b100 !
b100 &
b100 "
b100 '
b100 #
b100 (
b111 $
b111 %
b101 ,
b101 +
b101 )
b101 *
#8
b1100 !
b1100 &
b1100 #
b1100 (
b1100 "
b1100 '
b1000 $
b1000 %
b100 ,
b100 +
b100 )
b100 *
#9
b1101 !
b1101 &
b1101 "
b1101 '
b1101 #
b1101 (
b1001 $
b1001 %
b1100 ,
b1100 +
b1100 )
b1100 *
#10
b1111 !
b1111 &
b1111 "
b1111 '
b1111 #
b1111 (
b1010 $
b1010 %
b1101 ,
b1101 +
b1101 )
b1101 *
#11
b1110 !
b1110 &
b1110 "
b1110 '
b1110 #
b1110 (
b1011 $
b1011 %
b1111 ,
b1111 +
b1111 )
b1111 *
#12
b1010 !
b1010 &
b1010 "
b1010 '
b1010 #
b1010 (
b1100 $
b1100 %
b1110 ,
b1110 +
b1110 )
b1110 *
#13
b1011 !
b1011 &
b1011 "
b1011 '
b1011 #
b1011 (
b1101 $
b1101 %
b1010 ,
b1010 +
b1010 )
b1010 *
#14
b1001 !
b1001 &
b1001 "
b1001 '
b1001 #
b1001 (
b1110 $
b1110 %
b1011 ,
b1011 +
b1011 )
b1011 *
#15
b1000 !
b1000 &
b1000 "
b1000 '
b1000 #
b1000 (
b1111 $
b1111 %
b1001 ,
b1001 +
b1001 )
b1001 *
#16
b1000 ,
b1000 +
b1000 )
b1000 *
