Homework2/decoder_3to8/rtl/decoder_3to8.v
module decoder_3to8(
	input	wire	[2:0] 	s,
	output	wire	[7:0]	gate_out,
	output	wire	[7:0]	data_out,
	output	reg	[7:0]	behav_out
);
	wire	n0, n1, n2;

	//structural
	not(n0, s[0]);
	not(n1, s[1]);
	not(n2, s[2]);

	and(gate_out[0], n2, n1, n0);
	and(gate_out[1], n2, n1, s[0]);
	and(gate_out[2], n2, s[1], n0);
	and(gate_out[3], n2, s[1], s[0]);

	and(gate_out[4], s[2], n1, n0);
	and(gate_out[5], s[2], n1, s[0]);
	and(gate_out[6], s[2], s[1], n0);
	and(gate_out[7], s[2], s[1], s[0]);

	//dataflow
	assign data_out = (8'b0000_0001 << s);

	//behavioural
	always @(*) begin
		case(s)
				3'b000:		behav_out = 8'b0000_0001;
				3'b001:		behav_out = 8'b0000_0010;
				3'b010:		behav_out = 8'b0000_0100;
				3'b011:		behav_out = 8'b0000_1000;
				3'b100:		behav_out = 8'b0001_0000;
				3'b101:		behav_out = 8'b0010_0000;
				3'b110:		behav_out = 8'b0100_0000;
				3'b111:		behav_out = 8'b1000_0000;
				default:	behav_out = 8'b0;
		endcase
	end

endmodule

Homework2/decoder_3to8/tb/test_bench10.v
module test_bench10;

    reg [2:0] s;
    wire [7:0] gate_out, data_out, behav_out;

    decoder_3to8 DUT(.*);

    initial begin
        $dumpfile("wave10.vcd");
        $dumpvars(0,test_bench10);
        $display("===== Test 3 to 8 Decoder =====");

        s = 3'b000; 
	#1;
        $display("===== S = 3'b000 =====");
        if(gate_out!=8'b0000_0001 || data_out!=8'b0000_0001 || behav_out!=8'b0000_0001) begin
            $display("===== t=%d FAILED, value does not match =====", $time);
            $display("===== t=%d Expected=0000_0001, Gate=%b, Data=%b, Behavioral=%b =====", $time, gate_out, data_out, behav_out);
        end else begin
            $display("===== t=%d PASSED SUCCESSFULLY =====", $time);
        end

        s = 3'b001; 
	#1;
        $display("===== S = 3'b001 =====");
        if(gate_out!=8'b0000_0010 || data_out!=8'b0000_0010 || behav_out!=8'b0000_0010) begin
            $display("===== t=%d FAILED, value does not match =====", $time);
            $display("===== t=%d Expected=0000_0010, Gate=%b, Data=%b, Behavioral=%b =====", $time, gate_out, data_out, behav_out);
        end else begin
            $display("===== t=%d PASSED SUCCESSFULLY =====", $time);
        end

        s = 3'b010; 
	#1;
        $display("===== S = 3'b010 =====");
        if(gate_out!=8'b0000_0100 || data_out!=8'b0000_0100 || behav_out!=8'b0000_0100) begin
            $display("===== t=%d FAILED, value does not match =====", $time);
            $display("===== t=%d Expected=0000_0100, Gate=%b, Data=%b, Behavioral=%b =====", $time, gate_out, data_out, behav_out);
        end else begin
            $display("===== t=%d PASSED SUCCESSFULLY =====", $time);
        end

        s = 3'b011; 
	#1;
        $display("===== S = 3'b011 =====");
        if(gate_out!=8'b0000_1000 || data_out!=8'b0000_1000 || behav_out!=8'b0000_1000) begin
            $display("===== t=%d FAILED, value does not match =====", $time);
            $display("===== t=%d Expected=0001_0000, Gate=%b, Data=%b, Behavioral=%b =====", $time, gate_out, data_out, behav_out);
        end else begin
            $display("===== t=%d PASSED SUCCESSFULLY =====", $time);
        end

	s = 3'b100; 
	#1;
        $display("===== S = 3'b100 =====");
        if(gate_out!=8'b0001_0000 || data_out!=8'b0001_0000 || behav_out!=8'b0001_0000) begin
            $display("===== t=%d FAILED, value does not match =====", $time);
            $display("===== t=%d Expected=0001_0000, Gate=%b, Data=%b, Behavioral=%b =====", $time, gate_out, data_out, behav_out);
        end else begin
            $display("===== t=%d PASSED SUCCESSFULLY =====", $time);
        end

        s = 3'b101; 
	#1;
        $display("===== S = 3'b101 =====");
        if(gate_out!=8'b0010_0000 || data_out!=8'b0010_0000 || behav_out!=8'b0010_0000) begin
            $display("===== t=%d FAILED, value does not match =====", $time);
            $display("===== t=%d Expected=0010_0000, Gate=%b, Data=%b, Behavioral=%b =====", $time, gate_out, data_out, behav_out);
        end else begin
            $display("===== t=%d PASSED SUCCESSFULLY =====", $time);
        end

        s = 3'b110; 
	#1;
        $display("===== S = 3'b110 =====");
        if(gate_out!=8'b0100_0000 || data_out!=8'b0100_0000 || behav_out!=8'b0100_0000) begin
            $display("===== t=%d FAILED, value does not match =====", $time);
            $display("===== t=%d Expected=0100_0000, Gate=%b, Data=%b, Behavioral=%b =====", $time, gate_out, data_out, behav_out);
        end else begin
            $display("===== t=%d PASSED SUCCESSFULLY =====", $time);
        end

        s = 3'b111; 
	#1;
        $display("===== S = 3'b111 =====");
        if(gate_out!=8'b1000_0000 || data_out!=8'b1000_0000 || behav_out!=8'b1000_0000) begin
            $display("===== t=%d FAILED, value does not match =====", $time);
            $display("===== t=%d Expected=1000_0000, Gate=%b, Data=%b, Behavioral=%b =====", $time, gate_out, data_out, behav_out);
        end else begin
            $display("===== t=%d PASSED SUCCESSFULLY =====", $time);
        end

        #1;
        $finish;
    end

endmodule

Homework2/decoder_3to8/sim/wave10.vcd
$date
	Thu Sep 25 19:44:55 2025
$end
$version
	Icarus Verilog
$end
$timescale
	1s
$end
$scope module test_bench10 $end
$var wire 8 ! gate_out [7:0] $end
$var wire 8 " data_out [7:0] $end
$var wire 8 # behav_out [7:0] $end
$var reg 3 $ s [2:0] $end
$scope module DUT $end
$var wire 1 % n0 $end
$var wire 1 & n1 $end
$var wire 1 ' n2 $end
$var wire 3 ( s [2:0] $end
$var wire 8 ) gate_out [7:0] $end
$var wire 8 * data_out [7:0] $end
$var reg 8 + behav_out [7:0] $end
$upscope $end
$upscope $end
$enddefinitions $end
#0
$dumpvars
b1 +
b1 *
b1 )
b0 (
1'
1&
1%
b0 $
b1 #
b1 "
b1 !
$end
#1
0%
b10 !
b10 )
b10 #
b10 +
b10 "
b10 *
b1 $
b1 (
#2
1%
0&
b100 !
b100 )
b100 #
b100 +
b100 "
b100 *
b10 $
b10 (
#3
0%
b1000 !
b1000 )
b1000 #
b1000 +
b1000 "
b1000 *
b11 $
b11 (
#4
1%
1&
0'
b10000 !
b10000 )
b10000 #
b10000 +
b10000 "
b10000 *
b100 $
b100 (
#5
0%
b100000 !
b100000 )
b100000 #
b100000 +
b100000 "
b100000 *
b101 $
b101 (
#6
1%
0&
b1000000 !
b1000000 )
b1000000 #
b1000000 +
b1000000 "
b1000000 *
b110 $
b110 (
#7
0%
b10000000 !
b10000000 )
b10000000 #
b10000000 +
b10000000 "
b10000000 *
b111 $
b111 (
