Homework3/moore_detector/rtl/moore_detector.v
module moore_detector(
	input	wire	clk,
	input	wire	rst_n,
	input	wire	in,
	output	reg	out
);

	parameter	A = 4'h0;
	parameter	B = 4'h4;
	parameter	C = 4'h8;
	parameter	D = 4'hC;
	parameter	E = 4'hF;

	reg	[3:0]	state, current_state;

	always @(posedge clk or negedge rst_n) begin
		if(!rst_n)
			current_state	<= A;
		else
			current_state	<= state;
	end

	always @(posedge clk or negedge rst_n) begin
		if(!rst_n) begin
						out	<= 0;
		end
		else begin
			case(current_state)
				E: 		out	<= 1;
				default: 	out 	<= 0;
			endcase
		end
	end

	always @(*) begin
		case(current_state)
			A: begin
				if(in == 1)
					state 	= B;
				else
					state	= A;
			end
			B: begin
				if(in == 1)
					state 	= C;
				else
					state	= A;
			end
			C: begin
				if(in == 1)
					state 	= D;
				else
					state	= A;
			end
			D: begin
				if(in == 0) begin
					state 	= E;
				end
				else begin
					state	= D;
				end
			end
			E: begin
				if(in == 1) begin
					state 	= B;
				end
				else begin
					state	= A;
				end
			end
			default: begin
				state	= A;
			end
		endcase
	end
		
endmodule

Homework3/moore_detector/tb/test_bench.v
module test_bench;

	reg	clk, rst_n, in;
	wire	out;

	moore_detector DUT(.*);

	initial begin
		clk = 0;
		forever #25 clk = ~clk;
	end

	initial begin
		$dumpfile("wave.vcd");
		$dumpvars(0,test_bench);
		$display("===== Test Moore Sequence Detector =====");
		$monitor("===== With Input Value = %b =====",in);
		rst_n = 0; in = 0;
		$display("===== With Reset value = %b =====", rst_n);
		@(posedge clk);
		#1;
		check_result(1'b0, out);

		rst_n = 1;
		$display("===== With Reset value = %b =====", rst_n);
		in = 1;
		@(posedge clk);
		#1;
		check_result(1'b0, out);

		in = 0;
		@(posedge clk);
		#1;
		check_result(1'b0, out);

		in = 1;
		@(posedge clk);
		#1;
		check_result(1'b0, out);

		in = 0;
		@(posedge clk);
		#1;
		check_result(1'b1, out);

		in = 0;
		@(posedge clk);
		#1;
		check_result(1'b0, out);

		in = 1;
		@(posedge clk);
		#1;
		check_result(1'b0, out);

		in = 0;
		@(posedge clk);
		#1;
		check_result(1'b0, out);

		in = 0;
		@(posedge clk);
		#1;
		check_result(1'b0, out);

		in = 1;
		@(posedge clk);
		#1;
		check_result(1'b0, out);

		in = 0;
		@(posedge clk);
		#1;
		check_result(1'b0, out);

		in = 1;
		@(posedge clk);
		#1;
		check_result(1'b0, out);

		in = 0;
		@(posedge clk);
		#1;
		check_result(1'b1, out);

		#10;
		$finish;
	end

	task check_result;
		input		result;
		input		g;

		if(g!=result) begin
			$display("\n===== t=%d FAILED, output does not match =====",$time);
			$display("===== t=%d Expected value is %b, Actual value is %b =====",$time, result, g);
		end
		else begin
			$display("\n===== t=%d PASSED SUCCESSFULLY =====",$time);
		end
	endtask
	
endmodule

Homework3/moore_detector/sim/wave.vcd
$date
	Fri Oct 10 18:21:52 2025
$end
$version
	Icarus Verilog
$end
$timescale
	1s
$end
$scope module test_bench $end
$var wire 1 ! out $end
$var reg 1 " clk $end
$var reg 1 # in $end
$var reg 1 $ rst_n $end
$scope module DUT $end
$var wire 1 " clk $end
$var wire 1 # in $end
$var wire 1 $ rst_n $end
$var reg 4 % current_state [3:0] $end
$var reg 1 ! out $end
$var reg 4 & state [3:0] $end
$upscope $end
$scope task check_result $end
$var reg 1 ' g $end
$var reg 1 ( result $end
$upscope $end
$upscope $end
$enddefinitions $end
#0
$dumpvars
x(
x'
b0 &
b0 %
0$
0#
0"
0!
$end
#25
1"
#26
b100 &
1#
1$
0'
0(
#50
0"
#75
b100 %
1"
#76
b1000 &
0#
#100
0"
#125
b0 &
b1000 %
1"
#126
b1100 &
1#
#150
0"
#175
b100 &
b1100 %
1"
#176
b1000 &
0#
#200
0"
#225
b0 &
1!
b1000 %
1"
#226
1'
1(
#250
0"
#275
b0 %
0!
1"
#276
b100 &
1#
0'
0(
#300
0"
#325
b100 %
1"
#326
b1000 &
0#
#350
0"
#375
b0 &
b1000 %
1"
#400
0"
#425
b0 %
1"
#426
b100 &
1#
#450
0"
#475
b100 %
1"
#476
b1000 &
0#
#500
0"
#525
b0 &
b1000 %
1"
#526
b1100 &
1#
#550
0"
#575
b100 &
b1100 %
1"
#576
b1000 &
0#
#600
0"
#625
b0 &
1!
b1000 %
1"
#626
1'
1(
