Homework3/dff_syn/rtl/dff_syn.v
module dff_syn(
	input	wire	clk,
	input	wire	rst_n,
	input 	wire	[1:0]	in,
	output	reg	[1:0]	out
);

	always @(posedge clk) begin
		if(!rst_n)
			out	<= 2'b00;
		else	
			out	<= in;
	end

endmodule

Homework3/dff_syn/tb/test_bench.v
module test_bench;

	reg		clk, rst_n;
	reg	[1:0]	in;
	wire 	[1:0]	out;

	dff_syn DUT(.*);

	initial begin
		clk = 0;
		forever #25 clk = ~clk;
	end

	initial begin
		$dumpfile("wave.vcd");
		$dumpvars(0,test_bench);
		$display("===== DFF With Synchronous Reset Testbench =====");
		in = 2'b00;
		rst_n = 0;
		@(posedge clk); 
		#1;
		if(out!=0) begin
			$display("===== t=%d FAILED, output does not match =====",$time);
			$display("===== t=%d Expected value is %b, Actual value is %b =====",$time, 0, out);
		end
		else begin
			$display("===== t=%d PASSED SUCCESSFULLY =====",$time);
		end
		rst_n = 1;
		#50 in = 2'b01;
		#1;
		if(out!=0) begin
			$display("===== t=%d FAILED, output does not match =====",$time);
			$display("===== t=%d Expected value is %b, Actual value is %b =====",$time, 0, out);
		end
		else begin
			$display("===== t=%d PASSED SUCCESSFULLY =====",$time);
		end

		@(posedge clk); 
		#1;
		if(out!=2'b01) begin
			$display("===== t=%d FAILED, output does not match =====",$time);
			$display("===== t=%d Expected value is %b, Actual value is %b =====",$time, 2'b01, out);
		end
		else begin
			$display("===== t=%d PASSED SUCCESSFULLY =====",$time);
		end
		#50 in = 2'b10;
		if(out!=2'b01) begin
			$display("===== t=%d FAILED, output does not match =====",$time);
			$display("===== t=%d Expected value is %b, Actual value is %b =====",$time, 2'b01, out);
		end
		else begin
			$display("===== t=%d PASSED SUCCESSFULLY =====",$time);
		end

		@(posedge clk);
		#1;
		if(out!=2'b10) begin
			$display("===== t=%d FAILED, output does not match =====",$time);
			$display("===== t=%d Expected value is %b, Actual value is %b =====",$time, 2'b10, out);
		end
		else begin
			$display("===== t=%d PASSED SUCCESSFULLY =====",$time);
		end

		#50 in = 2'b11;
		if(out!=2'b10) begin
			$display("===== t=%d FAILED, output does not match =====",$time);
			$display("===== t=%d Expected value is %b, Actual value is %b =====",$time, 2'b10, out);
		end
		else begin
			$display("===== t=%d PASSED SUCCESSFULLY =====",$time);
		end

		@(posedge clk);
		#1;
		if(out!=2'b11) begin
			$display("===== t=%d FAILED, output does not match =====",$time);
			$display("===== t=%d Expected value is %b, Actual value is %b =====",$time, 2'b11, out);
		end
		else begin
			$display("===== t=%d PASSED SUCCESSFULLY =====",$time);
		end

		#10;
		$finish;
	end
	
endmodule

Homework3/dff_syn/sim/wave.vcd
$date
	Thu Oct 09 18:24:38 2025
$end
$version
	Icarus Verilog
$end
$timescale
	1s
$end
$scope module test_bench $end
$var wire 2 ! out [1:0] $end
$var reg 1 " clk $end
$var reg 2 # in [1:0] $end
$var reg 1 $ rst_n $end
$scope module DUT $end
$var wire 1 " clk $end
$var wire 2 % in [1:0] $end
$var wire 1 $ rst_n $end
$var reg 2 & out [1:0] $end
$upscope $end
$upscope $end
$enddefinitions $end
#0
$dumpvars
bx &
b0 %
0$
b0 #
0"
bx !
$end
#25
b0 !
b0 &
1"
#26
1$
#50
0"
#75
1"
#76
b1 #
b1 %
#100
0"
#125
b1 !
b1 &
1"
#150
0"
#175
1"
#176
b10 #
b10 %
#200
0"
#225
b10 !
b10 &
1"
#250
0"
#275
1"
#276
b11 #
b11 %
#300
0"
#325
b11 !
b11 &
1"
