Homework2/subtractor_1bit/rtl/subtractor_1bit.v
module subtractor_1bit(
	input	wire	a,
	input	wire	b,
	input	wire	bin,
	output	wire	gate_out,
	output	wire	data_out,
	output	reg	behav_out,
	output	wire	gate_carry,
	output	wire	data_carry,
	output	reg	behav_carry
);
	wire	n_a;
	wire	f1, f2, f3;

	//structural
	xor(gate_out, a, b, bin);

	not(n_a, a);

	and(f1, n_a, b);
	and(f2, n_a, bin);
	and(f3, b, bin);
	or(gate_carry, f1, f2, f3);

	//data_flow
	assign 	data_out = a ^ b ^ bin;
	assign	data_carry = (~a & b) | (~a & bin) | (b & bin);

	//behavioral
	always @(*) begin
		behav_out = a ^ b ^ bin;
		behav_carry = (~a & b) | (~a & bin) | (b & bin);
	end

endmodule

Homework2/subtractor_1bit/tb/test_bench18.v
module test_bench18;

	reg	a, b, bin;
	wire	gate_out, data_out, behav_out;
	wire	gate_carry, data_carry, behav_carry;

	subtractor_1bit DUT(.*);

	initial begin
		$dumpfile("wave18.vcd");
		$dumpvars(0,test_bench18);
		$display("===== Test 1 Bit Subtractor =====");
		$monitor("===== A = %b, B = %b, Bin = %b =====", a, b, bin);
		a=0; b=0; bin=0;
		#1;	
		check_result(0, gate_out, data_out, behav_out);
		check_borrow(0, gate_carry, data_carry, behav_carry);
		a=0; b=0; bin=1;
		#1;
		check_result(1, gate_out, data_out, behav_out);
		check_borrow(1, gate_carry, data_carry, behav_carry);
		a=0; b=1; bin=0;
		#1;
		check_result(1, gate_out, data_out, behav_out);
		check_borrow(1, gate_carry, data_carry, behav_carry);
		a=0; b=1; bin=1;
		#1;
		check_result(0, gate_out, data_out, behav_out);
		check_borrow(1, gate_carry, data_carry, behav_carry);
		a=1; b=0; bin=0;
		#1;
		check_result(1, gate_out, data_out, behav_out);
		check_borrow(0, gate_carry, data_carry, behav_carry);
		a=1; b=0; bin=1;
		#1;
		check_result(0, gate_out, data_out, behav_out);
		check_borrow(0, gate_carry, data_carry, behav_carry);
		a=1; b=1; bin=0;
		#1;
		check_result(0, gate_out, data_out, behav_out);
		check_borrow(0, gate_carry, data_carry, behav_carry);
		a=1; b=1; bin=1;
		#1;
		check_result(1, gate_out, data_out, behav_out);
		check_borrow(1, gate_carry, data_carry, behav_carry);

		#1;
		$finish;		

	end

	task check_result;
		input	expected_result;
		input	g_out;
		input	d_out;
		input	b_out;
		if(g_out != expected_result || d_out != expected_result || b_out != expected_result) begin
			$display("===== t=%d FAILED, output does not match =====", $time);
			$display("===== t=%d Expected output is %b, Actual gate output is %b, Actual dataflow output is %b, Actual behavioral output is %b =====",$time, expected_result, g_out, d_out, b_out);
		end
		else begin
			$display("===== t=%d PASSED SUCCESSFULLY =====",$time);
		end
	endtask

	task check_borrow;
		input	expected_borrow;
		input	g_borrow;
		input	d_borrow;
		input	b_borrow;
		if(g_borrow != expected_borrow || d_borrow != expected_borrow || b_borrow != expected_borrow) begin
			$display("===== t=%d FAILED, output does not match =====", $time);
			$display("===== t=%d Expected carry is %b, Actual gate carry is %b, Actual dataflow carry is %b, Actual behavioral carry is %b =====",$time, expected_borrow, g_borrow, d_borrow, b_borrow);
		end
		else begin
			$display("===== t=%d PASSED SUCCESSFULLY =====",$time);
		end
	endtask

endmodule

Homework2/subtractor_1bit/sim/wave18.vcd
$date
	Mon Sep 29 14:34:52 2025
$end
$version
	Icarus Verilog
$end
$timescale
	1s
$end
$scope module test_bench18 $end
$var wire 1 ! gate_out $end
$var wire 1 " gate_carry $end
$var wire 1 # data_out $end
$var wire 1 $ data_carry $end
$var wire 1 % behav_out $end
$var wire 1 & behav_carry $end
$var reg 1 ' a $end
$var reg 1 ( b $end
$var reg 1 ) bin $end
$scope module DUT $end
$var wire 1 ' a $end
$var wire 1 ( b $end
$var wire 1 ) bin $end
$var wire 1 $ data_carry $end
$var wire 1 # data_out $end
$var wire 1 * f1 $end
$var wire 1 + f2 $end
$var wire 1 , f3 $end
$var wire 1 " gate_carry $end
$var wire 1 ! gate_out $end
$var wire 1 - n_a $end
$var reg 1 & behav_carry $end
$var reg 1 % behav_out $end
$upscope $end
$scope task check_borrow $end
$var reg 1 . b_borrow $end
$var reg 1 / d_borrow $end
$var reg 1 0 expected_borrow $end
$var reg 1 1 g_borrow $end
$upscope $end
$scope task check_result $end
$var reg 1 2 b_out $end
$var reg 1 3 d_out $end
$var reg 1 4 expected_result $end
$var reg 1 5 g_out $end
$upscope $end
$upscope $end
$enddefinitions $end
#0
$dumpvars
x5
x4
x3
x2
x1
x0
x/
x.
1-
0,
0+
0*
0)
0(
0'
0&
0%
0$
0#
0"
0!
$end
#1
1$
1"
1!
1+
1#
1&
1%
1)
0.
0/
01
00
02
03
05
04
#2
0+
1*
0)
1(
1.
1/
11
10
12
13
15
14
#3
0!
1+
1,
0#
0%
1)
#4
0$
0"
0+
1#
0*
0,
1!
0-
0&
1%
0)
0(
1'
02
03
05
04
#5
0!
0#
0%
1)
0.
0/
01
00
12
13
15
14
#6
0)
1(
02
03
05
04
#7
1"
1$
1!
1,
1#
1&
1%
1)
#8
1.
1/
11
10
12
13
15
14
