Homework3/adder_subtractor_4bit/rtl/adder_subtractor_4bit.v
module adder_subtractor_4bit(
	input	wire	[3:0] 	a,
	input	wire	[3:0] 	b,
	input	wire		mode,		//mode 0 = add, mode 1 = sub
	output	wire	[3:0] 	gate_out,
	output	wire	[3:0] 	data_out,
	output	reg	[3:0] 	behav_out,
	output	wire	 	gate_carry,
	output	wire	 	data_carry,
	output	reg		behav_carry
);
	
	wire	gate_carry_1, gate_carry_2, gate_carry_3;
	wire	data_carry_1, data_carry_2, data_carry_3;
	reg	behav_carry_1, behav_carry_2, behav_carry_3;
	wire	f1_0, f2_0, f3_0, f1_1, f2_1, f3_1, f1_2, f2_2, f3_2, f1_3, f2_3, f3_3;
	wire	[3:0]	b_1, b_2;
	reg	[3:0]	b_3;
	
	//structural
	assign b_1 	= b ^ {4{mode}};
	xor(gate_out[0], a[0], b_1[0], mode);
	xor(gate_out[1], a[1], b_1[1], gate_carry_1);
	xor(gate_out[2], a[2], b_1[2], gate_carry_2);
	xor(gate_out[3], a[3], b_1[3], gate_carry_3);

	and(f1_0, a[0], b_1[0]);
	and(f2_0, a[0], mode);
	and(f3_0, mode, b_1[0]);
	or(gate_carry_1, f1_0, f2_0, f3_0);

	and(f1_1, a[1], b_1[1]);
	and(f2_1, a[1], gate_carry_1);
	and(f3_1, gate_carry_1, b_1[1]);
	or(gate_carry_2, f1_1, f2_1, f3_1);

	and(f1_2, a[2], b_1[2]);
	and(f2_2, a[2], gate_carry_2);
	and(f3_2, gate_carry_2, b_1[2]);
	or(gate_carry_3, f1_2, f2_2, f3_2);
		
	and(f1_3, a[3], b_1[3]);
	and(f2_3, a[3], gate_carry_3);
	and(f3_3, gate_carry_3, b_1[3]);
	or(gate_carry, f1_3, f2_3, f3_3);
	
	//dataflow
	assign b_2		= b ^ {4{mode}};
	assign data_out[0] 	= a[0] ^ b_2[0] ^ mode;
	assign data_carry_1	= (a[0] & b_2[0]) | (a[0] & mode) | (b_2[0] & mode);

	assign data_out[1] 	= a[1] ^ b_2[1] ^ data_carry_1;
	assign data_carry_2	= (a[1] & b_2[1]) | (a[1] & data_carry_1) | (b_2[1] & data_carry_1);

	assign data_out[2] 	= a[2] ^ b_2[2] ^ data_carry_2;
	assign data_carry_3	= (a[2] & b_2[2]) | (a[2] & data_carry_2) | (b_2[2] & data_carry_2);

	assign data_out[3] 	= a[3] ^ b_2[3] ^ data_carry_3;
	assign data_carry	= (a[3] & b_2[3]) | (a[3] & data_carry_3) | (b_2[3] & data_carry_3);

	//behavioral	
	always @(*) begin
		b_3		= b ^ {4{mode}};
		behav_out[0] 	= a[0] ^ b_3[0] ^ mode;
		behav_carry_1	= (a[0] & b_3[0]) | (a[0] & mode) | (b_3[0] & mode);
	end

	always @(*) begin
		behav_out[1] 	= a[1] ^ b_3[1] ^ behav_carry_1;
		behav_carry_2	= (a[1] & b_3[1]) | (a[1] & behav_carry_1) | (b_3[1] & behav_carry_1);
	end

	always @(*) begin
		behav_out[2] 	= a[2] ^ b_3[2] ^ behav_carry_2;
		behav_carry_3	= (a[2] & b_3[2]) | (a[2] & behav_carry_2) | (b_3[2] & behav_carry_2);
	end

	always @(*) begin
		behav_out[3] 	= a[3] ^ b_3[3] ^ behav_carry_3;
		behav_carry	= (a[3] & b_3[3]) | (a[3] & behav_carry_3) | (b_3[3] & behav_carry_3);
	end

	
endmodule

Homework3/adder_subtractor_4bit/tb/test_bench12.v
module test_bench12;

	reg	[3:0]	a, b;
	reg		mode;
	wire	[3:0]	gate_out, data_out, behav_out;
	wire		gate_carry, data_carry, behav_carry;
	integer		i, j, k;

	adder_subtractor_4bit DUT(.*);

	initial begin
		$dumpfile("wave.vcd");
        	$dumpvars(0,test_bench12);
        	$display("===== Test Adder/Subtractor 4 bits =====");
		$display("===== Initial State =====");
		$display("===== A = 4'b0000, B = 4'b0000, Mode = 1'b0 =====");
		a = 4'b0000; b = 4'b0000; mode = 1'b0;
		#1;
		if(gate_out!=4'b0000 || data_out!=4'b0000 || behav_out!=4'b0000) begin
			$display("===== t=%d FAILED, output does not match =====",$time);
			$display("===== t=%d Expected value is %2d, Actual gate_model value is %2d, Actual dataflow value is %2d, Actual behavioural model value is %2d =====", $time, 4'b0000, gate_out, data_out, behav_out);
		end
		else begin
			$display("===== t=%d PASSED SUCCESSFULLY =====", $time);
		end

		for (i = 0; i < 16; i = i + 1) begin
            		for (j = 0; j < 16; j = j + 1) begin
                		for (k = 0; k < 2; k = k + 1) begin
                    			a   = i;
       			                b   = j;
                    			mode = k;
                    			#1; 
					$monitor("\n===== t=%d With Mode = %b =====", $time, mode);
					if((gate_out != data_out) | (data_out != behav_out) | (gate_out != data_out)) begin
                    				$display("\n===== t=%d With A = %2d, B = %2d : Actual gate_model value is %2d, Actual dataflow value is %2d, Actual behavioural model value is %2d", $time, a, b, gate_out, data_out, behav_out);
						$finish;
					end
					else if((gate_carry != data_carry) | (data_carry != behav_carry) | (gate_carry != data_carry)) begin
						$display("===== t=%d Actual gate_model carry is %b, Actual dataflow carry is %b, Actual behavioural model carry is %b", $time, gate_carry, data_carry, behav_carry);
						$finish;
					end
					else begin
						$display("\n===== t=%d With A = %2d, B = %2d : Actual gate_model value is %2d, Actual dataflow value is %2d, Actual behavioural model value is %2d", $time, a, b, gate_out, data_out, behav_out);
						$display("===== t=%d Actual gate_model carry is %b, Actual dataflow carry is %b, Actual behavioural model carry is %b", $time, gate_carry, data_carry, behav_carry);
					end
                    		end
            		end
		end

	end

endmodule

Homework3/adder_subtractor_4bit/sim/wave.vcd
$date
	Fri Oct 10 20:23:39 2025
$end
$version
	Icarus Verilog
$end
$timescale
	1s
$end
$scope module test_bench12 $end
$var wire 4 ! gate_out [3:0] $end
$var wire 1 " gate_carry $end
$var wire 4 # data_out [3:0] $end
$var wire 1 $ data_carry $end
$var wire 4 % behav_out [3:0] $end
$var wire 1 & behav_carry $end
$var reg 4 ' a [3:0] $end
$var reg 4 ( b [3:0] $end
$var reg 1 ) mode $end
$var integer 32 * i [31:0] $end
$var integer 32 + j [31:0] $end
$var integer 32 , k [31:0] $end
$scope module DUT $end
$var wire 4 - a [3:0] $end
$var wire 4 . b [3:0] $end
$var wire 4 / b_1 [3:0] $end
$var wire 4 0 b_2 [3:0] $end
$var wire 1 $ data_carry $end
$var wire 1 1 data_carry_1 $end
$var wire 1 2 data_carry_2 $end
$var wire 1 3 data_carry_3 $end
$var wire 1 4 f1_0 $end
$var wire 1 5 f1_1 $end
$var wire 1 6 f1_2 $end
$var wire 1 7 f1_3 $end
$var wire 1 8 f2_0 $end
$var wire 1 9 f2_1 $end
$var wire 1 : f2_2 $end
$var wire 1 ; f2_3 $end
$var wire 1 < f3_0 $end
$var wire 1 = f3_1 $end
$var wire 1 > f3_2 $end
$var wire 1 ? f3_3 $end
$var wire 1 " gate_carry $end
$var wire 1 @ gate_carry_1 $end
$var wire 1 A gate_carry_2 $end
$var wire 1 B gate_carry_3 $end
$var wire 1 ) mode $end
$var wire 4 C gate_out [3:0] $end
$var wire 4 D data_out [3:0] $end
$var reg 4 E b_3 [3:0] $end
$var reg 1 & behav_carry $end
$var reg 1 F behav_carry_1 $end
$var reg 1 G behav_carry_2 $end
$var reg 1 H behav_carry_3 $end
$var reg 4 I behav_out [3:0] $end
$upscope $end
$upscope $end
$enddefinitions $end
#0
$dumpvars
b0 I
0H
0G
0F
b0 E
b0 D
b0 C
0B
0A
0@
0?
0>
0=
0<
0;
0:
09
08
07
06
05
04
03
02
01
b0 0
b0 /
b0 .
b0 -
bx ,
bx +
bx *
0)
b0 (
b0 '
0&
b0 %
0$
b0 #
0"
b0 !
$end
#1
b0 ,
b0 +
b0 *
#2
1"
1$
1?
1B
13
1>
1A
12
1=
1@
11
1<
1&
1H
1G
b0 !
b0 C
b0 #
b0 D
1F
b1111 E
b1111 /
b1111 0
1)
b1 ,
#3
0A
0B
0"
02
03
0$
0=
0>
0?
0@
01
0&
0H
0G
b1 !
b1 C
0<
b1 #
b1 D
b1 /
b1 0
0F
b1 %
b1 I
b1 E
0)
b1 (
b1 .
b1 +
b0 ,
#4
0"
0$
0?
0B
03
0>
0A
02
0=
0@
01
b1111 %
b1111 I
b1111 !
b1111 C
0<
b1111 #
b1111 D
b1110 E
b1110 /
b1110 0
1)
b1 ,
#5
b10 !
b10 C
b10 #
b10 D
b10 /
b10 0
b10 %
b10 I
b10 E
0)
b10 (
b10 .
b10 +
b0 ,
#6
1@
11
1<
b1110 %
b1110 I
b1110 !
b1110 C
b1110 #
b1110 D
1F
b1101 E
b1101 /
b1101 0
1)
b1 ,
#7
0@
01
b11 !
b11 C
0<
b11 #
b11 D
b11 /
b11 0
0F
b11 %
b11 I
b11 E
0)
b11 (
b11 .
b11 +
b0 ,
#8
0@
01
b1101 %
b1101 I
b1101 !
b1101 C
0<
b1101 #
b1101 D
b1100 E
b1100 /
b1100 0
1)
b1 ,
#9
b100 !
b100 C
b100 #
b100 D
b100 /
b100 0
b100 %
b100 I
b100 E
0)
b100 (
b100 .
b100 +
b0 ,
#10
1A
12
1=
1@
11
1<
b1100 %
b1100 I
1G
b1100 !
b1100 C
b1100 #
b1100 D
1F
b1011 E
b1011 /
b1011 0
1)
b1 ,
#11
0A
0B
02
03
0=
0>
0@
01
0G
b101 !
b101 C
0<
b101 #
b101 D
b101 /
b101 0
0F
b101 %
b101 I
b101 E
0)
b101 (
b101 .
b101 +
b0 ,
#12
0A
02
0=
0@
01
b1011 %
b1011 I
b1011 !
b1011 C
0<
b1011 #
b1011 D
b1010 E
b1010 /
b1010 0
1)
b1 ,
#13
b110 !
b110 C
b110 #
b110 D
b110 /
b110 0
b110 %
b110 I
b110 E
0)
b110 (
b110 .
b110 +
b0 ,
#14
1@
11
1<
b1010 %
b1010 I
b1010 !
b1010 C
b1010 #
b1010 D
1F
b1001 E
b1001 /
b1001 0
1)
b1 ,
#15
0@
01
b111 !
b111 C
0<
b111 #
b111 D
b111 /
b111 0
0F
b111 %
b111 I
b111 E
0)
b111 (
b111 .
b111 +
b0 ,
#16
0@
01
b1001 %
b1001 I
b1001 !
b1001 C
0<
b1001 #
b1001 D
b1000 E
b1000 /
b1000 0
1)
b1 ,
#17
b1000 !
b1000 C
b1000 #
b1000 D
b1000 %
b1000 I
0)
b1000 (
b1000 .
b1000 +
b0 ,
#18
1B
13
1>
1A
12
1=
1@
11
1<
1H
1G
b1000 !
b1000 C
b1000 #
b1000 D
1F
b111 E
b111 /
b111 0
1)
b1 ,
#19
0A
0B
0"
02
03
0$
0=
0>
0?
0@
01
0H
0G
b1001 !
b1001 C
0<
b1001 #
b1001 D
b1001 /
b1001 0
0F
b1001 %
b1001 I
b1001 E
0)
b1001 (
b1001 .
b1001 +
b0 ,
#20
0B
03
0>
0A
02
0=
0@
01
b111 %
b111 I
b111 !
b111 C
0<
b111 #
b111 D
b110 E
b110 /
b110 0
1)
b1 ,
#21
b1010 !
b1010 C
b1010 #
b1010 D
b1010 /
b1010 0
b1010 %
b1010 I
b1010 E
0)
b1010 (
b1010 .
b1010 +
b0 ,
#22
1@
11
1<
b110 %
b110 I
b110 !
b110 C
b110 #
b110 D
1F
b101 E
b101 /
b101 0
1)
b1 ,
#23
0@
01
b1011 !
b1011 C
0<
b1011 #
b1011 D
b1011 /
b1011 0
0F
b1011 %
b1011 I
b1011 E
0)
b1011 (
b1011 .
b1011 +
b0 ,
#24
0@
01
b101 %
b101 I
b101 !
b101 C
0<
b101 #
b101 D
b100 E
b100 /
b100 0
1)
b1 ,
#25
b1100 !
b1100 C
b1100 #
b1100 D
b1100 /
b1100 0
b1100 %
b1100 I
b1100 E
0)
b1100 (
b1100 .
b1100 +
b0 ,
#26
1A
12
1=
1@
11
1<
b100 %
b100 I
1G
b100 !
b100 C
b100 #
b100 D
1F
b11 E
b11 /
b11 0
1)
b1 ,
#27
0"
0$
0?
0A
0B
02
03
0=
0>
0@
01
0G
b1101 !
b1101 C
0<
b1101 #
b1101 D
b1101 /
b1101 0
0F
b1101 %
b1101 I
b1101 E
0)
b1101 (
b1101 .
b1101 +
b0 ,
#28
0A
02
0=
0@
01
b11 %
b11 I
b11 !
b11 C
0<
b11 #
b11 D
b10 E
b10 /
b10 0
1)
b1 ,
#29
b1110 !
b1110 C
b1110 #
b1110 D
b1110 /
b1110 0
b1110 %
b1110 I
b1110 E
0)
b1110 (
b1110 .
b1110 +
b0 ,
#30
1@
11
1<
b10 %
b10 I
b10 !
b10 C
b10 #
b10 D
1F
b1 E
b1 /
b1 0
1)
b1 ,
#31
0@
01
b1111 !
b1111 C
0<
b1111 #
b1111 D
b1111 /
b1111 0
0F
b1111 %
b1111 I
b1111 E
0)
b1111 (
b1111 .
b1111 +
b0 ,
#32
0@
01
b1 %
b1 I
b1 !
b1 C
0<
b1 #
b1 D
b0 E
b0 /
b0 0
1)
b1 ,
#33
b1 #
b1 D
0)
b0 (
b0 .
b1 '
b1 -
b1 *
b0 +
b0 ,
#34
1$
1"
13
1?
1B
12
1>
1A
11
14
1<
1=
1@
1&
1H
1G
b1 !
b1 C
18
b1 #
b1 D
1F
b1111 E
b1111 /
b1111 0
1)
b1 ,
#35
0A
0B
0"
02
03
0$
0=
0>
0?
0&
0H
0G
b10 !
b10 C
08
0<
b10 #
b10 D
b1 /
b1 0
b10 %
b10 I
b1 E
0)
b1 (
b1 .
b1 +
b0 ,
#36
1"
1$
1?
1B
13
1>
1A
12
04
1=
1&
1H
1G
b0 %
b0 I
b0 !
b0 C
18
0<
b0 #
b0 D
b1110 E
b1110 /
b1110 0
1)
b1 ,
#37
02
0A
0B
0"
03
0$
0=
01
0>
0?
0@
0&
0H
0G
b11 !
b11 C
08
b11 #
b11 D
b10 /
b10 0
0F
b11 %
b11 I
b10 E
0)
b10 (
b10 .
b10 +
b0 ,
#38
11
14
1<
1@
b1111 %
b1111 I
b1111 !
b1111 C
18
b1111 #
b1111 D
1F
b1101 E
b1101 /
b1101 0
1)
b1 ,
#39
1A
12
1=
1G
b100 !
b100 C
08
0<
b100 #
b100 D
b11 /
b11 0
b100 %
b100 I
b11 E
0)
b11 (
b11 .
b11 +
b0 ,
#40
0"
0$
0?
0A
0B
02
03
04
0=
0>
0G
b1110 %
b1110 I
b1110 !
b1110 C
18
0<
b1110 #
b1110 D
b1100 E
b1100 /
b1100 0
1)
b1 ,
#41
01
0@
b101 !
b101 C
08
b101 #
b101 D
b100 /
b100 0
0F
b101 %
b101 I
b100 E
0)
b100 (
b100 .
b100 +
b0 ,
#42
12
1A
11
14
1<
1=
1@
b1101 %
b1101 I
1G
b1101 !
b1101 C
18
b1101 #
b1101 D
1F
b1011 E
b1011 /
b1011 0
1)
b1 ,
#43
0A
0B
02
03
0=
0>
0G
b110 !
b110 C
08
0<
b110 #
b110 D
b101 /
b101 0
b110 %
b110 I
b101 E
0)
b101 (
b101 .
b101 +
b0 ,
#44
1A
12
04
1=
1G
b1100 %
b1100 I
b1100 !
b1100 C
18
0<
b1100 #
b1100 D
b1010 E
b1010 /
b1010 0
1)
b1 ,
#45
02
0A
0B
03
0=
01
0>
0@
0G
b111 !
b111 C
08
b111 #
b111 D
b110 /
b110 0
0F
b111 %
b111 I
b110 E
0)
b110 (
b110 .
b110 +
b0 ,
#46
11
14
1<
1@
b1011 %
b1011 I
b1011 !
b1011 C
18
b1011 #
b1011 D
1F
b1001 E
b1001 /
b1001 0
1)
b1 ,
#47
1B
13
1>
1A
12
1=
1H
1G
b1000 !
b1000 C
08
0<
b1000 #
b1000 D
b111 /
b111 0
b1000 %
b1000 I
b111 E
0)
b111 (
b111 .
b111 +
b0 ,
#48
0A
0B
0"
02
03
0$
04
0=
0>
0?
0H
0G
b1010 %
b1010 I
b1010 !
b1010 C
18
0<
b1010 #
b1010 D
b1000 E
b1000 /
b1000 0
1)
b1 ,
#49
01
0@
b1001 !
b1001 C
08
b1001 #
b1001 D
0F
b1001 %
b1001 I
0)
b1000 (
b1000 .
b1000 +
b0 ,
#50
13
1B
12
1>
1A
11
14
1<
1=
1@
1H
1G
b1001 !
b1001 C
18
b1001 #
b1001 D
1F
b111 E
b111 /
b111 0
1)
b1 ,
#51
0A
0B
0"
02
03
0$
0=
0>
0?
0H
0G
b1010 !
b1010 C
08
0<
b1010 #
b1010 D
b1001 /
b1001 0
b1010 %
b1010 I
b1001 E
0)
b1001 (
b1001 .
b1001 +
b0 ,
#52
1B
13
1>
1A
12
04
1=
1H
1G
b1000 %
b1000 I
b1000 !
b1000 C
18
0<
b1000 #
b1000 D
b110 E
b110 /
b110 0
1)
b1 ,
#53
02
0A
0B
0"
03
0$
0=
01
0>
0?
0@
0H
0G
b1011 !
b1011 C
08
b1011 #
b1011 D
b1010 /
b1010 0
0F
b1011 %
b1011 I
b1010 E
0)
b1010 (
b1010 .
b1010 +
b0 ,
#54
11
14
1<
1@
b111 %
b111 I
b111 !
b111 C
18
b111 #
b111 D
1F
b101 E
b101 /
b101 0
1)
b1 ,
#55
1A
12
1=
1G
b1100 !
b1100 C
08
0<
b1100 #
b1100 D
b1011 /
b1011 0
b1100 %
b1100 I
b1011 E
0)
b1011 (
b1011 .
b1011 +
b0 ,
#56
0A
0B
02
03
04
0=
0>
0G
b110 %
b110 I
b110 !
b110 C
18
0<
b110 #
b110 D
b100 E
b100 /
b100 0
1)
b1 ,
#57
01
0@
b1101 !
b1101 C
08
b1101 #
b1101 D
b1100 /
b1100 0
0F
b1101 %
b1101 I
b1100 E
0)
b1100 (
b1100 .
b1100 +
b0 ,
#58
12
1A
11
14
1<
1=
1@
b101 %
b101 I
1G
b101 !
b101 C
18
b101 #
b101 D
1F
b11 E
b11 /
b11 0
1)
b1 ,
#59
0"
0$
0?
0A
0B
02
03
0=
0>
0G
b1110 !
b1110 C
08
0<
b1110 #
b1110 D
b1101 /
b1101 0
b1110 %
b1110 I
b1101 E
0)
b1101 (
b1101 .
b1101 +
b0 ,
#60
1A
12
04
1=
1G
b100 %
b100 I
b100 !
b100 C
18
0<
b100 #
b100 D
b10 E
b10 /
b10 0
1)
b1 ,
#61
0"
0$
02
0?
0A
0B
03
0=
01
0>
0@
0G
b1111 !
b1111 C
08
b1111 #
b1111 D
b1110 /
b1110 0
0F
b1111 %
b1111 I
b1110 E
0)
b1110 (
b1110 .
b1110 +
b0 ,
#62
11
14
1<
1@
b11 %
b11 I
b11 !
b11 C
18
b11 #
b11 D
1F
b1 E
b1 /
b1 0
1)
b1 ,
#63
1"
1$
1?
1B
13
1>
1A
12
1=
1&
1H
1G
b0 !
b0 C
08
0<
b0 #
b0 D
b1111 /
b1111 0
b0 %
b0 I
b1111 E
0)
b1111 (
b1111 .
b1111 +
b0 ,
#64
0A
0B
0"
02
03
0$
04
0=
0>
0?
0&
0H
0G
b10 %
b10 I
b10 !
b10 C
18
0<
b10 #
b10 D
b0 E
b0 /
b0 0
1)
b1 ,
#65
02
01
0A
0@
b10 !
b10 C
09
08
b10 #
b10 D
0F
0)
b0 (
b0 .
b10 '
b10 -
b10 *
b0 +
b0 ,
#66
1$
1"
1?
13
1B
19
1=
1>
12
1@
1A
11
1<
15
1&
1H
1G
b10 !
b10 C
b10 #
b10 D
1F
b1111 E
b1111 /
b1111 0
1)
b1 ,
#67
02
0A
0B
0"
03
0$
09
05
0=
0>
0?
0@
01
0&
0H
0G
b11 !
b11 C
0<
b11 #
b11 D
b1 /
b1 0
0F
b11 %
b11 I
b1 E
0)
b1 (
b1 .
b1 +
b0 ,
#68
1"
1$
1?
1B
13
1>
1A
12
09
15
0=
0@
01
1&
1H
1G
b1 %
b1 I
b1 !
b1 C
0<
b1 #
b1 D
b1110 E
b1110 /
b1110 0
1)
b1 ,
#69
0B
0"
03
0$
0>
0?
0&
0H
b100 !
b100 C
b100 #
b100 D
b10 /
b10 0
b100 %
b100 I
b10 E
0)
b10 (
b10 .
b10 +
b0 ,
#70
1"
1$
19
1?
12
1@
1A
1B
11
13
1<
05
1>
1&
1H
b0 %
b0 I
b0 !
b0 C
b0 #
b0 D
1F
b1101 E
b1101 /
b1101 0
1)
b1 ,
#71
0B
0"
03
0$
09
15
0>
0?
0@
01
0&
0H
b101 !
b101 C
0<
b101 #
b101 D
b11 /
b11 0
0F
b101 %
b101 I
b11 E
0)
b11 (
b11 .
b11 +
b0 ,
#72
02
0A
0"
0$
0?
0B
03
09
05
0>
0@
01
0G
b1111 %
b1111 I
b1111 !
b1111 C
0<
b1111 #
b1111 D
b1100 E
b1100 /
b1100 0
1)
b1 ,
#73
b110 !
b110 C
b110 #
b110 D
b100 /
b100 0
b110 %
b110 I
b100 E
0)
b100 (
b100 .
b100 +
b0 ,
#74
19
1=
12
1@
1A
11
1<
15
b1110 %
b1110 I
1G
b1110 !
b1110 C
b1110 #
b1110 D
1F
b1011 E
b1011 /
b1011 0
1)
b1 ,
#75
02
0A
0B
03
09
05
0=
0>
0@
01
0G
b111 !
b111 C
0<
b111 #
b111 D
b101 /
b101 0
0F
b111 %
b111 I
b101 E
0)
b101 (
b101 .
b101 +
b0 ,
#76
1A
12
09
15
0=
0@
01
1G
b1101 %
b1101 I
b1101 !
b1101 C
0<
b1101 #
b1101 D
b1010 E
b1010 /
b1010 0
1)
b1 ,
#77
1B
13
1>
1H
b1000 !
b1000 C
b1000 #
b1000 D
b110 /
b110 0
b1000 %
b1000 I
b110 E
0)
b110 (
b110 .
b110 +
b0 ,
#78
19
12
1@
1A
0B
0"
11
03
0$
1<
05
0>
0?
0H
b1100 %
b1100 I
b1100 !
b1100 C
b1100 #
b1100 D
1F
b1001 E
b1001 /
b1001 0
1)
b1 ,
#79
1B
13
09
15
1>
0@
01
1H
b1001 !
b1001 C
0<
b1001 #
b1001 D
b111 /
b111 0
0F
b1001 %
b1001 I
b111 E
0)
b111 (
b111 .
b111 +
b0 ,
#80
02
0A
0B
0"
03
0$
09
05
0>
0?
0@
01
0H
0G
b1011 %
b1011 I
b1011 !
b1011 C
0<
b1011 #
b1011 D
b1000 E
b1000 /
b1000 0
1)
b1 ,
#81
b1010 !
b1010 C
b1010 #
b1010 D
b1010 %
b1010 I
0)
b1000 (
b1000 .
b1000 +
b0 ,
#82
13
1B
19
1=
1>
12
1@
1A
11
1<
15
1H
1G
b1010 !
b1010 C
b1010 #
b1010 D
1F
b111 E
b111 /
b111 0
1)
b1 ,
#83
02
0A
0B
0"
03
0$
09
05
0=
0>
0?
0@
01
0H
0G
b1011 !
b1011 C
0<
b1011 #
b1011 D
b1001 /
b1001 0
0F
b1011 %
b1011 I
b1001 E
0)
b1001 (
b1001 .
b1001 +
b0 ,
#84
1B
13
1>
1A
12
09
15
0=
0@
01
1H
1G
b1001 %
b1001 I
b1001 !
b1001 C
0<
b1001 #
b1001 D
b110 E
b110 /
b110 0
1)
b1 ,
#85
0B
0"
03
0$
0>
0?
0H
b1100 !
b1100 C
b1100 #
b1100 D
b1010 /
b1010 0
b1100 %
b1100 I
b1010 E
0)
b1010 (
b1010 .
b1010 +
b0 ,
#86
19
12
1@
1A
1B
11
13
1<
05
1>
1H
b1000 %
b1000 I
b1000 !
b1000 C
b1000 #
b1000 D
1F
b101 E
b101 /
b101 0
1)
b1 ,
#87
0B
0"
03
0$
09
15
0>
0?
0@
01
0H
b1101 !
b1101 C
0<
b1101 #
b1101 D
b1011 /
b1011 0
0F
b1101 %
b1101 I
b1011 E
0)
b1011 (
b1011 .
b1011 +
b0 ,
#88
02
0A
0B
03
09
05
0>
0@
01
0G
b111 %
b111 I
b111 !
b111 C
0<
b111 #
b111 D
b100 E
b100 /
b100 0
1)
b1 ,
#89
b1110 !
b1110 C
b1110 #
b1110 D
b1100 /
b1100 0
b1110 %
b1110 I
b1100 E
0)
b1100 (
b1100 .
b1100 +
b0 ,
#90
19
1=
12
1@
1A
11
1<
15
b110 %
b110 I
1G
b110 !
b110 C
b110 #
b110 D
1F
b11 E
b11 /
b11 0
1)
b1 ,
#91
0"
0$
0?
02
0A
0B
03
09
05
0=
0>
0@
01
0G
b1111 !
b1111 C
0<
b1111 #
b1111 D
b1101 /
b1101 0
0F
b1111 %
b1111 I
b1101 E
0)
b1101 (
b1101 .
b1101 +
b0 ,
#92
1A
12
09
15
0=
0@
01
1G
b101 %
b101 I
b101 !
b101 C
0<
b101 #
b101 D
b10 E
b10 /
b10 0
1)
b1 ,
#93
1"
1$
1?
1B
13
1>
1&
1H
b0 !
b0 C
b0 #
b0 D
b1110 /
b1110 0
b0 %
b0 I
b1110 E
0)
b1110 (
b1110 .
b1110 +
b0 ,
#94
19
12
1@
1A
0B
0"
11
03
0$
1<
05
0>
0?
0&
0H
b100 %
b100 I
b100 !
b100 C
b100 #
b100 D
1F
b1 E
b1 /
b1 0
1)
b1 ,
#95
1"
1$
1?
1B
13
09
15
1>
0@
01
1&
1H
b1 !
b1 C
0<
b1 #
b1 D
b1111 /
b1111 0
0F
b1 %
b1 I
b1111 E
0)
b1111 (
b1111 .
b1111 +
b0 ,
#96
02
0A
0B
0"
03
0$
09
05
0>
0?
0@
01
0&
0H
0G
b11 %
b11 I
b11 !
b11 C
0<
b11 #
b11 D
b0 E
b0 /
b0 0
1)
b1 ,
#97
b11 #
b11 D
0)
b0 (
b0 .
b11 '
b11 -
b11 *
b0 +
b0 ,
#98
1$
1"
1?
13
1B
1>
12
1A
19
11
14
1<
15
1=
1@
1&
1H
1G
b11 !
b11 C
18
b11 #
b11 D
1F
b1111 E
b1111 /
b1111 0
1)
b1 ,
#99
0B
0"
03
0$
05
0=
0>
0?
0&
0H
b100 !
b100 C
08
0<
b100 #
b100 D
b1 /
b1 0
b100 %
b100 I
b1 E
0)
b1 (
b1 .
b1 +
b0 ,
#100
1"
1$
1?
1B
13
04
15
1=
1>
1&
1H
b10 %
b10 I
b10 !
b10 C
18
0<
b10 #
b10 D
b1110 E
b1110 /
b1110 0
1)
b1 ,
#101
0B
0"
03
0$
09
0=
01
0>
0?
0@
0&
0H
b101 !
b101 C
08
b101 #
b101 D
b10 /
b10 0
0F
b101 %
b101 I
b10 E
0)
b10 (
b10 .
b10 +
b0 ,
#102
1"
1$
1?
12
1B
13
19
11
14
1<
05
1>
1@
1&
1H
b1 %
b1 I
b1 !
b1 C
18
b1 #
b1 D
1F
b1101 E
b1101 /
b1101 0
1)
b1 ,
#103
0B
0"
03
0$
15
1=
0>
0?
0&
0H
b110 !
b110 C
08
0<
b110 #
b110 D
b11 /
b11 0
b110 %
b110 I
b11 E
0)
b11 (
b11 .
b11 +
b0 ,
#104
1"
1$
1?
1B
13
04
05
0=
1>
1&
1H
b0 %
b0 I
b0 !
b0 C
18
0<
b0 #
b0 D
b1100 E
b1100 /
b1100 0
1)
b1 ,
#105
03
0B
02
0>
0A
0"
0$
09
01
0?
0@
0&
0H
0G
b111 !
b111 C
08
b111 #
b111 D
b100 /
b100 0
0F
b111 %
b111 I
b100 E
0)
b100 (
b100 .
b100 +
b0 ,
#106
12
1A
19
11
14
1<
15
1=
1@
b1111 %
b1111 I
1G
b1111 !
b1111 C
18
b1111 #
b1111 D
1F
b1011 E
b1011 /
b1011 0
1)
b1 ,
#107
1B
13
05
0=
1>
1H
b1000 !
b1000 C
08
0<
b1000 #
b1000 D
b101 /
b101 0
b1000 %
b1000 I
b101 E
0)
b101 (
b101 .
b101 +
b0 ,
#108
0B
0"
03
0$
04
15
1=
0>
0?
0H
b1110 %
b1110 I
b1110 !
b1110 C
18
0<
b1110 #
b1110 D
b1010 E
b1010 /
b1010 0
1)
b1 ,
#109
1B
13
09
0=
01
1>
0@
1H
b1001 !
b1001 C
08
b1001 #
b1001 D
b110 /
b110 0
0F
b1001 %
b1001 I
b110 E
0)
b110 (
b110 .
b110 +
b0 ,
#110
12
0B
0"
03
0$
19
11
14
1<
05
0>
0?
1@
0H
b1101 %
b1101 I
b1101 !
b1101 C
18
b1101 #
b1101 D
1F
b1001 E
b1001 /
b1001 0
1)
b1 ,
#111
1B
13
15
1=
1>
1H
b1010 !
b1010 C
08
0<
b1010 #
b1010 D
b111 /
b111 0
b1010 %
b1010 I
b111 E
0)
b111 (
b111 .
b111 +
b0 ,
#112
0B
0"
03
0$
04
05
0=
0>
0?
0H
b1100 %
b1100 I
b1100 !
b1100 C
18
0<
b1100 #
b1100 D
b1000 E
b1000 /
b1000 0
1)
b1 ,
#113
02
0A
09
01
0@
0G
b1011 !
b1011 C
08
b1011 #
b1011 D
0F
b1011 %
b1011 I
0)
b1000 (
b1000 .
b1000 +
b0 ,
#114
13
1B
1>
12
1A
19
11
14
1<
15
1=
1@
1H
1G
b1011 !
b1011 C
18
b1011 #
b1011 D
1F
b111 E
b111 /
b111 0
1)
b1 ,
#115
0B
0"
03
0$
05
0=
0>
0?
0H
b1100 !
b1100 C
08
0<
b1100 #
b1100 D
b1001 /
b1001 0
b1100 %
b1100 I
b1001 E
0)
b1001 (
b1001 .
b1001 +
b0 ,
#116
1B
13
04
15
1=
1>
1H
b1010 %
b1010 I
b1010 !
b1010 C
18
0<
b1010 #
b1010 D
b110 E
b110 /
b110 0
1)
b1 ,
#117
0B
0"
03
0$
09
0=
01
0>
0?
0@
0H
b1101 !
b1101 C
08
b1101 #
b1101 D
b1010 /
b1010 0
0F
b1101 %
b1101 I
b1010 E
0)
b1010 (
b1010 .
b1010 +
b0 ,
#118
12
1B
13
19
11
14
1<
05
1>
1@
1H
b1001 %
b1001 I
b1001 !
b1001 C
18
b1001 #
b1001 D
1F
b101 E
b101 /
b101 0
1)
b1 ,
#119
0B
0"
03
0$
15
1=
0>
0?
0H
b1110 !
b1110 C
08
0<
b1110 #
b1110 D
b1011 /
b1011 0
b1110 %
b1110 I
b1011 E
0)
b1011 (
b1011 .
b1011 +
b0 ,
