Homework1/rtl/first_module.v
module first_module(
	input 	wire	A,
	input	wire	B,
	input	wire	C,
	output	wire	F
);

	wire	F1, F2, F3;

	assign F1 = A && B && C;
	assign F2 = A && B && ~C;
	assign F3 = ~A && C;	

	assign F = F1 || F2 || F3;

endmodule

Homework1/tb/test_bench1.v
module test_bench1;

	reg 	A, B, C;
	wire	F;	

	first_module DUT(.*);

	initial begin
		$dumpfile("wave1.vcd");     
        	$dumpvars(0, test_bench1);
		$monitor("===== t=%d  A = %b, B = %b, C = %b, F = %b =====", $time, A, B, C, F);
		A = 0; B = 0; C = 0;
		#1;
		A = 0; B = 0; C = 1;
		#1;
		A = 0; B = 1; C = 0;
		#1;
		A = 0; B = 1; C = 1;
		#1;
		A = 1; B = 0; C = 0;
		#1;
		A = 1; B = 0; C = 1;
		#1;
		A = 1; B = 1; C = 0;
		#1;
		A = 1; B = 1; C = 1;
		#1;
		$finish;
	end

endmodule

Homework1/sim/wave1.vcd
$date
	Mon Sep 22 19:36:03 2025
$end
$version
	Icarus Verilog
$end
$timescale
	1s
$end
$scope module test_bench1 $end
$var wire 1 ! F $end
$var reg 1 " A $end
$var reg 1 # B $end
$var reg 1 $ C $end
$scope module DUT $end
$var wire 1 " A $end
$var wire 1 # B $end
$var wire 1 $ C $end
$var wire 1 ! F $end
$var wire 1 % F1 $end
$var wire 1 & F2 $end
$var wire 1 ' F3 $end
$upscope $end
$upscope $end
$enddefinitions $end
#0
$dumpvars
0'
0&
0%
0$
0#
0"
0!
$end
#1
1!
1'
1$
#2
0!
0'
0$
1#
#3
1!
1'
1$
#4
0!
0'
0$
0#
1"
#5
1$
#6
1!
1&
0$
1#
#7
0&
1%
1$
