Homework3/booth_multiplier/rtl/full_adder.v
module full_adder(
	input	wire	a,
	input 	wire	b,
	input 	wire	cin,
	output	wire	sum,
	output	wire	carry
);

	wire carry_1, carry_2, sum_1;	
	
	assign sum_1 = a ^ b;
	assign carry_1 = a & b;

	//half_adder_2
	assign carry_2 = sum_1 & cin;

	//full_adder
	assign sum = sum_1 ^ cin;
	assign carry = carry_1 | carry_2;

endmodule

Homework3/booth_multiplier/rtl/half_adder.v
module half_adder(
	input	wire	a,
	input 	wire	b,
	output	wire	sum,
	output	wire	carry
);

	assign sum = a ^ b;
	assign carry = a & b;

endmodule

Homework3/booth_multiplier/rtl/booth_multiplier.v
module booth_multiplier(
	input	wire	[3:0]	Q,
	input	wire	[3:0]	M,
	output	wire	[7:0]	gate_out,
	output	wire	[7:0]	data_out,
	output	reg	[7:0]	behav_out
);
	reg 		[3:0]	A;
	wire		[10:0]	c;
	wire		[5:0]	s;
	reg		[3:0]	Q_reg;
	wire  		[7:0] 	M_ext;
	genvar 			g;
	integer 		i;
	reg			q_1;
	wire			Q_1;

	wire 		[3:0] 	p0, p1, p2, p3;
	wire 		[7:0] 	pp0, pp1, pp2, pp3;

	and(p0[0], Q[0], M[0]);
	and(p0[1], Q[0], M[1]);
	and(p0[2], Q[0], M[2]);
	and(p0[3], Q[0], M[3]);

	and(p1[0], Q[1], M[0]);
	and(p1[1], Q[1], M[1]);
	and(p1[2], Q[1], M[2]);
	and(p1[3], Q[1], M[3]);

	and(p2[0], Q[2], M[0]);
	and(p2[1], Q[2], M[1]);
	and(p2[2], Q[2], M[2]);
	and(p2[3], Q[2], M[3]);

	and(p3[0], Q[3], M[0]);
	and(p3[1], Q[3], M[1]);
	and(p3[2], Q[3], M[2]);
	and(p3[3], Q[3], M[3]);

	assign gate_out[0] = p0[0];
	
	//row0
	half_adder ha0(
		.a(p0[1]), 
		.b(p1[0]), 
		.sum(gate_out[1]), 
		.carry(c[0])
	);
	half_adder ha1(
		.a(p1[1]), 
		.b(p2[0]), 
		.sum(s[0]), 
		.carry(c[1])
	);
	half_adder ha2(
		.a(p2[1]), 
		.b(p3[0]), 
		.sum(s[1]), 
		.carry(c[2])
	);
		
	//row1
	full_adder fa0(
		.a(p0[2]), 
		.b(c[0]), 
		.cin(s[0]), 
		.sum(gate_out[2]), 
		.carry(c[3])
	);

	full_adder fa1(
		.a(p1[2]), 
		.b(c[1]), 
		.cin(s[1]), 
		.sum(s[2]), 
		.carry(c[4])
	);

    	full_adder fa2(
		.a(p2[2]), 
		.b(c[2]), 
		.cin(p3[1]), 
		.sum(s[3]), 
		.carry(c[5])
	);

	//row2
	full_adder fa3(
		.a(p0[3]),
		.b(c[3]),
		.cin(s[2]),
		.sum(gate_out[3]),
		.carry(c[6])
	);
	full_adder fa4(
		.a(p1[3]),
		.b(c[4]),
		.cin(s[3]),
		.sum(s[4]),
		.carry(c[7])
	);
	full_adder fa5(
		.a(p2[3]),
		.b(c[5]),
		.cin(p3[2]),
		.sum(s[5]),
		.carry(c[8])
	);

	//row3
	half_adder ha3(
		.a(c[6]), 
		.b(s[4]), 
		.sum(gate_out[4]), 
		.carry(c[9])
	);

	full_adder fa6(
		.a(c[9]), 
		.b(c[7]), 
		.cin(s[5]), 
		.sum(gate_out[5]), 
		.carry(c[10])
	);

	full_adder fa7(
		.a(c[10]),
		.b(c[8]), 
		.cin(p3[3]), 
		.sum(gate_out[6]), 
		.carry(gate_out[7])
	);

	//dataflow
	assign M_ext	= 	{{4{M[3]}}, M};
	assign Q_1	= 	1'b0;

	assign pp0 	= 	({Q[0], Q_1} == 2'b01) ? $signed(M_ext << 0) :
                 		({Q[0], Q_1} == 2'b10) ? $signed((~M_ext + 1) << 0) : 
				8'sb0;

   	assign pp1 	= 	({Q[1], Q[0]} == 2'b01) ? $signed(M_ext << 1) :
                 		({Q[1], Q[0]} == 2'b10) ? $signed((~M_ext + 1) << 1) : 
				8'sb0;

    	assign pp2 	= 	({Q[2], Q[1]} == 2'b01) ? $signed(M_ext << 2) :
                 		({Q[2], Q[1]} == 2'b10) ? $signed((~M_ext + 1) << 2) : 
				8'sb0;

    	assign pp3 	= 	({Q[3], Q[2]} == 2'b01) ? $signed(M_ext << 3) :
                 		({Q[3], Q[2]} == 2'b10) ? $signed((~M_ext + 1) << 3) : 
				8'sb0;

	assign data_out = $signed(pp0) + $signed(pp1) + $signed(pp2) + $signed(pp3);

	always @(*) begin
		A = 4'b0;
		Q_reg = Q;
		q_1 = 1'b0;

		for (i = 0; i < 4; i = i + 1) begin
			case ({Q_reg[0], q_1})
				2'b01: 		A = A + M; 
				2'b10: 		A = A - M; 
				default: 	A = A; 
			endcase
			q_1 = Q_reg[0];
    			{A, Q_reg} = {A, Q_reg} >>> 1;
		end
		behav_out = {A, Q_reg};
	end	
endmodule

Homework3/booth_multiplier/tb/test_bench.v
module test_bench;

	reg	[3:0]	Q, M;
	wire	[7:0]	gate_out, data_out, behav_out;
	integer		i, j;

	booth_multiplier DUT(.*);

	initial begin
		$dumpfile("wave.vcd");
		$dumpvars(0,test_bench);
		$display("===== Test Booth Multiplier =====");
		$monitor("===== Q = %4b, M = %4b =====", Q, M);
		for(i = 0; i < 16; i = i + 1) begin
			for(j = 0; j < 16; j = j + 1) begin
				M = i[3:0];
               			Q = j[3:0];
               			#1;
                		check_result(M * Q, gate_out, data_out, behav_out);
			end
		end
		$display("===== t=%d Finished Stimulation =====",$time);
		$finish;
	end

	task check_result;
		input	[7:0]	result;
		input	[7:0]	e;
		input	[7:0]	f;
		input	[7:0]	g;

		if(e!=result | f!=result | g!=result) begin
			$display("===== t=%d FAILED, output does not match =====",$time);
			$display("===== t=%d Expected value is %b, Actual gate value is %b, Actual data value is %b, Actual behavioral value is %b =====",$time, result, e, f, g);
		end
		else begin
			$display("===== t=%d PASSED SUCCESSFULLY =====",$time);
		end
	endtask
	
endmodule

Homework3/booth_multiplier/sim/wave.vcd
$date
	Fri Oct 10 21:07:01 2025
$end
$version
	Icarus Verilog
$end
$timescale
	1s
$end
$scope module test_bench $end
$var wire 8 ! gate_out [7:0] $end
$var wire 8 " data_out [7:0] $end
$var wire 8 # behav_out [7:0] $end
$var reg 4 $ M [3:0] $end
$var reg 4 % Q [3:0] $end
$var integer 32 & i [31:0] $end
$var integer 32 ' j [31:0] $end
$scope module DUT $end
$var wire 4 ( M [3:0] $end
$var wire 4 ) Q [3:0] $end
$var wire 1 * Q_1 $end
$var wire 6 + s [5:0] $end
$var wire 8 , pp3 [7:0] $end
$var wire 8 - pp2 [7:0] $end
$var wire 8 . pp1 [7:0] $end
$var wire 8 / pp0 [7:0] $end
$var wire 4 0 p3 [3:0] $end
$var wire 4 1 p2 [3:0] $end
$var wire 4 2 p1 [3:0] $end
$var wire 4 3 p0 [3:0] $end
$var wire 8 4 gate_out [7:0] $end
$var wire 8 5 data_out [7:0] $end
$var wire 11 6 c [10:0] $end
$var wire 8 7 M_ext [7:0] $end
$var reg 4 8 A [3:0] $end
$var reg 4 9 Q_reg [3:0] $end
$var reg 8 : behav_out [7:0] $end
$var reg 1 ; q_1 $end
$var integer 32 < i [31:0] $end
$scope module fa0 $end
$var wire 1 = a $end
$var wire 1 > b $end
$var wire 1 ? carry $end
$var wire 1 @ carry_1 $end
$var wire 1 A carry_2 $end
$var wire 1 B cin $end
$var wire 1 C sum $end
$var wire 1 D sum_1 $end
$upscope $end
$scope module fa1 $end
$var wire 1 E a $end
$var wire 1 F b $end
$var wire 1 G carry $end
$var wire 1 H carry_1 $end
$var wire 1 I carry_2 $end
$var wire 1 J cin $end
$var wire 1 K sum $end
$var wire 1 L sum_1 $end
$upscope $end
$scope module fa2 $end
$var wire 1 M a $end
$var wire 1 N b $end
$var wire 1 O carry $end
$var wire 1 P carry_1 $end
$var wire 1 Q carry_2 $end
$var wire 1 R cin $end
$var wire 1 S sum $end
$var wire 1 T sum_1 $end
$upscope $end
$scope module fa3 $end
$var wire 1 U a $end
$var wire 1 V b $end
$var wire 1 W carry $end
$var wire 1 X carry_1 $end
$var wire 1 Y carry_2 $end
$var wire 1 Z cin $end
$var wire 1 [ sum $end
$var wire 1 \ sum_1 $end
$upscope $end
$scope module fa4 $end
$var wire 1 ] a $end
$var wire 1 ^ b $end
$var wire 1 _ carry $end
$var wire 1 ` carry_1 $end
$var wire 1 a carry_2 $end
$var wire 1 b cin $end
$var wire 1 c sum $end
$var wire 1 d sum_1 $end
$upscope $end
$scope module fa5 $end
$var wire 1 e a $end
$var wire 1 f b $end
$var wire 1 g carry $end
$var wire 1 h carry_1 $end
$var wire 1 i carry_2 $end
$var wire 1 j cin $end
$var wire 1 k sum $end
$var wire 1 l sum_1 $end
$upscope $end
$scope module fa6 $end
$var wire 1 m a $end
$var wire 1 n b $end
$var wire 1 o carry $end
$var wire 1 p carry_1 $end
$var wire 1 q carry_2 $end
$var wire 1 r cin $end
$var wire 1 s sum $end
$var wire 1 t sum_1 $end
$upscope $end
$scope module fa7 $end
$var wire 1 u a $end
$var wire 1 v b $end
$var wire 1 w carry $end
$var wire 1 x carry_1 $end
$var wire 1 y carry_2 $end
$var wire 1 z cin $end
$var wire 1 { sum $end
$var wire 1 | sum_1 $end
$upscope $end
$scope module ha0 $end
$var wire 1 } a $end
$var wire 1 ~ b $end
$var wire 1 !" carry $end
$var wire 1 "" sum $end
$upscope $end
$scope module ha1 $end
$var wire 1 #" a $end
$var wire 1 $" b $end
$var wire 1 %" carry $end
$var wire 1 &" sum $end
$upscope $end
$scope module ha2 $end
$var wire 1 '" a $end
$var wire 1 (" b $end
$var wire 1 )" carry $end
$var wire 1 *" sum $end
$upscope $end
$scope module ha3 $end
$var wire 1 +" a $end
$var wire 1 ," b $end
$var wire 1 -" carry $end
$var wire 1 ." sum $end
$upscope $end
$upscope $end
$scope task check_result $end
$var reg 8 /" e [7:0] $end
$var reg 8 0" f [7:0] $end
$var reg 8 1" g [7:0] $end
$var reg 8 2" result [7:0] $end
$upscope $end
$upscope $end
$enddefinitions $end
#0
$dumpvars
bx 2"
bx 1"
bx 0"
bx /"
0."
0-"
0,"
0+"
0*"
0)"
0("
0'"
0&"
0%"
0$"
0#"
0""
0!"
0~
0}
0|
0{
0z
0y
0x
0w
0v
0u
0t
0s
0r
0q
0p
0o
0n
0m
0l
0k
0j
0i
0h
0g
0f
0e
0d
0c
0b
0a
0`
0_
0^
0]
0\
0[
0Z
0Y
0X
0W
0V
0U
0T
0S
0R
0Q
0P
0O
0N
0M
0L
0K
0J
0I
0H
0G
0F
0E
0D
0C
0B
0A
0@
0?
0>
0=
b100 <
0;
b0 :
b0 9
b0 8
b0 7
b0 6
b0 5
b0 4
b0 3
b0 2
b0 1
b0 0
b0 /
b0 .
b0 -
b0 ,
b0 +
0*
b0 )
b0 (
b0 '
b0 &
b0 %
b0 $
b0 #
b0 "
b0 !
$end
#1
0;
b100 <
b0 9
b1 %
b1 )
b1 '
b0 1"
b0 0"
b0 /"
b0 2"
#2
0;
b100 <
b0 9
b10 %
b10 )
b10 '
#3
0;
b100 <
b0 9
b11 %
b11 )
b11 '
#4
0;
b100 <
b0 9
b100 %
b100 )
b100 '
#5
0;
b100 <
b0 9
b101 %
b101 )
b101 '
#6
0;
b100 <
b0 9
b110 %
b110 )
b110 '
#7
0;
b100 <
b0 9
b111 %
b111 )
b111 '
#8
1;
b100 <
b0 9
b1000 %
b1000 )
b1000 '
#9
b100 <
1;
b0 9
b1001 %
b1001 )
b1001 '
#10
b100 <
1;
b0 9
b1010 %
b1010 )
b1010 '
#11
b100 <
1;
b0 9
b1011 %
b1011 )
b1011 '
#12
b100 <
1;
b0 9
b1100 %
b1100 )
b1100 '
#13
b100 <
1;
b0 9
b1101 %
b1101 )
b1101 '
#14
b100 <
1;
b0 9
b1110 %
b1110 )
b1110 '
#15
b100 <
1;
b0 9
b1111 %
b1111 )
b1111 '
#16
b100 <
0;
b0 %
b0 )
b1 7
b1 $
b1 (
b1 &
b0 '
#17
b1 !
b1 4
b11111111 /
b1 3
b1 "
b1 5
b10 .
b10001 #
b10001 :
0;
b1 8
b100 <
b1 9
b1 %
b1 )
b1 '
#18
1""
b10 !
b10 4
1~
b0 /
b0 3
b1 2
b11111110 .
b10 "
b10 5
b100 -
b100010 #
b100010 :
0;
b100 <
b10 9
b10 8
b10 %
b10 )
b10 '
b10001 1"
b1 0"
b1 /"
b1 2"
#19
b11 !
b11 4
b11111111 /
b11 "
b11 5
b0 .
b1 3
b10011 #
b10011 :
0;
b100 <
b11 9
b1 8
b11 %
b11 )
b11 '
b100010 1"
b10 0"
b10 /"
b10 2"
#20
1C
1B
0""
b1 +
1&"
b100 !
b100 4
0~
1$"
b0 /
b0 3
b0 2
b1 1
b11111100 -
b100 "
b100 5
b1000 ,
b1000100 #
b1000100 :
0;
b100 <
b100 9
b100 8
b100 %
b100 )
b100 '
b10011 1"
b11 0"
b11 /"
b11 2"
#21
b101 !
b101 4
b11111111 /
b1 3
b101 "
b101 5
b10 .
b10101 #
b10101 :
0;
b100 <
b101 9
b1 8
b101 %
b101 )
b101 '
b1000100 1"
b100 0"
b100 /"
b100 2"
#22
1""
b110 !
b110 4
1~
b0 /
b0 -
b0 3
b1 2
b110 "
b110 5
b11111110 .
b100110 #
b100110 :
0;
b100 <
b110 9
b10 8
b110 %
b110 )
b110 '
b10101 1"
b101 0"
b101 /"
b101 2"
#23
b111 !
b111 4
b11111111 /
b111 "
b111 5
b0 .
b1 3
b10111 #
b10111 :
0;
b100 <
b111 9
b1 8
b111 %
b111 )
b111 '
b100110 1"
b110 0"
b110 /"
b110 2"
#24
1[
1Z
0C
1K
0B
1J
0""
0&"
b110 +
1*"
b1000 !
b1000 4
0~
0$"
1("
b0 /
b0 3
b0 2
b0 1
b1 0
b11111000 "
b11111000 5
b11111000 ,
b1111000 #
b1111000 :
1;
b100 <
b1000 9
b111 8
b1000 %
b1000 )
b1000 '
b10111 1"
b111 0"
b111 /"
b111 2"
#25
b1001 !
b1001 4
b11111111 /
b1 3
b11111001 "
b11111001 5
b10 .
b1001 #
b1001 :
b100 <
1;
b1001 9
b0 8
b1001 %
b1001 )
b1001 '
b1111000 1"
b11111000 0"
b1000 /"
b1000 2"
#26
1""
b1010 !
b1010 4
1~
b0 /
b0 3
b1 2
b11111110 .
b11111010 "
b11111010 5
b100 -
b11010 #
b11010 :
b1 8
b100 <
1;
b1010 9
b1010 %
b1010 )
b1010 '
b1001 1"
b11111001 0"
b1001 /"
b1001 2"
#27
b1011 !
b1011 4
b11111111 /
b11111011 "
b11111011 5
b0 .
b1 3
b1011 #
b1011 :
b100 <
1;
b1011 9
b0 8
b1011 %
b1011 )
b1011 '
b11010 1"
b11111010 0"
b1010 /"
b1010 2"
#28
1C
1B
0""
b111 +
1&"
b1100 !
b1100 4
0~
1$"
b0 /
b0 ,
b0 3
b0 2
b1 1
b11111100 "
b11111100 5
b11111100 -
b111100 #
b111100 :
b11 8
b100 <
1;
b1100 9
b1100 %
b1100 )
b1100 '
b1011 1"
b11111011 0"
b1011 /"
b1011 2"
#29
b1101 !
b1101 4
b11111111 /
b1 3
b11111101 "
b11111101 5
b10 .
b1101 #
b1101 :
b100 <
1;
b1101 9
b0 8
b1101 %
b1101 )
b1101 '
b111100 1"
b11111100 0"
b1100 /"
b1100 2"
#30
1""
b1110 !
b1110 4
1~
b0 /
b0 -
b0 3
b1 2
b11111110 "
b11111110 5
b11111110 .
b11110 #
b11110 :
b1 8
b100 <
1;
b1110 9
b1110 %
b1110 )
b1110 '
b1101 1"
b11111101 0"
b1101 /"
b1101 2"
#31
b1111 !
b1111 4
b11111111 /
b11111111 "
b11111111 5
b0 .
b1 3
b1111 #
b1111 :
b100 <
1;
b1111 9
b0 8
b1111 %
b1111 )
b1111 '
b11110 1"
b11111110 0"
b1110 /"
b1110 2"
#32
0[
0Z
0C
0K
0B
0J
0""
0&"
b0 +
0*"
b0 "
b0 5
b0 /
b0 !
b0 4
0~
0$"
0("
b0 3
b0 2
b0 1
b0 0
b0 #
b0 :
b100 <
0;
b0 9
b0 %
b0 )
b10 7
b10 $
b10 (
b10 &
b0 '
b1111 1"
b11111111 0"
b1111 /"
b1111 2"
#33
b10 !
b10 4
1""
1}
b11111110 /
b10 3
b10 "
b10 5
b100 .
b10010 #
b10010 :
0;
b1 8
b100 <
b10 9
b1 %
b1 )
b1 '
b0 1"
b0 0"
b0 /"
b0 2"
#34
1C
1B
b100 !
b100 4
0""
b1 +
1&"
0}
1#"
b0 /
b0 3
b10 2
b11111100 .
b100 "
b100 5
b1000 -
b100100 #
b100100 :
0;
b100 9
b100 <
b10 8
b10 %
b10 )
b10 '
b10010 1"
b10 0"
b10 /"
b10 2"
#35
b110 !
b110 4
1""
1}
b11111110 /
b110 "
b110 5
b0 .
b10 3
b10110 #
b10110 :
0;
b100 <
b110 9
b1 8
b11 %
b11 )
b11 '
b100100 1"
b100 0"
b100 /"
b100 2"
#36
1[
1Z
0C
1K
0B
1J
b1000 !
b1000 4
0""
0&"
b110 +
1*"
0}
0#"
1'"
b0 /
b0 3
b0 2
b10 1
b11111000 -
b1000 "
b1000 5
b10000 ,
b1001000 #
b1001000 :
0;
b100 <
b1000 9
b100 8
b100 %
b100 )
b100 '
b10110 1"
b110 0"
b110 /"
b110 2"
#37
b1010 !
b1010 4
1""
1}
b11111110 /
b10 3
b1010 "
b1010 5
b100 .
b11010 #
b11010 :
0;
b100 <
b1010 9
b1 8
b101 %
b101 )
b101 '
b1001000 1"
b1000 0"
b1000 /"
b1000 2"
#38
1C
1B
b1100 !
b1100 4
0""
b111 +
1&"
0}
1#"
b0 /
b0 -
b0 3
b10 2
b1100 "
b1100 5
b11111100 .
b101100 #
b101100 :
0;
b100 <
b1100 9
b10 8
b110 %
b110 )
b110 '
b11010 1"
b1010 0"
b1010 /"
b1010 2"
#39
b1110 !
b1110 4
1""
1}
b11111110 /
b1110 "
b1110 5
b0 .
b10 3
b11110 #
b11110 :
0;
b100 <
b1110 9
b1 8
b111 %
b111 )
b111 '
b101100 1"
b1100 0"
b1100 /"
b1100 2"
#40
0[
1."
0Z
1,"
0C
0K
1c
0B
0J
1b
b10000 !
b10000 4
0""
0&"
0*"
b11000 +
1S
0}
0#"
0'"
1R
b0 /
b0 3
b0 2
b0 1
b10 0
b11110000 "
b11110000 5
b11110000 ,
b1110000 #
b1110000 :
1;
b100 <
b0 9
b111 8
b1000 %
b1000 )
b1000 '
b11110 1"
b1110 0"
b1110 /"
b1110 2"
#41
b10010 !
b10010 4
1""
1}
b11111110 /
b10 3
b11110010 "
b11110010 5
b100 .
b10 #
b10 :
b100 <
1;
b10 9
b0 8
b1001 %
b1001 )
b1001 '
b1110000 1"
b11110000 0"
b10000 /"
b10000 2"
#42
1C
1B
b10100 !
b10100 4
0""
b11001 +
1&"
0}
1#"
b0 /
b0 3
b10 2
b11111100 .
b11110100 "
b11110100 5
b1000 -
b10100 #
b10100 :
b1 8
b100 <
1;
b100 9
b1010 %
b1010 )
b1010 '
b10 1"
b11110010 0"
b10010 /"
b10010 2"
#43
b10110 !
b10110 4
1""
1}
b11111110 /
b11110110 "
b11110110 5
b0 .
b10 3
b110 #
b110 :
b100 <
1;
b110 9
b0 8
b1011 %
b1011 )
b1011 '
b10100 1"
b11110100 0"
b10100 /"
b10100 2"
#44
1[
1Z
0C
1K
0B
1J
b11000 !
b11000 4
0""
0&"
b11110 +
1*"
0}
0#"
1'"
b0 /
b0 ,
b0 3
b0 2
b10 1
b11111000 "
b11111000 5
b11111000 -
b111000 #
b111000 :
b11 8
b100 <
1;
b1000 9
b1100 %
b1100 )
b1100 '
b110 1"
b11110110 0"
b10110 /"
b10110 2"
#45
b11010 !
b11010 4
1""
1}
b11111110 /
b10 3
b11111010 "
b11111010 5
b100 .
b1010 #
b1010 :
b100 <
1;
b1010 9
b0 8
b1101 %
b1101 )
b1101 '
b111000 1"
b11111000 0"
b11000 /"
b11000 2"
#46
1C
1B
b11100 !
b11100 4
0""
b11111 +
1&"
0}
1#"
b0 /
b0 -
b0 3
b10 2
b11111100 "
b11111100 5
b11111100 .
b11100 #
b11100 :
b1 8
b100 <
1;
b1100 9
b1110 %
b1110 )
b1110 '
b1010 1"
b11111010 0"
b11010 /"
b11010 2"
#47
b11110 !
b11110 4
1""
1}
b11111110 /
b11111110 "
b11111110 5
b0 .
b10 3
b1110 #
b1110 :
b100 <
1;
b1110 9
b0 8
b1111 %
b1111 )
b1111 '
b11100 1"
b11111100 0"
b11100 /"
b11100 2"
#48
0[
0."
0Z
0,"
0C
0K
0c
0B
0J
0b
b0 !
b0 4
0""
0&"
0*"
b0 +
0S
0}
0#"
0'"
0R
b0 "
b0 5
b0 /
b0 3
b0 2
b0 1
b0 0
b0 #
b0 :
b100 <
0;
b0 9
b0 %
b0 )
b11 7
b11 $
b11 (
b11 &
b0 '
b1110 1"
b11111110 0"
b11110 /"
b11110 2"
#49
1""
b11 !
b11 4
1}
b11111101 /
b11 3
b11 "
b11 5
b110 .
b10011 #
b10011 :
0;
b1 8
b100 <
b11 9
b1 %
b1 )
b1 '
b0 1"
b0 0"
b0 /"
b0 2"
#50
1C
1B
b1 +
1&"
b110 !
b110 4
0}
1~
1#"
b0 /
b0 3
b11 2
b11111010 .
b110 "
b110 5
b1100 -
b100110 #
b100110 :
0;
b100 <
b110 9
b10 8
b10 %
b10 )
b10 '
b10011 1"
b11 0"
b11 /"
b11 2"
#51
1[
1\
1V
1?
1A
0C
1D
1>
0""
b1001 6
1!"
b1001 !
b1001 4
1}
b11111101 /
b1001 "
b1001 5
b0 .
b11 3
b11001 #
b11001 :
0;
b100 <
b1001 9
b1 8
b11 %
b11 )
b11 '
b100110 1"
b110 0"
b110 /"
b110 2"
#52
0."
0\
0+"
0V
0W
0?
0Y
1[
0A
1C
1Z
0D
1K
0>
1J
b0 6
0!"
b111 +
1*"
b1100 !
b1100 4
0}
0~
0#"
1$"
1'"
b0 /
b0 3
b0 2
b11 1
b11110100 -
b1100 "
b1100 5
b11000 ,
b1001100 #
b1001100 :
0;
b100 <
b1100 9
b100 8
b100 %
b100 )
b100 '
b11001 1"
b1001 0"
b1001 /"
b1001 2"
#53
1""
b1111 !
b1111 4
1}
b11111101 /
b11 3
b1111 "
b1111 5
b110 .
b11111 #
b11111 :
0;
b100 <
b1111 9
b1 8
b101 %
b101 )
b101 '
b1001100 1"
b1100 0"
b1100 /"
b1100 2"
#54
1."
1,"
1c
1d
1^
0[
1G
0Z
1I
0K
0C
1L
0B
1F
b10010 +
0&"
b10010 6
1%"
b10010 !
b10010 4
0}
1~
1#"
b0 /
b0 -
b0 3
b11 2
b10010 "
b10010 5
b11111010 .
b110010 #
b110010 :
0;
b100 <
b10 9
b11 8
b110 %
b110 )
b110 '
b11111 1"
b1111 0"
b1111 /"
b1111 2"
#55
1C
1D
1>
0""
b10011 6
1!"
b10101 !
b10101 4
1}
b11111101 /
b10101 "
b10101 5
b0 .
b11 3
b100101 #
b100101 :
0;
b100 <
b101 9
b10 8
b111 %
b111 )
b111 '
b110010 1"
b10010 0"
b10010 /"
b10010 2"
#56
0d
0s
0^
1[
0t
0G
1Z
0n
1."
0C
0I
1K
0_
1,"
0D
0L
0a
1c
0>
0F
1b
0!"
b0 6
0%"
b11110 +
1S
b11000 !
b11000 4
0}
0~
0#"
0$"
0'"
1("
1R
b0 /
b0 3
b0 2
b0 1
b11 0
b11101000 "
b11101000 5
b11101000 ,
b1101000 #
b1101000 :
1;
b100 <
b1000 9
b110 8
b1000 %
b1000 )
b1000 '
b100101 1"
b10101 0"
b10101 /"
b10101 2"
#57
1""
b11011 !
b11011 4
1}
b11111101 /
b11 3
b11101011 "
b11101011 5
b110 .
b1111011 #
b1111011 :
b100 <
1;
b1011 9
b111 8
b1001 %
b1001 )
b1001 '
b1101000 1"
b11101000 0"
b11000 /"
b11000 2"
#58
1C
1B
b11111 +
1&"
b11110 !
b11110 4
0}
1~
1#"
b0 /
b0 3
b11 2
b11111010 .
b11101110 "
b11101110 5
b1100 -
b1110 #
b1110 :
b100 <
1;
b1110 9
b0 8
b1010 %
b1010 )
b1010 '
b1111011 1"
b11101011 0"
b11011 /"
b11011 2"
#59
1s
1t
1m
0."
1-"
1+"
1W
1Y
0[
1\
1V
1?
1A
0C
1D
1>
0""
b1001001001 6
1!"
b100001 !
b100001 4
1}
b11111101 /
b11110001 "
b11110001 5
b0 .
b11 3
b1 #
b1 :
b0 8
b100 <
1;
b1 9
b1011 %
b1011 )
b1011 '
b1110 1"
b11101110 0"
b11110 /"
b11110 2"
#60
0t
1r
0m
1k
0-"
0\
0+"
1l
0,"
0V
0W
1f
0c
0?
0Y
0[
1O
0b
0A
1C
0Z
1Q
0S
0D
0K
1T
0>
0J
1N
0!"
b100001 +
0*"
b100100 6
1)"
b100100 !
b100100 4
0}
0~
0#"
1$"
1'"
b0 /
b0 ,
b0 3
b0 2
b11 1
b11110100 "
b11110100 5
b11110100 -
b110100 #
b110100 :
b11 8
b100 <
1;
b100 9
b1100 %
b1100 )
b1100 '
b1 1"
b11110001 0"
b100001 /"
b100001 2"
#61
1""
b100111 !
b100111 4
1}
b11111101 /
b11 3
b11110111 "
b11110111 5
b110 .
b111 #
b111 :
b100 <
1;
b111 9
b0 8
b1101 %
b1101 )
b1101 '
b110100 1"
b11110100 0"
b100100 /"
b100100 2"
#62
1[
1Z
1K
0C
1L
0B
1F
b100100 +
0&"
b100110 6
1%"
b101010 !
b101010 4
0}
1~
1#"
b0 /
b0 -
b0 3
b11 2
b11111010 "
b11111010 5
b11111010 .
b11010 #
b11010 :
b1 8
b100 <
1;
b1010 9
b1110 %
b1110 )
b1110 '
b111 1"
b11110111 0"
b100111 /"
b100111 2"
#63
1C
1D
1>
0""
b100111 6
1!"
b101101 !
b101101 4
1}
b11111101 /
b11111101 "
b11111101 5
b0 .
b11 3
b1101 #
b1101 :
b100 <
1;
b1101 9
b0 8
b1111 %
b1111 )
b1111 '
b11010 1"
b11111010 0"
b101010 /"
b101010 2"
#64
0s
0[
0r
0Z
0k
0."
0C
0K
0l
0,"
0D
0L
0T
0f
0c
0>
0F
0N
0O
0b
0!"
0%"
b0 6
0)"
0Q
b0 +
0S
b0 "
b0 5
b0 /
b0 !
b0 4
0}
0~
0#"
0$"
0'"
0("
0R
b0 3
b0 2
b0 1
b0 0
b0 #
b0 :
b100 <
0;
b0 9
b0 %
b0 )
b100 7
b100 $
b100 (
b100 &
b0 '
b1101 1"
b11111101 0"
b101101 /"
b101101 2"
#65
b100 !
b100 4
1C
1D
1=
b11111100 /
b100 3
b100 "
b100 5
b1000 .
b10100 #
b10100 :
0;
b1 8
b100 <
b100 9
b1 %
b1 )
b1 '
b0 1"
b0 0"
b0 /"
b0 2"
#66
1[
1Z
b1000 !
b1000 4
0C
b100 +
1K
0D
1L
0=
1E
b0 /
b0 3
b100 2
b11111000 .
b1000 "
b1000 5
b10000 -
b101000 #
b101000 :
0;
b100 <
b1000 9
b10 8
b10 %
b10 )
b10 '
b10100 1"
b100 0"
b100 /"
b100 2"
#67
b1100 !
b1100 4
1C
1D
1=
b11111100 /
b1100 "
b1100 5
b0 .
b100 3
b11100 #
b11100 :
0;
b100 <
b1100 9
b1 8
b11 %
b11 )
b11 '
b101000 1"
b1000 0"
b1000 /"
b1000 2"
#68
1."
1,"
0[
1c
0Z
1b
b10000 !
b10000 4
0C
0K
b11000 +
1S
0D
0L
1T
0=
0E
1M
b0 /
b0 3
b0 2
b100 1
b11110000 -
b10000 "
b10000 5
b100000 ,
b1010000 #
b1010000 :
0;
b100 <
b0 9
b101 8
b100 %
b100 )
b100 '
b11100 1"
b1100 0"
b1100 /"
b1100 2"
#69
b10100 !
b10100 4
1C
1D
1=
b11111100 /
b100 3
b10100 "
b10100 5
b1000 .
b100100 #
b100100 :
0;
b100 <
b100 9
b10 8
b101 %
b101 )
b101 '
b1010000 1"
b10000 0"
b10000 /"
b10000 2"
#70
1[
1Z
b11000 !
b11000 4
0C
b11100 +
1K
0D
1L
0=
1E
b0 /
b0 -
b0 3
b100 2
b11000 "
b11000 5
b11111000 .
b111000 #
b111000 :
0;
b100 <
b1000 9
b11 8
b110 %
b110 )
b110 '
b100100 1"
b10100 0"
b10100 /"
b10100 2"
#71
b11100 !
b11100 4
1C
1D
1=
b11111100 /
b11100 "
b11100 5
b0 .
b100 3
b101100 #
b101100 :
0;
b100 <
b1100 9
b10 8
b111 %
b111 )
b111 '
b111000 1"
b11000 0"
b11000 /"
b11000 2"
#72
0."
0,"
0[
0c
0Z
0b
1s
b100000 !
b100000 4
0C
0K
0S
1r
0D
0L
0T
b100000 +
1k
0=
0E
0M
1j
b0 /
b0 3
b0 2
b0 1
b100 0
b11100000 "
b11100000 5
b11100000 ,
b1100000 #
b1100000 :
1;
b100 <
b0 9
b110 8
b1000 %
b1000 )
b1000 '
b101100 1"
b11100 0"
b11100 /"
b11100 2"
#73
b100100 !
b100100 4
1C
1D
1=
b11111100 /
b100 3
b11100100 "
b11100100 5
b1000 .
b1110100 #
b1110100 :
b100 <
1;
b100 9
b111 8
b1001 %
b1001 )
b1001 '
b1100000 1"
b11100000 0"
b100000 /"
b100000 2"
#74
1[
1Z
b101000 !
b101000 4
0C
b100100 +
1K
0D
1L
0=
1E
b0 /
b0 3
b100 2
b11111000 .
b11101000 "
b11101000 5
b10000 -
b1000 #
b1000 :
b100 <
1;
b1000 9
b0 8
b1010 %
b1010 )
b1010 '
b1110100 1"
b11100100 0"
b100100 /"
b100100 2"
