Homework3/mealy_detector/rtl/mealy_detector.v
module mealy_detector(
	input	wire	clk,
	input	wire	rst_n,
	input	wire	in,
	output	reg	out
);

	parameter	A = 4'h0;
	parameter	B = 4'h4;
	parameter	C = 4'h8;
	parameter	D = 4'hC;

	reg	[3:0]	state, current_state;

	always @(posedge clk or negedge rst_n) begin
		if(!rst_n)
			current_state	<= A;
		else
			current_state	<= state;
	end

	always @(*) begin
		state 	= current_state;
		out	= 0;
		case(current_state)
			A: begin
				if(in == 1)
					state 	= B;
				else
					state	= A;
			end
			B: begin
				if(in == 0)
					state 	= C;
				else
					state	= B;
			end
			C: begin
				if(in == 1)
					state 	= D;
				else
					state	= A;
			end
			D: begin
				if(in == 0) begin
					state 	= C;
					out	= 1;
				end
				else begin
					state	= B;
				end
			end
			default: begin
				state	= A;
			end
		endcase
	end
		
endmodule

Homework3/mealy_detector/tb/test_bench.v
module test_bench;

	reg	clk, rst_n, in;
	wire	out;

	mealy_detector DUT(.*);

	initial begin
		clk = 0;
		forever #25 clk = ~clk;
	end

	initial begin
		$dumpfile("wave.vcd");
		$dumpvars(0,test_bench);
		$display("===== Test Mealy Sequence Detector =====");
		$monitor("===== With Input Value = %b =====",in);
		rst_n = 0; in = 0;
		$display("===== With Reset value = %b =====", rst_n);
		@(posedge clk);
		#1;
		check_result(1'b0, out);

		rst_n = 1;
		$display("===== With Reset value = %b =====", rst_n);
		in = 1;
		@(posedge clk);
		#1;
		check_result(1'b0, out);

		in = 0;
		@(posedge clk);
		#1;
		check_result(1'b0, out);

		in = 1;
		@(posedge clk);
		#1;
		check_result(1'b0, out);

		in = 0;
		#1;
		check_result(1'b1, out);

		in = 0;
		@(posedge clk);
		#1;
		check_result(1'b0, out);

		in = 1;
		@(posedge clk);
		#1;
		check_result(1'b0, out);

		in = 0;
		@(posedge clk);
		#1;
		check_result(1'b0, out);

		in = 0;
		@(posedge clk);
		#1;
		check_result(1'b0, out);

		in = 1;
		@(posedge clk);
		#1;
		check_result(1'b0, out);

		in = 0;
		@(posedge clk);
		#1;
		check_result(1'b0, out);

		in = 1;
		@(posedge clk);
		#1;
		check_result(1'b0, out);

		in = 0;
		#1;
		check_result(1'b1, out);

		#10;
		$finish;
	end

	task check_result;
		input		result;
		input		g;

		if(g!=result) begin
			$display("\n===== t=%d FAILED, output does not match =====",$time);
			$display("===== t=%d Expected value is %b, Actual value is %b =====",$time, result, g);
		end
		else begin
			$display("\n===== t=%d PASSED SUCCESSFULLY =====",$time);
		end
	endtask
	
endmodule

Homework3/mealy_detector/sim/wave.vcd
$date
	Fri Oct 10 17:59:26 2025
$end
$version
	Icarus Verilog
$end
$timescale
	1s
$end
$scope module test_bench $end
$var wire 1 ! out $end
$var reg 1 " clk $end
$var reg 1 # in $end
$var reg 1 $ rst_n $end
$scope module DUT $end
$var wire 1 " clk $end
$var wire 1 # in $end
$var wire 1 $ rst_n $end
$var reg 4 % current_state [3:0] $end
$var reg 1 ! out $end
$var reg 4 & state [3:0] $end
$upscope $end
$scope task check_result $end
$var reg 1 ' g $end
$var reg 1 ( result $end
$upscope $end
$upscope $end
$enddefinitions $end
#0
$dumpvars
x(
x'
b0 &
b0 %
0$
0#
0"
0!
$end
#25
1"
#26
b100 &
1#
1$
0'
0(
#50
0"
#75
b100 %
1"
#76
b1000 &
0#
#100
0"
#125
b0 &
b1000 %
1"
#126
b1100 &
1#
#150
0"
#175
b100 &
b1100 %
1"
#176
1!
b1000 &
0#
#177
1'
1(
#200
0"
#225
b0 &
0!
b1000 %
1"
#226
b1100 &
1#
0'
0(
#250
0"
#275
b100 &
b1100 %
1"
#276
1!
b1000 &
0#
#300
0"
#325
b0 &
0!
b1000 %
1"
#350
0"
#375
b0 %
1"
#376
b100 &
1#
#400
0"
#425
b100 %
1"
#426
b1000 &
0#
#450
0"
#475
b0 &
b1000 %
1"
#476
b1100 &
1#
#500
0"
#525
b100 &
b1100 %
1"
#526
1!
b1000 &
0#
#527
1'
1(
