Homework2/adder_4bit/rtl/adder_4bit.v
module adder_4bit(
	input	wire	[3:0] 	a,
	input	wire	[3:0] 	b,
	input	wire	 	cin,
	output	wire	[3:0] 	gate_out,
	output	wire	[3:0] 	data_out,
	output	reg	[3:0] 	behav_out,
	output	wire	 	gate_carry,
	output	wire	 	data_carry,
	output	reg		behav_carry
);
	
	wire	gate_carry_1, gate_carry_2, gate_carry_3;
	wire	data_carry_1, data_carry_2, data_carry_3;
	reg	behav_carry_1, behav_carry_2, behav_carry_3;
	wire	f1_0, f2_0, f3_0, f1_1, f2_1, f3_1, f1_2, f2_2, f3_2, f1_3, f2_3, f3_3;
	
	//structural
	xor(gate_out[0], a[0], b[0], cin);
	xor(gate_out[1], a[1], b[1], gate_carry_1);
	xor(gate_out[2], a[2], b[2], gate_carry_2);
	xor(gate_out[3], a[3], b[3], gate_carry_3);

	and(f1_0,a[0],b[0]);
	and(f2_0,a[0],cin);
	and(f3_0,cin,b[0]);
	or(gate_carry_1, f1_0, f2_0, f3_0);

	and(f1_1,a[1],b[1]);
	and(f2_1,a[1],gate_carry_1);
	and(f3_1,gate_carry_1,b[1]);
	or(gate_carry_2, f1_1, f2_1, f3_1);

	and(f1_2,a[2],b[2]);
	and(f2_2,a[2],gate_carry_2);
	and(f3_2,gate_carry_2,b[2]);
	or(gate_carry_3, f1_2, f2_2, f3_2);
		
	and(f1_3,a[3],b[3]);
	and(f2_3,a[3],gate_carry_3);
	and(f3_3,gate_carry_3,b[3]);
	or(gate_carry, f1_3, f2_3, f3_3);
	
	//dataflow
	assign data_out[0] 	= a[0] ^ b[0] ^ cin;
	assign data_carry_1	= (a[0] & b[0]) | (a[0] & cin) | (b[0] & cin);

	assign data_out[1] 	= a[1] ^ b[1] ^ data_carry_1;
	assign data_carry_2	= (a[1] & b[1]) | (a[1] & data_carry_1) | (b[1] & data_carry_1);

	assign data_out[2] 	= a[2] ^ b[2] ^ data_carry_2;
	assign data_carry_3	= (a[2] & b[2]) | (a[2] & data_carry_2) | (b[2] & data_carry_2);

	assign data_out[3] 	= a[3] ^ b[3] ^ data_carry_3;
	assign data_carry	= (a[3] & b[3]) | (a[3] & data_carry_3) | (b[3] & data_carry_3);

	//behavioral	
	always @(*) begin
		behav_out[0] 	= a[0] ^ b[0] ^ cin;
		behav_carry_1	= (a[0] & b[0]) | (a[0] & cin) | (b[0] & cin);
	end

	always @(*) begin
		behav_out[1] 	= a[1] ^ b[1] ^ behav_carry_1;
		behav_carry_2	= (a[1] & b[1]) | (a[1] & data_carry_1) | (b[1] & behav_carry_1);
	end

	always @(*) begin
		behav_out[2] 	= a[2] ^ b[2] ^ behav_carry_2;
		behav_carry_3	= (a[2] & b[2]) | (a[2] & data_carry_2) | (b[2] & behav_carry_2);
	end

	always @(*) begin
		behav_out[3] 	= a[3] ^ b[3] ^ behav_carry_3;
		behav_carry	= (a[3] & b[3]) | (a[3] & data_carry_3) | (b[3] & behav_carry_3);
	end

endmodule

Homework2/adder_4bit/tb/test_bench12.v
module test_bench12;

	reg	[3:0]	a, b;
	reg		cin;
	wire	[3:0]	gate_out, data_out, behav_out;
	wire		gate_carry, data_carry, behav_carry;
	integer		i, j, k;

	adder_4bit DUT(.*);

	initial begin
		$dumpfile("wave12.vcd");
        	$dumpvars(0,test_bench12);
        	$display("===== Test Adder 4 bits =====");
		$display("===== Initial State =====");
		$display("===== A = 4'b0000, B = 4'b0000, Cin = 1'b0 =====");
		a = 4'b0000; b = 4'b0000; cin = 1'b0;
		#1;
		if(gate_out!=4'b0000 || data_out!=4'b0000 || behav_out!=4'b0000) begin
			$display("===== t=%d FAILED, output does not match =====",$time);
			$display("===== t=%d Expected value is %2d, Actual gate_model value is %2d, Actual dataflow value is %2d, Actual behavioural model value is %2d =====", $time, 4'b0000, gate_out, data_out, behav_out);
		end
		else begin
			$display("===== t=%d PASSED SUCCESSFULLY =====", $time);
		end

		for (i = 0; i < 16; i = i + 1) begin
            		for (j = 0; j < 16; j = j + 1) begin
                		for (k = 0; k < 2; k = k + 1) begin
                    			a   = i;
       			                b   = j;
                    			cin = k;
                    			#1; 

                    			$display("\n===== t=%d With A = %2d, B = %2d : Actual gate_model value is %2d, Actual dataflow value is %2d, Actual behavioural model value is %2d", $time, a, b, gate_out, data_out, behav_out);
					$display("===== t=%d Actual gate_model carry is %b, Actual dataflow carry is %b, Actual behavioural model carry is %b", $time, gate_carry, data_carry, behav_carry);
                    		end
            		end
		end

	end

endmodule

Homework2/adder_4bit/sim/wave12.vcd
$date
	Fri Sep 26 08:44:41 2025
$end
$version
	Icarus Verilog
$end
$timescale
	1s
$end
$scope module test_bench12 $end
$var wire 4 ! gate_out [3:0] $end
$var wire 1 " gate_carry $end
$var wire 4 # data_out [3:0] $end
$var wire 1 $ data_carry $end
$var wire 4 % behav_out [3:0] $end
$var wire 1 & behav_carry $end
$var reg 4 ' a [3:0] $end
$var reg 4 ( b [3:0] $end
$var reg 1 ) cin $end
$var integer 32 * i [31:0] $end
$var integer 32 + j [31:0] $end
$var integer 32 , k [31:0] $end
$scope module DUT $end
$var wire 4 - a [3:0] $end
$var wire 4 . b [3:0] $end
$var wire 1 ) cin $end
$var wire 1 $ data_carry $end
$var wire 1 / data_carry_1 $end
$var wire 1 0 data_carry_2 $end
$var wire 1 1 data_carry_3 $end
$var wire 1 2 f1_0 $end
$var wire 1 3 f1_1 $end
$var wire 1 4 f1_2 $end
$var wire 1 5 f1_3 $end
$var wire 1 6 f2_0 $end
$var wire 1 7 f2_1 $end
$var wire 1 8 f2_2 $end
$var wire 1 9 f2_3 $end
$var wire 1 : f3_0 $end
$var wire 1 ; f3_1 $end
$var wire 1 < f3_2 $end
$var wire 1 = f3_3 $end
$var wire 1 " gate_carry $end
$var wire 1 > gate_carry_1 $end
$var wire 1 ? gate_carry_2 $end
$var wire 1 @ gate_carry_3 $end
$var wire 4 A gate_out [3:0] $end
$var wire 4 B data_out [3:0] $end
$var reg 1 & behav_carry $end
$var reg 1 C behav_carry_1 $end
$var reg 1 D behav_carry_2 $end
$var reg 1 E behav_carry_3 $end
$var reg 4 F behav_out [3:0] $end
$upscope $end
$upscope $end
$enddefinitions $end
#0
$dumpvars
b0 F
0E
0D
0C
b0 B
b0 A
0@
0?
0>
0=
0<
0;
0:
09
08
07
06
05
04
03
02
01
00
0/
b0 .
b0 -
bx ,
bx +
bx *
0)
b0 (
b0 '
0&
b0 %
0$
b0 #
0"
b0 !
$end
#1
b0 ,
b0 +
b0 *
#2
b1 !
b1 A
b1 #
b1 B
b1 %
b1 F
1)
b1 ,
#3
b1 #
b1 B
0)
b1 (
b1 .
b1 +
b0 ,
#4
1>
1/
b10 !
b10 A
1:
b10 #
b10 B
1C
b10 %
b10 F
1)
b1 ,
#5
0?
00
0>
0/
b10 !
b10 A
0;
0:
b10 #
b10 B
0C
0)
b10 (
b10 .
b10 +
b0 ,
#6
b11 !
b11 A
b11 #
b11 B
b11 %
b11 F
1)
b1 ,
#7
b11 #
b11 B
0)
b11 (
b11 .
b11 +
b0 ,
#8
1?
10
1;
1>
1/
1D
b100 !
b100 A
1:
b100 #
b100 B
1C
b100 %
b100 F
1)
b1 ,
#9
0?
0@
00
01
0>
0/
b100 !
b100 A
0;
0<
0:
b100 #
b100 B
0D
0C
0)
b100 (
b100 .
b100 +
b0 ,
#10
b101 !
b101 A
b101 #
b101 B
b101 %
b101 F
1)
b1 ,
#11
b101 #
b101 B
0)
b101 (
b101 .
b101 +
b0 ,
#12
1>
1/
b110 !
b110 A
1:
b110 #
b110 B
1C
b110 %
b110 F
1)
b1 ,
#13
0@
01
0<
0?
00
0>
0/
b110 !
b110 A
0;
0:
b110 #
b110 B
0C
0)
b110 (
b110 .
b110 +
b0 ,
#14
b111 !
b111 A
b111 #
b111 B
b111 %
b111 F
1)
b1 ,
#15
b111 #
b111 B
0)
b111 (
b111 .
b111 +
b0 ,
#16
1@
11
1<
1?
10
1;
1E
1>
1/
1D
b1000 !
b1000 A
1:
b1000 #
b1000 B
1C
b1000 %
b1000 F
1)
b1 ,
#17
0?
0@
0"
00
01
0$
0>
0/
b1000 !
b1000 A
0;
0<
0=
0:
b1000 #
b1000 B
0E
0D
0C
0)
b1000 (
b1000 .
b1000 +
b0 ,
#18
b1001 !
b1001 A
b1001 #
b1001 B
b1001 %
b1001 F
1)
b1 ,
#19
b1001 #
b1001 B
0)
b1001 (
b1001 .
b1001 +
b0 ,
#20
1>
1/
b1010 !
b1010 A
1:
b1010 #
b1010 B
1C
b1010 %
b1010 F
1)
b1 ,
#21
0?
00
0>
0/
b1010 !
b1010 A
0;
0:
b1010 #
b1010 B
0C
0)
b1010 (
b1010 .
b1010 +
b0 ,
#22
b1011 !
b1011 A
b1011 #
b1011 B
b1011 %
b1011 F
1)
b1 ,
#23
b1011 #
b1011 B
0)
b1011 (
b1011 .
b1011 +
b0 ,
#24
1?
10
1;
1>
1/
1D
b1100 !
b1100 A
1:
b1100 #
b1100 B
1C
b1100 %
b1100 F
1)
b1 ,
#25
0"
0$
0=
0?
0@
00
01
0>
0/
b1100 !
b1100 A
0;
0<
0:
b1100 #
b1100 B
0D
0C
0)
b1100 (
b1100 .
b1100 +
b0 ,
#26
b1101 !
b1101 A
b1101 #
b1101 B
b1101 %
b1101 F
1)
b1 ,
#27
b1101 #
b1101 B
0)
b1101 (
b1101 .
b1101 +
b0 ,
#28
1>
1/
b1110 !
b1110 A
1:
b1110 #
b1110 B
1C
b1110 %
b1110 F
1)
b1 ,
#29
0"
0$
0=
0@
01
0<
0?
00
0>
0/
b1110 !
b1110 A
0;
0:
b1110 #
b1110 B
0C
0)
b1110 (
b1110 .
b1110 +
b0 ,
#30
b1111 !
b1111 A
b1111 #
b1111 B
b1111 %
b1111 F
1)
b1 ,
#31
b1111 #
b1111 B
0)
b1111 (
b1111 .
b1111 +
b0 ,
#32
1"
1$
1=
1@
11
1<
1?
10
1&
1;
1E
1>
1/
1D
b0 !
b0 A
1:
b0 #
b0 B
1C
b0 %
b0 F
1)
b1 ,
#33
0?
0@
0"
00
01
0$
0>
0/
0;
0<
0=
b1 !
b1 A
0:
b1 #
b1 B
0&
0E
0D
0C
b1 %
b1 F
0)
b0 (
b0 .
b1 '
b1 -
b1 *
b0 +
b0 ,
#34
1/
1>
b10 !
b10 A
16
b10 #
b10 B
1C
b10 %
b10 F
1)
b1 ,
#35
12
06
b10 #
b10 B
0)
b1 (
b1 .
b1 +
b0 ,
#36
b11 !
b11 A
16
1:
b11 #
b11 B
b11 %
b11 F
1)
b1 ,
#37
0/
0?
00
0>
b11 !
b11 A
02
0;
06
0:
b11 #
b11 B
0C
0)
b10 (
b10 .
b10 +
b0 ,
#38
10
1?
1;
1/
1>
1D
b100 !
b100 A
16
b100 #
b100 B
1C
b100 %
b100 F
1)
b1 ,
#39
12
06
b100 #
b100 B
0)
b11 (
b11 .
b11 +
b0 ,
#40
b101 !
b101 A
16
1:
b101 #
b101 B
b101 %
b101 F
1)
b1 ,
#41
0/
0?
0@
00
01
0>
b101 !
b101 A
02
0;
0<
06
0:
b101 #
b101 B
0D
0C
0)
b100 (
b100 .
b100 +
b0 ,
#42
1/
1>
b110 !
b110 A
16
b110 #
b110 B
1C
b110 %
b110 F
1)
b1 ,
#43
12
06
b110 #
b110 B
0)
b101 (
b101 .
b101 +
b0 ,
#44
b111 !
b111 A
16
1:
b111 #
b111 B
b111 %
b111 F
1)
b1 ,
#45
0@
01
0<
0/
0?
00
0>
b111 !
b111 A
02
0;
06
0:
b111 #
b111 B
0C
0)
b110 (
b110 .
b110 +
b0 ,
#46
11
1@
1<
10
1?
1;
1/
1E
1>
1D
b1000 !
b1000 A
16
b1000 #
b1000 B
1C
b1000 %
b1000 F
1)
b1 ,
#47
12
06
b1000 #
b1000 B
0)
b111 (
b111 .
b111 +
b0 ,
#48
b1001 !
b1001 A
16
1:
b1001 #
b1001 B
b1001 %
b1001 F
1)
b1 ,
#49
0/
0?
0@
0"
00
01
0$
0>
b1001 !
b1001 A
02
0;
0<
0=
06
0:
b1001 #
b1001 B
0E
0D
0C
0)
b1000 (
b1000 .
b1000 +
b0 ,
#50
1/
1>
b1010 !
b1010 A
16
b1010 #
b1010 B
1C
b1010 %
b1010 F
1)
b1 ,
#51
12
06
b1010 #
b1010 B
0)
b1001 (
b1001 .
b1001 +
b0 ,
#52
b1011 !
b1011 A
16
1:
b1011 #
b1011 B
b1011 %
b1011 F
1)
b1 ,
#53
0/
0?
00
0>
b1011 !
b1011 A
02
0;
06
0:
b1011 #
b1011 B
0C
0)
b1010 (
b1010 .
b1010 +
b0 ,
#54
10
1?
1;
1/
1>
1D
b1100 !
b1100 A
16
b1100 #
b1100 B
1C
b1100 %
b1100 F
1)
b1 ,
#55
12
06
b1100 #
b1100 B
0)
b1011 (
b1011 .
b1011 +
b0 ,
#56
b1101 !
b1101 A
16
1:
b1101 #
b1101 B
b1101 %
b1101 F
1)
b1 ,
#57
0"
0$
0=
0/
0?
0@
00
01
0>
b1101 !
b1101 A
02
0;
0<
06
0:
b1101 #
b1101 B
0D
0C
0)
b1100 (
b1100 .
b1100 +
b0 ,
#58
1/
1>
b1110 !
b1110 A
16
b1110 #
b1110 B
1C
b1110 %
b1110 F
1)
b1 ,
#59
12
06
b1110 #
b1110 B
0)
b1101 (
b1101 .
b1101 +
b0 ,
#60
b1111 !
b1111 A
16
1:
b1111 #
b1111 B
b1111 %
b1111 F
1)
b1 ,
#61
0"
0$
0=
0@
01
0<
0/
0?
00
0>
b1111 !
b1111 A
02
0;
06
0:
b1111 #
b1111 B
0C
0)
b1110 (
b1110 .
b1110 +
b0 ,
#62
1$
1"
1=
11
1@
1<
10
1?
1&
1;
1/
1E
1>
1D
b0 !
b0 A
16
b0 #
b0 B
1C
b0 %
b0 F
1)
b1 ,
#63
12
06
b0 #
b0 B
0)
b1111 (
b1111 .
b1111 +
b0 ,
#64
b1 !
b1 A
16
1:
b1 #
b1 B
b1 %
b1 F
1)
b1 ,
#65
00
0?
0D
0/
0@
0"
01
0$
0>
0;
0<
0=
02
07
b10 !
b10 A
06
0:
b10 #
b10 B
0&
0E
0C
b10 %
b10 F
0)
b0 (
b0 .
b10 '
b10 -
b10 *
b0 +
b0 ,
#66
b11 !
b11 A
b11 #
b11 B
b11 %
b11 F
1)
b1 ,
#67
b11 #
b11 B
0)
b1 (
b1 .
b1 +
b0 ,
#68
10
1?
17
1D
1>
1/
b100 !
b100 A
1:
b100 #
b100 B
1C
b100 %
b100 F
1)
b1 ,
#69
07
0>
0/
b100 !
b100 A
13
0;
0:
b100 #
b100 B
0C
0)
b10 (
b10 .
b10 +
b0 ,
#70
b101 !
b101 A
b101 #
b101 B
b101 %
b101 F
1)
b1 ,
#71
b101 #
b101 B
0)
b11 (
b11 .
b11 +
b0 ,
#72
17
1;
1>
1/
b110 !
b110 A
1:
b110 #
b110 B
1C
b110 %
b110 F
1)
b1 ,
#73
00
0?
07
0D
0@
01
0>
0/
b110 !
b110 A
03
0;
0<
0:
b110 #
b110 B
0E
b110 %
b110 F
0C
0)
b100 (
b100 .
b100 +
b0 ,
#74
b111 !
b111 A
b111 #
b111 B
b111 %
b111 F
1)
b1 ,
#75
b111 #
b111 B
0)
b101 (
b101 .
b101 +
b0 ,
#76
11
1@
1<
10
1?
1E
17
1D
1>
1/
b1000 !
b1000 A
1:
b1000 #
b1000 B
1C
b1000 %
b1000 F
1)
b1 ,
#77
07
0>
0/
b1000 !
b1000 A
13
0;
0:
b1000 #
b1000 B
0C
0)
b110 (
b110 .
b110 +
b0 ,
#78
b1001 !
b1001 A
b1001 #
b1001 B
b1001 %
b1001 F
1)
b1 ,
#79
b1001 #
b1001 B
0)
b111 (
b111 .
b111 +
b0 ,
#80
17
1;
1>
1/
b1010 !
b1010 A
1:
b1010 #
b1010 B
1C
b1010 %
b1010 F
1)
b1 ,
#81
00
0?
07
0D
0@
0"
01
0$
0>
0/
b1010 !
b1010 A
03
0;
0<
0=
0:
b1010 #
b1010 B
0E
b1010 %
b1010 F
0C
0)
b1000 (
b1000 .
b1000 +
b0 ,
#82
b1011 !
b1011 A
b1011 #
b1011 B
b1011 %
b1011 F
1)
b1 ,
#83
b1011 #
b1011 B
0)
b1001 (
b1001 .
b1001 +
b0 ,
#84
10
1?
17
1D
1>
1/
b1100 !
b1100 A
1:
b1100 #
b1100 B
1C
b1100 %
b1100 F
1)
b1 ,
#85
07
0>
0/
b1100 !
b1100 A
13
0;
0:
b1100 #
b1100 B
0C
0)
b1010 (
b1010 .
b1010 +
b0 ,
#86
b1101 !
b1101 A
b1101 #
b1101 B
b1101 %
b1101 F
1)
b1 ,
#87
b1101 #
b1101 B
0)
b1011 (
b1011 .
b1011 +
b0 ,
#88
17
1;
1>
1/
b1110 !
b1110 A
1:
b1110 #
b1110 B
1C
b1110 %
b1110 F
1)
b1 ,
#89
00
0"
0$
0?
0=
07
0D
0@
01
0>
0/
b1110 !
b1110 A
03
0;
0<
0:
b1110 #
b1110 B
0&
0E
b1110 %
b1110 F
0C
0)
b1100 (
b1100 .
b1100 +
b0 ,
#90
b1111 !
b1111 A
b1111 #
b1111 B
b1111 %
b1111 F
1)
b1 ,
#91
b1111 #
b1111 B
0)
b1101 (
b1101 .
b1101 +
b0 ,
#92
1$
1"
1=
11
1@
1<
10
1&
1?
1E
17
1D
1>
1/
b0 !
b0 A
1:
b0 #
b0 B
1C
b0 %
b0 F
1)
b1 ,
#93
07
0>
0/
b0 !
b0 A
13
0;
0:
b0 #
b0 B
0C
0)
b1110 (
b1110 .
b1110 +
b0 ,
#94
b1 !
b1 A
b1 #
b1 B
b1 %
b1 F
1)
b1 ,
#95
b1 #
b1 B
0)
b1111 (
b1111 .
b1111 +
b0 ,
#96
17
1;
1>
1/
b10 !
b10 A
1:
b10 #
b10 B
1C
b10 %
b10 F
1)
b1 ,
#97
00
0?
07
0D
0@
0"
01
0$
0>
0/
03
0;
0<
0=
b11 !
b11 A
0:
b11 #
b11 B
0&
0E
0C
b11 %
b11 F
0)
b0 (
b0 .
b11 '
b11 -
b11 *
b0 +
b0 ,
#98
10
1?
1D
17
1/
1>
b100 !
b100 A
16
b100 #
b100 B
1C
b100 %
b100 F
1)
b1 ,
#99
12
06
b100 #
b100 B
0)
b1 (
b1 .
b1 +
b0 ,
#100
b101 !
b101 A
16
1:
b101 #
b101 B
b101 %
b101 F
1)
b1 ,
#101
07
0/
0>
b101 !
b101 A
02
13
0;
06
0:
b101 #
b101 B
0C
0)
b10 (
b10 .
b10 +
b0 ,
#102
17
1;
1/
1>
b110 !
b110 A
16
b110 #
b110 B
1C
b110 %
b110 F
1)
b1 ,
#103
12
06
b110 #
b110 B
0)
b11 (
b11 .
b11 +
b0 ,
#104
b111 !
b111 A
16
1:
b111 #
b111 B
b111 %
b111 F
1)
b1 ,
#105
00
0?
0D
07
0/
0@
01
0>
b111 !
b111 A
02
03
0;
0<
06
0:
b111 #
b111 B
0E
b111 %
b111 F
0C
0)
b100 (
b100 .
b100 +
b0 ,
#106
11
1@
10
1<
1E
1?
1D
17
1/
1>
b1000 !
b1000 A
16
b1000 #
b1000 B
1C
b1000 %
b1000 F
1)
b1 ,
#107
12
06
b1000 #
b1000 B
0)
b101 (
b101 .
b101 +
b0 ,
#108
b1001 !
b1001 A
16
1:
b1001 #
b1001 B
b1001 %
b1001 F
1)
b1 ,
#109
07
0/
0>
b1001 !
b1001 A
02
13
0;
06
0:
b1001 #
b1001 B
0C
0)
b110 (
b110 .
b110 +
b0 ,
#110
17
1;
1/
1>
b1010 !
b1010 A
16
b1010 #
b1010 B
1C
b1010 %
b1010 F
1)
b1 ,
#111
12
06
b1010 #
b1010 B
0)
b111 (
b111 .
b111 +
b0 ,
#112
b1011 !
b1011 A
16
1:
b1011 #
b1011 B
b1011 %
b1011 F
1)
b1 ,
#113
00
0?
0D
07
0/
0@
0"
01
0$
0>
b1011 !
b1011 A
02
03
0;
0<
0=
06
0:
b1011 #
b1011 B
0E
b1011 %
b1011 F
0C
0)
b1000 (
b1000 .
b1000 +
b0 ,
#114
10
1?
1D
17
1/
1>
b1100 !
b1100 A
16
b1100 #
b1100 B
1C
b1100 %
b1100 F
1)
b1 ,
#115
12
06
b1100 #
b1100 B
0)
b1001 (
b1001 .
b1001 +
b0 ,
#116
b1101 !
b1101 A
16
1:
b1101 #
b1101 B
b1101 %
b1101 F
1)
b1 ,
#117
07
0/
0>
b1101 !
b1101 A
02
13
0;
06
0:
b1101 #
b1101 B
0C
0)
b1010 (
b1010 .
b1010 +
b0 ,
#118
17
1;
1/
1>
b1110 !
b1110 A
16
b1110 #
b1110 B
1C
b1110 %
b1110 F
1)
b1 ,
#119
12
06
b1110 #
b1110 B
0)
b1011 (
b1011 .
b1011 +
b0 ,
#120
b1111 !
b1111 A
16
1:
b1111 #
b1111 B
b1111 %
b1111 F
1)
b1 ,
#121
00
0"
0$
0?
0D
0=
07
0/
0@
01
0>
b1111 !
b1111 A
02
03
0;
0<
06
0:
b1111 #
b1111 B
0&
0E
b1111 %
b1111 F
0C
0)
b1100 (
b1100 .
b1100 +
b0 ,
#122
1$
1"
11
1=
1@
10
1&
1<
1E
1?
1D
17
1/
1>
b0 !
b0 A
16
b0 #
b0 B
1C
b0 %
b0 F
1)
b1 ,
#123
12
06
b0 #
b0 B
0)
b1101 (
b1101 .
b1101 +
b0 ,
#124
b1 !
b1 A
16
1:
b1 #
b1 B
b1 %
b1 F
1)
b1 ,
#125
07
0/
0>
b1 !
b1 A
02
13
0;
06
0:
b1 #
b1 B
0C
0)
b1110 (
b1110 .
b1110 +
b0 ,
#126
17
1;
1/
1>
b10 !
b10 A
16
b10 #
b10 B
1C
b10 %
b10 F
1)
b1 ,
#127
12
06
b10 #
b10 B
0)
b1111 (
b1111 .
b1111 +
b0 ,
#128
b11 !
b11 A
16
1:
b11 #
b11 B
b11 %
b11 F
1)
b1 ,
#129
01
0@
0E
0/
0"
00
0$
0?
0>
0;
0<
0=
02
03
07
08
b100 !
b100 A
06
0:
b100 #
b100 B
0&
0D
0C
b100 %
b100 F
0)
b0 (
b0 .
b100 '
b100 -
b100 *
b0 +
b0 ,
#130
b101 !
b101 A
b101 #
b101 B
b101 %
b101 F
1)
b1 ,
#131
b101 #
b101 B
0)
b1 (
b1 .
b1 +
b0 ,
#132
1>
1/
b110 !
b110 A
1:
b110 #
b110 B
1C
b110 %
b110 F
1)
b1 ,
#133
01
0@
b110 %
b110 F
08
0E
0?
00
0>
0/
b110 !
b110 A
0;
0:
b110 #
b110 B
0C
0)
b10 (
b10 .
b10 +
b0 ,
#134
b111 !
b111 A
b111 #
b111 B
b111 %
b111 F
1)
b1 ,
#135
b111 #
b111 B
0)
b11 (
b11 .
b11 +
b0 ,
#136
11
1@
18
1E
1?
10
1;
1>
1/
1D
b1000 !
b1000 A
1:
b1000 #
b1000 B
1C
b1000 %
b1000 F
1)
b1 ,
#137
08
0?
00
0>
0/
b1000 !
b1000 A
0;
14
0<
0:
b1000 #
b1000 B
0D
0C
0)
b100 (
b100 .
b100 +
b0 ,
#138
b1001 !
b1001 A
b1001 #
b1001 B
b1001 %
b1001 F
1)
b1 ,
#139
b1001 #
b1001 B
0)
b101 (
b101 .
b101 +
b0 ,
#140
1>
1/
b1010 !
b1010 A
1:
b1010 #
b1010 B
1C
b1010 %
b1010 F
1)
b1 ,
#141
08
0<
0?
00
0>
0/
b1010 !
b1010 A
0;
0:
b1010 #
b1010 B
0C
0)
b110 (
b110 .
b110 +
b0 ,
#142
b1011 !
b1011 A
b1011 #
b1011 B
b1011 %
b1011 F
1)
b1 ,
#143
b1011 #
b1011 B
0)
b111 (
b111 .
b111 +
b0 ,
#144
18
1<
1?
10
1;
1>
1/
1D
b1100 !
b1100 A
1:
b1100 #
b1100 B
1C
b1100 %
b1100 F
1)
b1 ,
#145
01
0@
08
0E
0?
0"
00
0$
0>
0/
b1100 !
b1100 A
0;
04
0<
0=
0:
b1100 #
b1100 B
0&
b1100 %
b1100 F
0D
0C
0)
b1000 (
b1000 .
b1000 +
b0 ,
#146
b1101 !
b1101 A
b1101 #
b1101 B
b1101 %
b1101 F
1)
b1 ,
#147
b1101 #
b1101 B
0)
b1001 (
b1001 .
b1001 +
b0 ,
#148
1>
1/
b1110 !
b1110 A
1:
b1110 #
b1110 B
1C
b1110 %
b1110 F
1)
b1 ,
#149
0$
0"
0=
01
0@
0&
b1110 %
b1110 F
08
0E
0?
00
0>
0/
b1110 !
b1110 A
0;
0:
b1110 #
b1110 B
0C
0)
b1010 (
b1010 .
b1010 +
b0 ,
#150
b1111 !
b1111 A
b1111 #
b1111 B
b1111 %
b1111 F
1)
b1 ,
#151
b1111 #
b1111 B
0)
b1011 (
b1011 .
b1011 +
b0 ,
#152
1$
1"
1=
11
1@
1&
18
1E
1?
10
1;
1>
1/
1D
b0 !
b0 A
1:
b0 #
b0 B
1C
b0 %
b0 F
1)
b1 ,
#153
08
0?
00
0>
0/
b0 !
b0 A
0;
14
0<
0:
b0 #
b0 B
0D
0C
0)
b1100 (
b1100 .
b1100 +
b0 ,
#154
b1 !
b1 A
b1 #
b1 B
b1 %
b1 F
1)
b1 ,
#155
b1 #
b1 B
0)
b1101 (
b1101 .
b1101 +
b0 ,
#156
1>
1/
b10 !
b10 A
1:
b10 #
b10 B
1C
b10 %
b10 F
1)
b1 ,
#157
08
0<
0?
00
0>
0/
b10 !
b10 A
0;
0:
b10 #
b10 B
0C
0)
b1110 (
b1110 .
b1110 +
b0 ,
#158
b11 !
b11 A
b11 #
b11 B
b11 %
b11 F
1)
b1 ,
#159
b11 #
b11 B
0)
b1111 (
b1111 .
b1111 +
b0 ,
#160
18
1<
1?
10
1;
1>
1/
1D
b100 !
b100 A
1:
b100 #
b100 B
1C
b100 %
b100 F
1)
b1 ,
#161
01
0@
08
0E
0?
0"
00
0$
0>
0/
0;
04
0<
0=
b101 !
b101 A
0:
b101 #
b101 B
0&
0D
0C
b101 %
b101 F
0)
b0 (
b0 .
b101 '
b101 -
b101 *
b0 +
b0 ,
#162
1/
1>
b110 !
b110 A
16
b110 #
b110 B
1C
b110 %
b110 F
1)
b1 ,
#163
12
06
b110 #
b110 B
0)
b1 (
b1 .
b1 +
b0 ,
#164
b111 !
b111 A
16
1:
b111 #
b111 B
b111 %
b111 F
1)
b1 ,
#165
01
0@
b111 %
b111 F
08
0E
0/
0?
00
0>
b111 !
b111 A
02
0;
06
0:
b111 #
b111 B
0C
0)
b10 (
b10 .
b10 +
b0 ,
#166
11
1@
1E
18
10
1?
1;
1/
1>
1D
b1000 !
b1000 A
16
b1000 #
b1000 B
1C
b1000 %
b1000 F
1)
b1 ,
#167
12
06
b1000 #
b1000 B
0)
b11 (
b11 .
b11 +
b0 ,
#168
b1001 !
b1001 A
16
1:
b1001 #
b1001 B
b1001 %
b1001 F
1)
b1 ,
#169
08
0/
0?
00
0>
b1001 !
b1001 A
02
0;
14
0<
06
0:
b1001 #
b1001 B
0D
0C
0)
b100 (
b100 .
b100 +
b0 ,
#170
1/
1>
b1010 !
b1010 A
16
b1010 #
b1010 B
1C
b1010 %
b1010 F
1)
b1 ,
#171
12
06
b1010 #
b1010 B
0)
b101 (
b101 .
b101 +
b0 ,
#172
b1011 !
b1011 A
16
1:
b1011 #
b1011 B
b1011 %
b1011 F
1)
b1 ,
#173
08
0<
0/
0?
00
0>
b1011 !
b1011 A
02
0;
06
0:
b1011 #
b1011 B
0C
0)
b110 (
b110 .
b110 +
b0 ,
#174
18
1<
10
1?
1;
1/
1>
1D
b1100 !
b1100 A
16
b1100 #
b1100 B
1C
b1100 %
b1100 F
1)
b1 ,
#175
12
06
b1100 #
b1100 B
0)
b111 (
b111 .
b111 +
b0 ,
#176
b1101 !
b1101 A
16
1:
b1101 #
b1101 B
b1101 %
b1101 F
1)
b1 ,
#177
01
0@
08
0E
0/
0?
0"
00
0$
0>
b1101 !
b1101 A
02
0;
04
0<
0=
06
0:
b1101 #
b1101 B
0&
b1101 %
b1101 F
0D
0C
0)
b1000 (
b1000 .
b1000 +
b0 ,
#178
1/
1>
b1110 !
b1110 A
16
b1110 #
b1110 B
1C
b1110 %
b1110 F
1)
b1 ,
#179
12
06
b1110 #
b1110 B
0)
b1001 (
b1001 .
b1001 +
b0 ,
#180
b1111 !
b1111 A
16
1:
b1111 #
b1111 B
b1111 %
b1111 F
1)
b1 ,
#181
0$
0"
0=
01
0@
0&
b1111 %
b1111 F
08
0E
0/
0?
00
0>
b1111 !
b1111 A
02
0;
06
0:
b1111 #
b1111 B
0C
0)
b1010 (
b1010 .
b1010 +
b0 ,
#182
1$
1"
11
1=
1&
1@
1E
18
10
1?
1;
1/
1>
1D
b0 !
b0 A
16
b0 #
b0 B
1C
b0 %
b0 F
1)
b1 ,
#183
12
06
b0 #
b0 B
0)
b1011 (
b1011 .
b1011 +
b0 ,
#184
b1 !
b1 A
16
1:
b1 #
b1 B
b1 %
b1 F
1)
b1 ,
#185
08
0/
0?
00
0>
b1 !
b1 A
02
0;
14
0<
06
0:
b1 #
b1 B
0D
0C
0)
b1100 (
b1100 .
b1100 +
b0 ,
#186
1/
1>
b10 !
b10 A
16
b10 #
b10 B
1C
b10 %
b10 F
1)
b1 ,
#187
12
06
b10 #
b10 B
0)
b1101 (
b1101 .
b1101 +
b0 ,
#188
b11 !
b11 A
16
1:
b11 #
b11 B
b11 %
b11 F
1)
b1 ,
#189
08
0<
0/
0?
00
0>
b11 !
b11 A
02
0;
06
0:
b11 #
b11 B
0C
0)
b1110 (
b1110 .
b1110 +
b0 ,
#190
18
1<
10
1?
1;
1/
1>
1D
b100 !
b100 A
16
b100 #
b100 B
1C
b100 %
b100 F
1)
b1 ,
