Homework3/wallace_tree_multiplier/rtl/full_adder.v
module full_adder(
	input	wire	a,
	input 	wire	b,
	input 	wire	cin,
	output	wire	sum,
	output	wire	carry
);
	wire	s1, c1, c2;

	xor(s1, a, b);
	xor(sum, s1, cin);
	and(c1, a, b);
	and(c2, s1, cin);
	or(carry, c1, c2);

endmodule

Homework3/wallace_tree_multiplier/rtl/half_adder.v
module half_adder(
	input	wire	a,
	input 	wire	b,
	output	wire	sum,
	output	wire	carry
);

	xor(sum, a, b);
	and(carry, a, b);

endmodule

Homework3/wallace_tree_multiplier/rtl/wallace_tree_multiplier.v
module wallace_tree_multiplier(
	input	wire	[3:0]	a,
	input	wire	[3:0]	b,
	output	wire	[7:0]	gate_out,
	output	wire	[7:0]	data_out,
	output	reg	[7:0]	behav_out
);
	wire	[3:0]	d0, d1, d2, d3;
	reg	[3:0]	b0, b1, b2, b3;
	wire	[3:0]	g0, g1, g2, g3;
	wire	[6:0]	carry_row, sum_row;
	wire		c_final;
	wire		s1, s2, s3, s4, s5, s6, s7, s8, s9, s10, s11, s12, s13, s14, s15, s16, s17, s21;
	wire		c1, c2, c3, c4, c5, c6, c7, c8, c9, c10, c11, c12, c13, c14, c15, c16, c17, c21;

	//structural
	and(g0[0], a[0], b[0]);
	and(g0[1], a[1], b[0]);
	and(g0[2], a[2], b[0]);
	and(g0[3], a[3], b[0]);

	and(g1[0], a[0], b[1]);
	and(g1[1], a[1], b[1]);
	and(g1[2], a[2], b[1]);
	and(g1[3], a[3], b[1]);

	and(g2[0], a[0], b[2]);
	and(g2[1], a[1], b[2]);
	and(g2[2], a[2], b[2]);
	and(g2[3], a[3], b[2]);

	and(g3[0], a[0], b[3]);
	and(g3[1], a[1], b[3]);
	and(g3[2], a[2], b[3]);
	and(g3[3], a[3], b[3]);
	
	half_adder ha1_1(.a(g0[1]), .b(g1[0]), .sum(gate_out[1]), .carry(c11));
	
	half_adder ha2_1(.a(g0[2]), .b(g1[1]), .sum(s0), .carry(c0));
	full_adder fa2_2(.a(s0), .b(c11), .cin(g2[0]), .sum(gate_out[2]), .carry(c12));

	full_adder fa3_1(.a(g0[3]), .b(g1[2]), .cin(g2[1]), .sum(s1), .carry(c1));
	half_adder ha3_1(.a(s1), .b(g3[0]), .sum(s6), .carry(c6));
	full_adder fa3_2(.a(s6), .b(c0), .cin(c12), .sum(gate_out[3]), .carry(c13));

	full_adder fa4_1(.a(g3[1]), .b(g1[3]), .cin(g2[2]), .sum(s2), .carry(c2));
	full_adder fa4_2(.a(s2), .b(1'b0), .cin(c1), .sum(s7), .carry(c7));
	full_adder fa4_3(.a(s7), .b(c13), .cin(c6), .sum(gate_out[4]), .carry(c14));

	full_adder fa5_1(.a(g3[2]), .b(1'b0), .cin(g2[3]), .sum(s3), .carry(c3));
	full_adder fa5_2(.a(s3), .b(1'b0), .cin(c2), .sum(s8), .carry(c8));
	full_adder fa5_3(.a(s8), .b(c14), .cin(c7), .sum(gate_out[5]), .carry(c15));

	full_adder fa6_1(.a(g3[3]), .b(1'b0), .cin(1'b0), .sum(s4), .carry(c4));
	full_adder fa6_2(.a(s4), .b(1'b0), .cin(c3), .sum(s9), .carry(c9));
	full_adder fa6_3(.a(s9), .b(c15), .cin(c8), .sum(gate_out[6]), .carry(c16));

	full_adder fa7_1(.a(1'b0), .b(1'b0), .cin(1'b0), .sum(s5), .carry(c21));
	full_adder fa7_2(.a(s5), .b(1'b0), .cin(c4), .sum(s10), .carry(c10));
	full_adder fa7_3(.a(s10), .b(c16), .cin(c9), .sum(gate_out[7]), .carry(c17));	
    
	buf(gate_out[0], g0[0]);  

	//dataflow
	assign d0 = a & {4{b[0]}};
	assign d1 = a & {4{b[1]}};
	assign d2 = a & {4{b[2]}};
	assign d3 = a & {4{b[3]}};

	assign data_out = (d0 << 0) + (d1 << 1) + (d2 << 2) + (d3 << 3);

	//behavioral
	always @(*) begin
		b0 = a & {4{b[0]}};
		b1 = a & {4{b[1]}};
		b2 = a & {4{b[2]}};
		b3 = a & {4{b[3]}};
		behav_out = (b0 << 0) + (b1 << 1) + (b2 << 2) + (b3 << 3);
	end
	
endmodule

Homework3/wallace_tree_multiplier/tb/test_bench.v
module test_bench;

	reg	[3:0]	a, b;
	wire	[7:0]	gate_out, data_out, behav_out;
	integer		i, j;

	wallace_tree_multiplier DUT(.*);

	initial begin
		$dumpfile("wave.vcd");
		$dumpvars(0,test_bench);
		$display("===== Test Wallace Tree Multiplier =====");
		$monitor("===== Q = %4b, M = %4b =====", a, b);
		for(i = 0; i < 16; i = i + 1) begin
			for(j = 0; j < 16; j = j + 1) begin
				a = i[3:0];
               			b = j[3:0];
               			#1;
                		check_result(a * b, gate_out, data_out, behav_out);
			end
		end
		$display("===== t=%d Finished Stimulation =====",$time);
		$finish;
	end

	task check_result;
		input	[7:0]	result;
		input	[7:0]	e;
		input	[7:0]	f;
		input	[7:0]	g;

		if(e!=result | f!=result | g!=result) begin
			$display("===== t=%d FAILED, output does not match =====",$time);
			$display("===== t=%d Expected value is %b, Actual gate value is %b, Actual data value is %b, Actual behavioral value is %b =====",$time, result, e, f, g);
		end
		else begin
			$display("===== t=%d PASSED SUCCESSFULLY =====",$time);
		end
	endtask
	
endmodule

Homework3/wallace_tree_multiplier/sim/wave.vcd
$date
	Fri Oct 10 21:09:32 2025
$end
$version
	Icarus Verilog
$end
$timescale
	1s
$end
$scope module test_bench $end
$var wire 8 ! gate_out [7:0] $end
$var wire 8 " data_out [7:0] $end
$var wire 8 # behav_out [7:0] $end
$var reg 4 $ a [3:0] $end
$var reg 4 % b [3:0] $end
$var integer 32 & i [31:0] $end
$var integer 32 ' j [31:0] $end
$scope module DUT $end
$var wire 4 ( a [3:0] $end
$var wire 4 ) b [3:0] $end
$var wire 4 * d0 [3:0] $end
$var wire 4 + d1 [3:0] $end
$var wire 4 , d2 [3:0] $end
$var wire 4 - d3 [3:0] $end
$var wire 1 . s9 $end
$var wire 1 / s8 $end
$var wire 1 0 s7 $end
$var wire 1 1 s6 $end
$var wire 1 2 s5 $end
$var wire 1 3 s4 $end
$var wire 1 4 s3 $end
$var wire 1 5 s2 $end
$var wire 1 6 s10 $end
$var wire 1 7 s1 $end
$var wire 1 8 s0 $end
$var wire 8 9 gate_out [7:0] $end
$var wire 4 : g3 [3:0] $end
$var wire 4 ; g2 [3:0] $end
$var wire 4 < g1 [3:0] $end
$var wire 4 = g0 [3:0] $end
$var wire 8 > data_out [7:0] $end
$var wire 1 ? c9 $end
$var wire 1 @ c8 $end
$var wire 1 A c7 $end
$var wire 1 B c6 $end
$var wire 1 C c4 $end
$var wire 1 D c3 $end
$var wire 1 E c21 $end
$var wire 1 F c2 $end
$var wire 1 G c17 $end
$var wire 1 H c16 $end
$var wire 1 I c15 $end
$var wire 1 J c14 $end
$var wire 1 K c13 $end
$var wire 1 L c12 $end
$var wire 1 M c11 $end
$var wire 1 N c10 $end
$var wire 1 O c1 $end
$var wire 1 P c0 $end
$var reg 4 Q b0 [3:0] $end
$var reg 4 R b1 [3:0] $end
$var reg 4 S b2 [3:0] $end
$var reg 4 T b3 [3:0] $end
$var reg 8 U behav_out [7:0] $end
$scope module fa2_2 $end
$var wire 1 V c1 $end
$var wire 1 W c2 $end
$var wire 1 L carry $end
$var wire 1 X cin $end
$var wire 1 Y s1 $end
$var wire 1 Z sum $end
$var wire 1 M b $end
$var wire 1 8 a $end
$upscope $end
$scope module fa3_1 $end
$var wire 1 [ a $end
$var wire 1 \ b $end
$var wire 1 ] c1 $end
$var wire 1 ^ c2 $end
$var wire 1 O carry $end
$var wire 1 _ cin $end
$var wire 1 ` s1 $end
$var wire 1 7 sum $end
$upscope $end
$scope module fa3_2 $end
$var wire 1 a c1 $end
$var wire 1 b c2 $end
$var wire 1 K carry $end
$var wire 1 L cin $end
$var wire 1 c s1 $end
$var wire 1 d sum $end
$var wire 1 P b $end
$var wire 1 1 a $end
$upscope $end
$scope module fa4_1 $end
$var wire 1 e a $end
$var wire 1 f b $end
$var wire 1 g c1 $end
$var wire 1 h c2 $end
$var wire 1 F carry $end
$var wire 1 i cin $end
$var wire 1 j s1 $end
$var wire 1 5 sum $end
$upscope $end
$scope module fa4_2 $end
$var wire 1 5 a $end
$var wire 1 k b $end
$var wire 1 l c1 $end
$var wire 1 m c2 $end
$var wire 1 A carry $end
$var wire 1 O cin $end
$var wire 1 n s1 $end
$var wire 1 0 sum $end
$upscope $end
$scope module fa4_3 $end
$var wire 1 0 a $end
$var wire 1 K b $end
$var wire 1 o c1 $end
$var wire 1 p c2 $end
$var wire 1 J carry $end
$var wire 1 q s1 $end
$var wire 1 r sum $end
$var wire 1 B cin $end
$upscope $end
$scope module fa5_1 $end
$var wire 1 s a $end
$var wire 1 t b $end
$var wire 1 u c1 $end
$var wire 1 v c2 $end
$var wire 1 D carry $end
$var wire 1 w cin $end
$var wire 1 x s1 $end
$var wire 1 4 sum $end
$upscope $end
$scope module fa5_2 $end
$var wire 1 4 a $end
$var wire 1 y b $end
$var wire 1 z c1 $end
$var wire 1 { c2 $end
$var wire 1 @ carry $end
$var wire 1 F cin $end
$var wire 1 | s1 $end
$var wire 1 / sum $end
$upscope $end
$scope module fa5_3 $end
$var wire 1 / a $end
$var wire 1 J b $end
$var wire 1 } c1 $end
$var wire 1 ~ c2 $end
$var wire 1 I carry $end
$var wire 1 A cin $end
$var wire 1 !" s1 $end
$var wire 1 "" sum $end
$upscope $end
$scope module fa6_1 $end
$var wire 1 #" a $end
$var wire 1 $" b $end
$var wire 1 %" c1 $end
$var wire 1 &" c2 $end
$var wire 1 C carry $end
$var wire 1 '" cin $end
$var wire 1 (" s1 $end
$var wire 1 3 sum $end
$upscope $end
$scope module fa6_2 $end
$var wire 1 3 a $end
$var wire 1 )" b $end
$var wire 1 *" c1 $end
$var wire 1 +" c2 $end
$var wire 1 ? carry $end
$var wire 1 D cin $end
$var wire 1 ," s1 $end
$var wire 1 . sum $end
$upscope $end
$scope module fa6_3 $end
$var wire 1 . a $end
$var wire 1 I b $end
$var wire 1 -" c1 $end
$var wire 1 ." c2 $end
$var wire 1 H carry $end
$var wire 1 @ cin $end
$var wire 1 /" s1 $end
$var wire 1 0" sum $end
$upscope $end
$scope module fa7_1 $end
$var wire 1 1" a $end
$var wire 1 2" b $end
$var wire 1 3" c1 $end
$var wire 1 4" c2 $end
$var wire 1 E carry $end
$var wire 1 5" cin $end
$var wire 1 6" s1 $end
$var wire 1 2 sum $end
$upscope $end
$scope module fa7_2 $end
$var wire 1 2 a $end
$var wire 1 7" b $end
$var wire 1 8" c1 $end
$var wire 1 9" c2 $end
$var wire 1 N carry $end
$var wire 1 C cin $end
$var wire 1 :" s1 $end
$var wire 1 6 sum $end
$upscope $end
$scope module fa7_3 $end
$var wire 1 6 a $end
$var wire 1 H b $end
$var wire 1 ;" c1 $end
$var wire 1 <" c2 $end
$var wire 1 G carry $end
$var wire 1 ? cin $end
$var wire 1 =" s1 $end
$var wire 1 >" sum $end
$upscope $end
$scope module ha1_1 $end
$var wire 1 ?" a $end
$var wire 1 @" b $end
$var wire 1 M carry $end
$var wire 1 A" sum $end
$upscope $end
$scope module ha2_1 $end
$var wire 1 B" a $end
$var wire 1 C" b $end
$var wire 1 P carry $end
$var wire 1 8 sum $end
$upscope $end
$scope module ha3_1 $end
$var wire 1 7 a $end
$var wire 1 D" b $end
$var wire 1 B carry $end
$var wire 1 1 sum $end
$upscope $end
$upscope $end
$scope task check_result $end
$var reg 8 E" e [7:0] $end
$var reg 8 F" f [7:0] $end
$var reg 8 G" g [7:0] $end
$var reg 8 H" result [7:0] $end
$upscope $end
$upscope $end
$enddefinitions $end
#0
$dumpvars
bx H"
bx G"
bx F"
bx E"
0D"
0C"
0B"
0A"
0@"
0?"
0>"
0="
0<"
0;"
0:"
09"
08"
07"
06"
05"
04"
03"
02"
01"
00"
0/"
0."
0-"
0,"
0+"
0*"
0)"
0("
0'"
0&"
0%"
0$"
0#"
0""
0!"
0~
0}
0|
0{
0z
0y
0x
0w
0v
0u
0t
0s
0r
0q
0p
0o
0n
0m
0l
0k
0j
0i
0h
0g
0f
0e
0d
0c
0b
0a
0`
0_
0^
0]
0\
0[
0Z
0Y
0X
0W
0V
b0 U
b0 T
b0 S
b0 R
b0 Q
0P
0O
0N
0M
0L
0K
0J
0I
0H
0G
0F
0E
0D
0C
0B
0A
0@
0?
b0 >
b0 =
b0 <
b0 ;
b0 :
b0 9
08
07
06
05
04
03
02
01
00
0/
0.
b0 -
b0 ,
b0 +
b0 *
b0 )
b0 (
b0 '
b0 &
b0 %
b0 $
b0 #
b0 "
b0 !
$end
#1
b1 %
b1 )
b1 '
b0 G"
b0 F"
b0 E"
b0 H"
#2
b10 %
b10 )
b10 '
#3
b11 %
b11 )
b11 '
#4
b100 %
b100 )
b100 '
#5
b101 %
b101 )
b101 '
#6
b110 %
b110 )
b110 '
#7
b111 %
b111 )
b111 '
#8
b1000 %
b1000 )
b1000 '
#9
b1001 %
b1001 )
b1001 '
#10
b1010 %
b1010 )
b1010 '
#11
b1011 %
b1011 )
b1011 '
#12
b1100 %
b1100 )
b1100 '
#13
b1101 %
b1101 )
b1101 '
#14
b1110 %
b1110 )
b1110 '
#15
b1111 %
b1111 )
b1111 '
#16
b0 "
b0 >
b0 *
b0 +
b0 ,
b0 -
b0 %
b0 )
b1 $
b1 (
b1 &
b0 '
#17
b1 !
b1 9
b1 =
b1 "
b1 >
b1 *
b1 #
b1 U
b1 Q
b1 %
b1 )
b1 '
#18
b10 !
b10 9
1A"
1@"
b0 =
b1 <
b10 "
b10 >
b0 *
b1 +
b10 #
b10 U
b1 R
b0 Q
b10 %
b10 )
b10 '
b1 G"
b1 F"
b1 E"
b1 H"
#19
b11 !
b11 9
b1 =
b11 "
b11 >
b1 *
b11 #
b11 U
b1 Q
b11 %
b11 )
b11 '
b10 G"
b10 F"
b10 E"
b10 H"
#20
0A"
b100 !
b100 9
1Z
0@"
1X
b0 =
b0 <
b1 ;
b100 "
b100 >
b0 *
b0 +
b1 ,
b100 #
b100 U
b1 S
b0 R
b0 Q
b100 %
b100 )
b100 '
b11 G"
b11 F"
b11 E"
b11 H"
#21
b101 !
b101 9
b1 =
b101 "
b101 >
b1 *
b101 #
b101 U
b1 Q
b101 %
b101 )
b101 '
b100 G"
b100 F"
b100 E"
b100 H"
#22
b110 !
b110 9
1A"
1@"
b0 =
b1 <
b110 "
b110 >
b0 *
b1 +
b110 #
b110 U
b1 R
b0 Q
b110 %
b110 )
b110 '
b101 G"
b101 F"
b101 E"
b101 H"
#23
b111 !
b111 9
b1 =
b111 "
b111 >
b1 *
b111 #
b111 U
b1 Q
b111 %
b111 )
b111 '
b110 G"
b110 F"
b110 E"
b110 H"
#24
1d
1c
0A"
b1000 !
b1000 9
0Z
11
0@"
0X
1D"
b0 =
b0 <
b0 ;
b1 :
b1000 "
b1000 >
b0 *
b0 +
b0 ,
b1 -
b1000 #
b1000 U
b1 T
b0 S
b0 R
b0 Q
b1000 %
b1000 )
b1000 '
b111 G"
b111 F"
b111 E"
b111 H"
#25
b1001 !
b1001 9
b1 =
b1001 "
b1001 >
b1 *
b1001 #
b1001 U
b1 Q
b1001 %
b1001 )
b1001 '
b1000 G"
b1000 F"
b1000 E"
b1000 H"
#26
b1010 !
b1010 9
1A"
1@"
b0 =
b1 <
b1010 "
b1010 >
b0 *
b1 +
b1010 #
b1010 U
b1 R
b0 Q
b1010 %
b1010 )
b1010 '
b1001 G"
b1001 F"
b1001 E"
b1001 H"
#27
b1011 !
b1011 9
b1 =
b1011 "
b1011 >
b1 *
b1011 #
b1011 U
b1 Q
b1011 %
b1011 )
b1011 '
b1010 G"
b1010 F"
b1010 E"
b1010 H"
#28
0A"
b1100 !
b1100 9
1Z
0@"
1X
b0 =
b0 <
b1 ;
b1100 "
b1100 >
b0 *
b0 +
b1 ,
b1100 #
b1100 U
b1 S
b0 R
b0 Q
b1100 %
b1100 )
b1100 '
b1011 G"
b1011 F"
b1011 E"
b1011 H"
#29
b1101 !
b1101 9
b1 =
b1101 "
b1101 >
b1 *
b1101 #
b1101 U
b1 Q
b1101 %
b1101 )
b1101 '
b1100 G"
b1100 F"
b1100 E"
b1100 H"
#30
b1110 !
b1110 9
1A"
1@"
b0 =
b1 <
b1110 "
b1110 >
b0 *
b1 +
b1110 #
b1110 U
b1 R
b0 Q
b1110 %
b1110 )
b1110 '
b1101 G"
b1101 F"
b1101 E"
b1101 H"
#31
b1111 !
b1111 9
b1 =
b1111 "
b1111 >
b1 *
b1111 #
b1111 U
b1 Q
b1111 %
b1111 )
b1111 '
b1110 G"
b1110 F"
b1110 E"
b1110 H"
#32
0d
0c
0A"
b0 !
b0 9
0Z
01
0@"
0X
0D"
b0 =
b0 <
b0 ;
b0 :
b0 "
b0 >
b0 *
b0 +
b0 ,
b0 -
b0 #
b0 U
b0 T
b0 S
b0 R
b0 Q
b0 %
b0 )
b10 $
b10 (
b10 &
b0 '
b1111 G"
b1111 F"
b1111 E"
b1111 H"
#33
b10 !
b10 9
1A"
1?"
b10 =
b10 "
b10 >
b10 *
b10 #
b10 U
b10 Q
b1 %
b1 )
b1 '
b0 G"
b0 F"
b0 E"
b0 H"
#34
1Z
1Y
b100 !
b100 9
0A"
18
0?"
1C"
b0 =
b10 <
b100 "
b100 >
b0 *
b10 +
b100 #
b100 U
b10 R
b0 Q
b10 %
b10 )
b10 '
b10 G"
b10 F"
b10 E"
b10 H"
#35
b110 !
b110 9
1A"
1?"
b10 =
b110 "
b110 >
b10 *
b110 #
b110 U
b10 Q
b11 %
b11 )
b11 '
b100 G"
b100 F"
b100 E"
b100 H"
#36
1d
0Z
1c
0Y
11
b1000 !
b1000 9
0A"
08
17
0?"
0C"
1_
b0 =
b0 <
b10 ;
b1000 "
b1000 >
b0 *
b0 +
b10 ,
b1000 #
b1000 U
b10 S
b0 R
b0 Q
b100 %
b100 )
b100 '
b110 G"
b110 F"
b110 E"
b110 H"
#37
b1010 !
b1010 9
1A"
1?"
b10 =
b1010 "
b1010 >
b10 *
b1010 #
b1010 U
b10 Q
b101 %
b101 )
b101 '
b1000 G"
b1000 F"
b1000 E"
b1000 H"
#38
1Z
1Y
b1100 !
b1100 9
0A"
18
0?"
1C"
b0 =
b10 <
b1100 "
b1100 >
b0 *
b10 +
b1100 #
b1100 U
b10 R
b0 Q
b110 %
b110 )
b110 '
b1010 G"
b1010 F"
b1010 E"
b1010 H"
#39
b1110 !
b1110 9
1A"
1?"
b10 =
b1110 "
b1110 >
b10 *
b1110 #
b1110 U
b10 Q
b111 %
b111 )
b111 '
b1100 G"
b1100 F"
b1100 E"
b1100 H"
#40
1r
1q
0d
10
0Z
0c
1n
0Y
01
15
b10000 !
b10000 9
0A"
08
07
1j
0?"
0C"
0_
1e
b0 =
b0 <
b0 ;
b10 :
b10000 "
b10000 >
b0 *
b0 +
b0 ,
b10 -
b10000 #
b10000 U
b10 T
b0 S
b0 R
b0 Q
b1000 %
b1000 )
b1000 '
b1110 G"
b1110 F"
b1110 E"
b1110 H"
#41
b10010 !
b10010 9
1A"
1?"
b10 =
b10010 "
b10010 >
b10 *
b10010 #
b10010 U
b10 Q
b1001 %
b1001 )
b1001 '
b10000 G"
b10000 F"
b10000 E"
b10000 H"
#42
1Z
1Y
b10100 !
b10100 9
0A"
18
0?"
1C"
b0 =
b10 <
b10100 "
b10100 >
b0 *
b10 +
b10100 #
b10100 U
b10 R
b0 Q
b1010 %
b1010 )
b1010 '
b10010 G"
b10010 F"
b10010 E"
b10010 H"
#43
b10110 !
b10110 9
1A"
1?"
b10 =
b10110 "
b10110 >
b10 *
b10110 #
b10110 U
b10 Q
b1011 %
b1011 )
b1011 '
b10100 G"
b10100 F"
b10100 E"
b10100 H"
#44
1d
0Z
1c
0Y
11
b11000 !
b11000 9
0A"
08
17
0?"
0C"
1_
b0 =
b0 <
b10 ;
b11000 "
b11000 >
b0 *
b0 +
b10 ,
b11000 #
b11000 U
b10 S
b0 R
b0 Q
b1100 %
b1100 )
b1100 '
b10110 G"
b10110 F"
b10110 E"
b10110 H"
#45
b11010 !
b11010 9
1A"
1?"
b10 =
b11010 "
b11010 >
b10 *
b11010 #
b11010 U
b10 Q
b1101 %
b1101 )
b1101 '
b11000 G"
b11000 F"
b11000 E"
b11000 H"
#46
1Z
1Y
b11100 !
b11100 9
0A"
18
0?"
1C"
b0 =
b10 <
b11100 "
b11100 >
b0 *
b10 +
b11100 #
b11100 U
b10 R
b0 Q
b1110 %
b1110 )
b1110 '
b11010 G"
b11010 F"
b11010 E"
b11010 H"
#47
b11110 !
b11110 9
1A"
1?"
b10 =
b11110 "
b11110 >
b10 *
b11110 #
b11110 U
b10 Q
b1111 %
b1111 )
b1111 '
b11100 G"
b11100 F"
b11100 E"
b11100 H"
#48
0r
0q
0d
00
0Z
0c
0n
0Y
01
05
b0 !
b0 9
0A"
08
07
0j
0?"
0C"
0_
0e
b0 =
b0 <
b0 ;
b0 :
b0 "
b0 >
b0 *
b0 +
b0 ,
b0 -
b0 #
b0 U
b0 T
b0 S
b0 R
b0 Q
b0 %
b0 )
b11 $
b11 (
b11 &
b0 '
b11110 G"
b11110 F"
b11110 E"
b11110 H"
#49
b11 !
b11 9
1A"
1?"
b11 =
b11 "
b11 >
b11 *
b11 #
b11 U
b11 Q
b1 %
b1 )
b1 '
b0 G"
b0 F"
b0 E"
b0 H"
#50
1Z
1Y
b110 !
b110 9
18
0?"
1@"
1C"
b0 =
b11 <
b110 "
b110 >
b0 *
b11 +
b110 #
b110 U
b11 R
b0 Q
b10 %
b10 )
b10 '
b11 G"
b11 F"
b11 E"
b11 H"
#51
1d
1L
0Z
1V
0Y
b1001 !
b1001 9
0A"
1M
1?"
b11 =
b1001 "
b1001 >
b11 *
b1001 #
b1001 U
b11 Q
b11 %
b11 )
b11 '
b110 G"
b110 F"
b110 E"
b110 H"
#52
0L
1c
0V
11
0M
08
b1100 !
b1100 9
1Z
17
0?"
0@"
0C"
1X
1_
b0 =
b0 <
b11 ;
b1100 "
b1100 >
b0 *
b0 +
b11 ,
b1100 #
b1100 U
b11 S
b0 R
b0 Q
b100 %
b100 )
b100 '
b1001 G"
b1001 F"
b1001 E"
b1001 H"
#53
b1111 !
b1111 9
1A"
1?"
b11 =
b1111 "
b1111 >
b11 *
b1111 #
b1111 U
b11 Q
b101 %
b101 )
b101 '
b1100 G"
b1100 F"
b1100 E"
b1100 H"
#54
1r
1q
1K
0d
1b
1L
0Z
1W
1Y
b10010 !
b10010 9
18
0?"
1@"
1C"
b0 =
b11 <
b10010 "
b10010 >
b0 *
b11 +
b10010 #
b10010 U
b11 R
b0 Q
b110 %
b110 )
b110 '
b1111 G"
b1111 F"
b1111 E"
b1111 H"
#55
1Z
0W
1V
0Y
b10101 !
b10101 9
0A"
1M
1?"
b11 =
b10101 "
b10101 >
b11 *
b10101 #
b10101 U
b11 Q
b111 %
b111 )
b111 '
b10010 G"
b10010 F"
b10010 E"
b10010 H"
#56
0""
0K
0!"
10
0L
1d
0b
0J
1n
0V
1c
0p
1r
15
0M
08
b11000 !
b11000 9
0Z
07
11
0B
1j
0?"
0@"
0C"
0X
0_
1D"
1e
b0 =
b0 <
b0 ;
b11 :
b11000 "
b11000 >
b0 *
b0 +
b0 ,
b11 -
b11000 #
b11000 U
b11 T
b0 S
b0 R
b0 Q
b1000 %
b1000 )
b1000 '
b10101 G"
b10101 F"
b10101 E"
b10101 H"
#57
b11011 !
b11011 9
1A"
1?"
b11 =
b11011 "
b11011 >
b11 *
b11011 #
b11011 U
b11 Q
b1001 %
b1001 )
b1001 '
b11000 G"
b11000 F"
b11000 E"
b11000 H"
#58
1Z
1Y
b11110 !
b11110 9
18
0?"
1@"
1C"
b0 =
b11 <
b11110 "
b11110 >
b0 *
b11 +
b11110 #
b11110 U
b11 R
b0 Q
b1010 %
b1010 )
b1010 '
b11011 G"
b11011 F"
b11011 E"
b11011 H"
#59
1""
1!"
0r
1J
0q
1o
1K
0d
1b
1L
0Z
1V
0Y
b100001 !
b100001 9
0A"
1M
1?"
b11 =
b100001 "
b100001 >
b11 *
b100001 #
b100001 U
b11 Q
b1011 %
b1011 )
b1011 '
b11110 G"
b11110 F"
b11110 E"
b11110 H"
#60
1""
1!"
1p
1J
1q
0o
0K
0b
0L
0c
0r
0V
01
1B
0M
08
b100100 !
b100100 9
1Z
17
0?"
0@"
0C"
1X
1_
b0 =
b0 <
b11 ;
b100100 "
b100100 >
b0 *
b0 +
b11 ,
b100100 #
b100100 U
b11 S
b0 R
b0 Q
b1100 %
b1100 )
b1100 '
b100001 G"
b100001 F"
b100001 E"
b100001 H"
#61
b100111 !
b100111 9
1A"
1?"
b11 =
b100111 "
b100111 >
b11 *
b100111 #
b100111 U
b11 Q
b1101 %
b1101 )
b1101 '
b100100 G"
b100100 F"
b100100 E"
b100100 H"
#62
1d
1L
0Z
1W
1Y
b101010 !
b101010 9
18
0?"
1@"
1C"
b0 =
b11 <
b101010 "
b101010 >
b0 *
b11 +
b101010 #
b101010 U
b11 R
b0 Q
b1110 %
b1110 )
b1110 '
b100111 G"
b100111 F"
b100111 E"
b100111 H"
#63
1Z
0W
1V
0Y
b101101 !
b101101 9
0A"
1M
1?"
b11 =
b101101 "
b101101 >
b11 *
b101101 #
b101101 U
b11 Q
b1111 %
b1111 )
b1111 '
b101010 G"
b101010 F"
b101010 E"
b101010 H"
#64
0q
0""
0K
0!"
00
0L
0d
0b
0J
0n
0V
0c
0p
0r
05
0M
08
b0 !
b0 9
0Z
07
01
0B
0j
0?"
0@"
0C"
0X
0_
0D"
0e
b0 =
b0 <
b0 ;
b0 :
b0 "
b0 >
b0 *
b0 +
b0 ,
b0 -
b0 #
b0 U
b0 T
b0 S
b0 R
b0 Q
b0 %
b0 )
b100 $
b100 (
b100 &
b0 '
b101101 G"
b101101 F"
b101101 E"
b101101 H"
#65
b100 !
b100 9
1Z
1Y
18
1B"
b100 =
b100 "
b100 >
b100 *
b100 #
b100 U
b100 Q
b1 %
b1 )
b1 '
b0 G"
b0 F"
b0 E"
b0 H"
#66
1d
1c
b1000 !
b1000 9
0Z
11
0Y
17
08
1`
0B"
1\
b0 =
b100 <
b1000 "
b1000 >
b0 *
b100 +
b1000 #
b1000 U
b100 R
b0 Q
b10 %
b10 )
b10 '
b100 G"
b100 F"
b100 E"
b100 H"
#67
b1100 !
b1100 9
1Z
1Y
18
1B"
b100 =
b1100 "
b1100 >
b100 *
b1100 #
b1100 U
b100 Q
b11 %
b11 )
b11 '
b1000 G"
b1000 F"
b1000 E"
b1000 H"
#68
0d
1r
0c
1q
b10000 !
b10000 9
0Z
01
10
0Y
07
1n
08
0`
15
0B"
0\
1i
b0 =
b0 <
b100 ;
b10000 "
b10000 >
b0 *
b0 +
b100 ,
b10000 #
b10000 U
b100 S
b0 R
b0 Q
b100 %
b100 )
b100 '
b1100 G"
b1100 F"
b1100 E"
b1100 H"
#69
b10100 !
b10100 9
1Z
1Y
18
1B"
b100 =
b10100 "
b10100 >
b100 *
b10100 #
b10100 U
b100 Q
b101 %
b101 )
b101 '
b10000 G"
b10000 F"
b10000 E"
b10000 H"
#70
1d
1c
b11000 !
b11000 9
0Z
11
0Y
17
08
1`
0B"
1\
b0 =
b100 <
b11000 "
b11000 >
b0 *
b100 +
b11000 #
b11000 U
b100 R
b0 Q
b110 %
b110 )
b110 '
b10100 G"
b10100 F"
b10100 E"
b10100 H"
#71
b11100 !
b11100 9
1Z
1Y
18
1B"
b100 =
b11100 "
b11100 >
b100 *
b11100 #
b11100 U
b100 Q
b111 %
b111 )
b111 '
b11000 G"
b11000 F"
b11000 E"
b11000 H"
#72
1""
0d
0r
1!"
0c
0q
1/
b100000 !
b100000 9
0Z
01
00
1|
0Y
07
0n
14
08
0`
05
1x
0B"
0\
0i
1s
b0 =
b0 <
b0 ;
b100 :
b100000 "
b100000 >
b0 *
b0 +
b0 ,
b100 -
b100000 #
b100000 U
b100 T
b0 S
b0 R
b0 Q
b1000 %
b1000 )
b1000 '
b11100 G"
b11100 F"
b11100 E"
b11100 H"
#73
b100100 !
b100100 9
1Z
1Y
18
1B"
b100 =
b100100 "
b100100 >
b100 *
b100100 #
b100100 U
b100 Q
b1001 %
b1001 )
b1001 '
b100000 G"
b100000 F"
b100000 E"
b100000 H"
#74
1d
1c
b101000 !
b101000 9
0Z
11
0Y
17
08
1`
0B"
1\
b0 =
b100 <
b101000 "
b101000 >
b0 *
b100 +
b101000 #
b101000 U
b100 R
b0 Q
b1010 %
b1010 )
b1010 '
b100100 G"
b100100 F"
b100100 E"
b100100 H"
#75
b101100 !
b101100 9
1Z
1Y
18
1B"
b100 =
b101100 "
b101100 >
b100 *
b101100 #
b101100 U
b100 Q
b1011 %
b1011 )
b1011 '
b101000 G"
b101000 F"
b101000 E"
b101000 H"
#76
0d
1r
0c
1q
b110000 !
b110000 9
0Z
01
10
0Y
07
1n
08
0`
15
0B"
0\
1i
b0 =
b0 <
b100 ;
b110000 "
b110000 >
b0 *
b0 +
b100 ,
b110000 #
b110000 U
b100 S
b0 R
b0 Q
b1100 %
b1100 )
b1100 '
b101100 G"
b101100 F"
b101100 E"
b101100 H"
#77
b110100 !
b110100 9
1Z
1Y
18
1B"
b100 =
b110100 "
b110100 >
b100 *
b110100 #
b110100 U
b100 Q
b1101 %
b1101 )
b1101 '
b110000 G"
b110000 F"
b110000 E"
b110000 H"
#78
1d
1c
b111000 !
b111000 9
0Z
11
0Y
17
08
1`
0B"
1\
b0 =
b100 <
b111000 "
b111000 >
b0 *
b100 +
b111000 #
b111000 U
b100 R
b0 Q
b1110 %
b1110 )
b1110 '
b110100 G"
b110100 F"
b110100 E"
b110100 H"
