Homework2/parity_generator/rtl/parity_generator.v
module parity_generator(
	input	wire	[3:0]	a,
	output	wire	[4:0]	gate_out,
	output	wire		gate_parity,
	output	wire	[4:0]	data_out,
	output	wire		data_parity,
	output	reg	[4:0]	behav_out,
	output	reg		behav_parity
);

	integer	i, sum;
	wire	gate_parity_1;

	// -----------------
	// Structural parity (XOR chain)
	xor(gate_parity_1, a[0], a[1], a[2], a[3]);
	not(gate_parity, gate_parity_1);

	buf(gate_out[4], a[3]);
	buf(gate_out[3], a[2]);
	buf(gate_out[2], a[1]);
	buf(gate_out[1], a[0]);
	buf(gate_out[0], gate_parity);


	// Dataflow style
	assign data_parity	= ~(a[0] ^ a[1] ^ a[2] ^ a[3]);
	assign data_out		= {a, data_parity};

	// Behavioural style
	always @(*) begin
		sum = 0;
		for(i=0; i<4; i=i+1) begin
			sum = sum + a[i];
		end
		behav_parity = (sum % 2) == 0 ? 1 : 0;
		behav_out = {a, behav_parity};
	end

endmodule

Homework2/parity_generator/tb/test_bench19.v
module test_bench19;

	reg	[3:0]	a;
	wire	[4:0]	gate_out, data_out, behav_out;
	wire		gate_parity, data_parity, behav_parity;

	parity_generator DUT(.*);

	initial begin
		$dumpfile("wave19.vcd");
		$dumpvars(0,test_bench19);
		$display("===== Test Parity Generator =====");
		$monitor("===== A = %b =====", a);
		a=4'b0000;
		#1;	
		check_result(5'b00001, gate_out, data_out, behav_out);
		check_parity(1, gate_parity, data_parity, behav_parity);

		a=4'b0001;
		#1;	
		check_result(5'b00010, gate_out, data_out, behav_out);
		check_parity(0, gate_parity, data_parity, behav_parity);

		a=4'b0010;
		#1;	
		check_result(5'b00100, gate_out, data_out, behav_out);
		check_parity(0, gate_parity, data_parity, behav_parity);

		a=4'b0100;
		#1;	
		check_result(5'b01000, gate_out, data_out, behav_out);
		check_parity(0, gate_parity, data_parity, behav_parity);

		a=4'b1000;
		#1;	
		check_result(5'b10000, gate_out, data_out, behav_out);
		check_parity(0, gate_parity, data_parity, behav_parity);

		a=4'b0011;
		#1;	
		check_result(5'b00111, gate_out, data_out, behav_out);
		check_parity(1, gate_parity, data_parity, behav_parity);

		a=4'b0111;
		#1;	
		check_result(5'b01110, gate_out, data_out, behav_out);
		check_parity(0, gate_parity, data_parity, behav_parity);

		a=4'b0101;
		#1;	
		check_result(5'b01011, gate_out, data_out, behav_out);
		check_parity(1, gate_parity, data_parity, behav_parity);	

		a=4'b1101;
		#1;	
		check_result(5'b11010, gate_out, data_out, behav_out);
		check_parity(0, gate_parity, data_parity, behav_parity);

		a=4'b1011;
		#1;	
		check_result(5'b10110, gate_out, data_out, behav_out);
		check_parity(0, gate_parity, data_parity, behav_parity);

		a=4'b1111;
		#1;	
		check_result(5'b11111, gate_out, data_out, behav_out);
		check_parity(1, gate_parity, data_parity, behav_parity);	
		
		#1;
		$finish;		

	end

	task check_result;
		input 	[4:0]	expected_result;
		input	[4:0]	g_out;
		input	[4:0]	d_out;
		input	[4:0]	b_out;
		if(g_out != expected_result || d_out != expected_result || b_out != expected_result) begin
			$display("===== t=%d FAILED, output does not match =====", $time);
			$display("===== t=%d Expected output is %b, Actual gate output is %b, Actual dataflow output is %b, Actual behavioral output is %b =====",$time, expected_result, g_out, d_out, b_out);
		end
		else begin
			$display("===== t=%d PASSED SUCCESSFULLY =====",$time);
		end
	endtask

	task check_parity;
		input	expected_parity;
		input	g_parity;
		input	d_parity;
		input	b_parity;
		if(g_parity != expected_parity || d_parity != expected_parity || b_parity != expected_parity) begin
			$display("===== t=%d FAILED, output does not match =====", $time);
			$display("===== t=%d Expected parity is %b, Actual gate parity is %b, Actual dataflow parity is %b, Actual behavioral parity is %b =====",$time, expected_parity, g_parity, d_parity, b_parity);
		end
		else begin
			$display("===== t=%d PASSED SUCCESSFULLY =====",$time);
		end
	endtask

endmodule

Homework2/parity_generator/sim/wave19.vcd
$date
	Mon Sep 29 15:16:47 2025
$end
$version
	Icarus Verilog
$end
$timescale
	1s
$end
$scope module test_bench19 $end
$var wire 1 ! gate_parity $end
$var wire 5 " gate_out [4:0] $end
$var wire 1 # data_parity $end
$var wire 5 $ data_out [4:0] $end
$var wire 1 % behav_parity $end
$var wire 5 & behav_out [4:0] $end
$var reg 4 ' a [3:0] $end
$scope module DUT $end
$var wire 4 ( a [3:0] $end
$var wire 1 # data_parity $end
$var wire 1 ! gate_parity $end
$var wire 1 ) gate_parity_1 $end
$var wire 5 * gate_out [4:0] $end
$var wire 5 + data_out [4:0] $end
$var reg 5 , behav_out [4:0] $end
$var reg 1 % behav_parity $end
$var integer 32 - i [31:0] $end
$var integer 32 . sum [31:0] $end
$upscope $end
$scope task check_parity $end
$var reg 1 / b_parity $end
$var reg 1 0 d_parity $end
$var reg 1 1 expected_parity $end
$var reg 1 2 g_parity $end
$upscope $end
$scope task check_result $end
$var reg 5 3 b_out [4:0] $end
$var reg 5 4 d_out [4:0] $end
$var reg 5 5 expected_result [4:0] $end
$var reg 5 6 g_out [4:0] $end
$upscope $end
$upscope $end
$enddefinitions $end
#0
$dumpvars
bx 6
bx 5
bx 4
bx 3
x2
x1
x0
x/
b0 .
b100 -
b1 ,
b1 +
b1 *
0)
b0 (
b0 '
b1 &
1%
b1 $
1#
b1 "
1!
$end
#1
0#
0!
1)
b10 "
b10 *
b10 &
b10 ,
0%
b1 .
b100 -
b10 $
b10 +
b1 '
b1 (
1/
10
12
11
b1 3
b1 4
b1 6
b1 5
#2
b100 "
b100 *
b100 &
b100 ,
b100 -
b1 .
b100 $
b100 +
b10 '
b10 (
0/
00
02
01
b10 3
b10 4
b10 6
b10 5
#3
0#
b1000 "
b1000 *
b1000 &
b1000 ,
b100 -
b1 .
b1000 $
b1000 +
b100 '
b100 (
b100 3
b100 4
b100 6
b100 5
#4
0#
b10000 "
b10000 *
b10000 &
b10000 ,
b100 -
b1 .
b10000 $
b10000 +
b1000 '
b1000 (
b1000 3
b1000 4
b1000 6
b1000 5
#5
1!
1#
0)
b111 "
b111 *
b111 &
b111 ,
1%
b100 -
b10 .
b111 $
b111 +
b11 '
b11 (
b10000 3
b10000 4
b10000 6
b10000 5
#6
0#
0!
1)
b1110 "
b1110 *
b1110 &
b1110 ,
0%
b100 -
b11 .
b1110 $
b1110 +
b111 '
b111 (
1/
10
12
11
b111 3
b111 4
b111 6
b111 5
#7
1#
1!
0)
b1011 "
b1011 *
b1011 &
b1011 ,
1%
b100 -
b10 .
b1011 $
b1011 +
b101 '
b101 (
0/
00
02
01
b1110 3
b1110 4
b1110 6
b1110 5
#8
0!
0#
1)
b11010 "
b11010 *
b11010 &
b11010 ,
0%
b100 -
b11 .
b11010 $
b11010 +
b1101 '
b1101 (
1/
10
12
11
b1011 3
b1011 4
b1011 6
b1011 5
#9
0#
b10110 "
b10110 *
b10110 &
b10110 ,
b100 -
b11 .
b10110 $
b10110 +
b1011 '
b1011 (
0/
00
02
01
b11010 3
b11010 4
b11010 6
b11010 5
#10
1#
1!
0)
b11111 "
b11111 *
b11111 &
b11111 ,
1%
b100 -
b100 .
b11111 $
b11111 +
b1111 '
b1111 (
b10110 3
b10110 4
b10110 6
b10110 5
#11
1/
10
12
11
b11111 3
b11111 4
b11111 6
b11111 5
