Homework2/majority_circuit/rtl/majority_circuit.v
module majority_circuit(
	input	wire	a,
	input	wire	b,
	input	wire	c,
	output	wire	gate_out,
	output	wire	data_out,
	output	reg	behav_out
);
	wire	f1, f2, f3;

	//structural
	and(f1, a, b);
	and(f2, a, c);
	and(f3, c, b);
	or(gate_out, f1, f2, f3);

	//dataflow
	assign	data_out = (a & b) | (a & c) | (b & c);

	//behavioural
	always @(*) begin
		behav_out = (a & b) | (a & c) | (b & c);
	end	

endmodule

Homework2/majority_circuit/tb/test_bench16.v
module test_bench16;

    reg 	a, b, c;
    wire  	gate_out, data_out, behav_out;

    majority_circuit DUT(.*);

    initial begin
        $dumpfile("wave16.vcd");
        $dumpvars(0,test_bench16);
        $display("===== Majority Circuit Testbench =====");
	$monitor("===== With A = %b, B = %b, C = %b =====", a, b, c);
        a = 0; b = 0; c = 0; 
        #1;
        check_result(0, gate_out, data_out, behav_out);

	a = 0; b = 0; c = 1; 
        #1;
        check_result(0, gate_out, data_out, behav_out);

	a = 0; b = 1; c = 0; 
        #1;
        check_result(0, gate_out, data_out, behav_out);

	a = 1; b = 0; c = 0; 
        #1;
        check_result(0, gate_out, data_out, behav_out);

	a = 0; b = 1; c = 1; 
        #1;
        check_result(1, gate_out, data_out, behav_out);

	a = 1; b = 0; c = 1; 
        #1;
        check_result(1, gate_out, data_out, behav_out);
	
	a = 1; b = 1; c = 0; 
        #1;
        check_result(1, gate_out, data_out, behav_out);

	a = 1; b = 1; c = 1; 
        #1;
        check_result(1, gate_out, data_out, behav_out);

        $finish;
    end

    // ===== Task for checking result =====
    task check_result;
        input 	expected_result;
        input 	e;    
        input 	f;
        input	g;
    begin
        if(e != expected_result || f != expected_result || g != expected_result) begin
            $display("===== t=%d FAILED, output value does not match =====", $time);
            $display("===== t=%d Expected value is %b, Actual gate_model value is %b, Actual dataflow value is %b, Actual behavioral_model value is %b =====", $time, expected_result, e, f, g);
        end
        else begin
            $display("===== t=%d PASSED SUCCESSFULLY =====", $time);
        end
    end
    endtask

endmodule

Homework2/majority_circuit/sim/wave16.vcd
$date
	Sat Sep 27 14:22:39 2025
$end
$version
	Icarus Verilog
$end
$timescale
	1s
$end
$scope module test_bench16 $end
$var wire 1 ! gate_out $end
$var wire 1 " data_out $end
$var wire 1 # behav_out $end
$var reg 1 $ a $end
$var reg 1 % b $end
$var reg 1 & c $end
$scope module DUT $end
$var wire 1 $ a $end
$var wire 1 % b $end
$var wire 1 & c $end
$var wire 1 " data_out $end
$var wire 1 ' f1 $end
$var wire 1 ( f2 $end
$var wire 1 ) f3 $end
$var wire 1 ! gate_out $end
$var reg 1 # behav_out $end
$upscope $end
$scope task check_result $end
$var reg 1 * e $end
$var reg 1 + expected_result $end
$var reg 1 , f $end
$var reg 1 - g $end
$upscope $end
$upscope $end
$enddefinitions $end
#0
$dumpvars
x-
x,
x+
x*
0)
0(
0'
0&
0%
0$
0#
0"
0!
$end
#1
1&
0-
0,
0*
0+
#2
0&
1%
#3
0%
1$
#4
1!
1"
1)
1#
1&
1%
0$
#5
0)
1(
0%
1$
1-
1,
1*
1+
#6
0(
1'
0&
1%
#7
1(
1)
1&
